{"v":"5.8.1","fr":30,"ip":0,"op":241,"w":800,"h":800,"nm":"Miss Suit Timeremap","ddd":0,"assets":[],"layers":[{"ddd":0,"ind":1,"ty":3,"nm":"Global Control","sr":1,"ks":{"o":{"a":0,"k":0,"ix":11},"r":{"a":0,"k":0,"ix":10},"p":{"a":1,"k":[{"i":{"x":0.833,"y":0.833},"o":{"x":0.167,"y":0.167},"t":0,"s":[-157,474.5,0],"to":[60.083,-0.75,0],"ti":[-60.083,0.75,0]},{"t":41.958984375,"s":[203.5,470,0]}],"ix":2,"l":2},"a":{"a":0,"k":[0,0,0],"ix":1,"l":2},"s":{"a":0,"k":[130,130,100],"ix":6,"l":2}},"ao":0,"ip":0,"op":1071.07107107107,"st":0,"bm":0},{"ddd":0,"ind":2,"ty":4,"nm":"Target","sr":1,"ks":{"o":{"a":0,"k":100,"ix":11},"r":{"a":0,"k":0,"ix":10},"p":{"a":0,"k":[655,479.5,0],"ix":2,"l":2},"a":{"a":0,"k":[255,79.5,0],"ix":1,"l":2},"s":{"a":1,"k":[{"i":{"x":[0.833,0.833,0.833],"y":[1,1,1]},"o":{"x":[0.333,0.333,0.333],"y":[0,0,0]},"t":0,"s":[0,0,100]},{"t":10,"s":[100,100,100]}],"ix":6,"l":2,"x":"var $bm_rt;\nvar amp, freq, decay, n, n, t, t, v;\namp = 0.4;\nfreq = 2;\ndecay = 7;\n$bm_rt = n = 0;\nif (numKeys > 0) {\n    $bm_rt = n = nearestKey(time).index;\n    if (key(n).time > time) {\n        n--;\n    }\n}\nif (n == 0) {\n    $bm_rt = t = 0;\n} else {\n    $bm_rt = t = $bm_sub(time, key(n).time);\n}\nif (n > 0) {\n    v = velocityAtTime($bm_sub(key(n).time, $bm_div(thisComp.frameDuration, 10)));\n    $bm_rt = $bm_sum(value, $bm_div($bm_mul($bm_mul(v, amp), Math.sin($bm_mul($bm_mul($bm_mul(freq, t), 2), Math.PI))), Math.exp($bm_mul(decay, t))));\n} else {\n    $bm_rt = value;\n}"}},"ao":0,"shapes":[{"ty":"gr","it":[{"d":1,"ty":"el","s":{"a":0,"k":[34,50.5],"ix":2},"p":{"a":0,"k":[0,0],"ix":3},"nm":"Ellipse Path 1","mn":"ADBE Vector Shape - Ellipse","hd":false},{"ty":"fl","c":{"a":0,"k":[0.788234994926,0.282353001015,0.16470600203,1],"ix":4},"o":{"a":0,"k":100,"ix":5},"r":1,"bm":0,"nm":"Fill 1","mn":"ADBE Vector Graphic - Fill","hd":false},{"ty":"tr","p":{"a":0,"k":[249.5,62.25],"ix":2},"a":{"a":0,"k":[0,0],"ix":1},"s":{"a":0,"k":[100,100],"ix":3},"r":{"a":0,"k":0,"ix":6},"o":{"a":0,"k":100,"ix":7},"sk":{"a":0,"k":0,"ix":4},"sa":{"a":0,"k":0,"ix":5},"nm":"Transform"}],"nm":"Ellipse 1","np":3,"cix":2,"bm":0,"ix":1,"mn":"ADBE Vector Group","hd":false},{"ty":"gr","it":[{"d":1,"ty":"el","s":{"a":0,"k":[61.5,77.5],"ix":2},"p":{"a":0,"k":[0,0],"ix":3},"nm":"Ellipse Path 1","mn":"ADBE Vector Shape - Ellipse","hd":false},{"ty":"fl","c":{"a":0,"k":[0.941176470588,0.941176470588,0.941176470588,1],"ix":4},"o":{"a":0,"k":100,"ix":5},"r":1,"bm":0,"nm":"Fill 1","mn":"ADBE Vector Graphic - Fill","hd":false},{"ty":"tr","p":{"a":0,"k":[249.75,62.75],"ix":2},"a":{"a":0,"k":[0,0],"ix":1},"s":{"a":0,"k":[100,100],"ix":3},"r":{"a":0,"k":0,"ix":6},"o":{"a":0,"k":100,"ix":7},"sk":{"a":0,"k":0,"ix":4},"sa":{"a":0,"k":0,"ix":5},"nm":"Transform"}],"nm":"Ellipse 2","np":3,"cix":2,"bm":0,"ix":2,"mn":"ADBE Vector Group","hd":false},{"ty":"gr","it":[{"d":1,"ty":"el","s":{"a":0,"k":[94.5,111.5],"ix":2},"p":{"a":0,"k":[0,0],"ix":3},"nm":"Ellipse Path 1","mn":"ADBE Vector Shape - Ellipse","hd":false},{"ty":"fl","c":{"a":0,"k":[0.690196078431,0.282352941176,0.2,1],"ix":4},"o":{"a":0,"k":100,"ix":5},"r":1,"bm":0,"nm":"Fill 1","mn":"ADBE Vector Graphic - Fill","hd":false},{"ty":"tr","p":{"a":0,"k":[250.25,62.75],"ix":2},"a":{"a":0,"k":[0,0],"ix":1},"s":{"a":0,"k":[100,100],"ix":3},"r":{"a":0,"k":0,"ix":6},"o":{"a":0,"k":100,"ix":7},"sk":{"a":0,"k":0,"ix":4},"sa":{"a":0,"k":0,"ix":5},"nm":"Transform"}],"nm":"Ellipse 3","np":3,"cix":2,"bm":0,"ix":3,"mn":"ADBE Vector Group","hd":false},{"ty":"gr","it":[{"d":1,"ty":"el","s":{"a":0,"k":[118.5,131],"ix":2},"p":{"a":0,"k":[0,0],"ix":3},"nm":"Ellipse Path 1","mn":"ADBE Vector Shape - Ellipse","hd":false},{"ty":"fl","c":{"a":0,"k":[0.894117647059,0.913725490196,0.905882352941,1],"ix":4},"o":{"a":0,"k":100,"ix":5},"r":1,"bm":0,"nm":"Fill 1","mn":"ADBE Vector Graphic - Fill","hd":false},{"ty":"tr","p":{"a":0,"k":[251.25,63],"ix":2},"a":{"a":0,"k":[0,0],"ix":1},"s":{"a":0,"k":[100,100],"ix":3},"r":{"a":0,"k":0,"ix":6},"o":{"a":0,"k":100,"ix":7},"sk":{"a":0,"k":0,"ix":4},"sa":{"a":0,"k":0,"ix":5},"nm":"Transform"}],"nm":"Ellipse 4","np":3,"cix":2,"bm":0,"ix":4,"mn":"ADBE Vector Group","hd":false},{"ty":"gr","it":[{"d":1,"ty":"el","s":{"a":0,"k":[121.5,133],"ix":2},"p":{"a":0,"k":[0,0],"ix":3},"nm":"Ellipse Path 1","mn":"ADBE Vector Shape - Ellipse","hd":false},{"ty":"fl","c":{"a":0,"k":[0.766274605545,0.700164675245,0.700164675245,1],"ix":4},"o":{"a":0,"k":100,"ix":5},"r":1,"bm":0,"nm":"Fill 1","mn":"ADBE Vector Graphic - Fill","hd":false},{"ty":"tr","p":{"a":0,"k":[259.25,62],"ix":2},"a":{"a":0,"k":[0,0],"ix":1},"s":{"a":0,"k":[100,100],"ix":3},"r":{"a":0,"k":0,"ix":6},"o":{"a":0,"k":100,"ix":7},"sk":{"a":0,"k":0,"ix":4},"sa":{"a":0,"k":0,"ix":5},"nm":"Transform"}],"nm":"Ellipse 6","np":3,"cix":2,"bm":0,"ix":5,"mn":"ADBE Vector Group","hd":false},{"ty":"gr","it":[{"ind":0,"ty":"sh","ix":1,"ks":{"a":0,"k":{"i":[[0,0],[0,0]],"o":[[0,0],[0,0]],"v":[[262.5,143.5],[249,68.5]],"c":false},"ix":2},"nm":"Path 1","mn":"ADBE Vector Shape - Group","hd":false},{"ty":"st","c":{"a":0,"k":[0.333333333333,0.211764705882,0.145098039216,1],"ix":3},"o":{"a":0,"k":100,"ix":4},"w":{"a":0,"k":9,"ix":5},"lc":2,"lj":1,"ml":4,"bm":0,"nm":"Stroke 1","mn":"ADBE Vector Graphic - Stroke","hd":false},{"ty":"tr","p":{"a":0,"k":[0,0],"ix":2},"a":{"a":0,"k":[0,0],"ix":1},"s":{"a":0,"k":[100,100],"ix":3},"r":{"a":0,"k":0,"ix":6},"o":{"a":0,"k":100,"ix":7},"sk":{"a":0,"k":0,"ix":4},"sa":{"a":0,"k":0,"ix":5},"nm":"Transform"}],"nm":"Shape 3","np":3,"cix":2,"bm":0,"ix":6,"mn":"ADBE Vector Group","hd":false},{"ty":"gr","it":[{"ind":0,"ty":"sh","ix":1,"ks":{"a":0,"k":{"i":[[0,0],[0,0]],"o":[[0,0],[0,0]],"v":[[297,159],[249.5,66]],"c":false},"ix":2},"nm":"Path 1","mn":"ADBE Vector Shape - Group","hd":false},{"ty":"st","c":{"a":0,"k":[0.333333333333,0.211764705882,0.145098039216,1],"ix":3},"o":{"a":0,"k":100,"ix":4},"w":{"a":0,"k":9,"ix":5},"lc":2,"lj":1,"ml":4,"bm":0,"nm":"Stroke 1","mn":"ADBE Vector Graphic - Stroke","hd":false},{"ty":"tr","p":{"a":0,"k":[0,0],"ix":2},"a":{"a":0,"k":[0,0],"ix":1},"s":{"a":0,"k":[100,100],"ix":3},"r":{"a":0,"k":0,"ix":6},"o":{"a":0,"k":100,"ix":7},"sk":{"a":0,"k":0,"ix":4},"sa":{"a":0,"k":0,"ix":5},"nm":"Transform"}],"nm":"Shape 2","np":3,"cix":2,"bm":0,"ix":7,"mn":"ADBE Vector Group","hd":false},{"ty":"gr","it":[{"ind":0,"ty":"sh","ix":1,"ks":{"a":0,"k":{"i":[[0,0],[0,0]],"o":[[0,0],[0,0]],"v":[[208,154.5],[250.5,65]],"c":false},"ix":2},"nm":"Path 1","mn":"ADBE Vector Shape - Group","hd":false},{"ty":"st","c":{"a":0,"k":[0.333333333333,0.211764705882,0.145098039216,1],"ix":3},"o":{"a":0,"k":100,"ix":4},"w":{"a":0,"k":9,"ix":5},"lc":2,"lj":1,"ml":4,"bm":0,"nm":"Stroke 1","mn":"ADBE Vector Graphic - Stroke","hd":false},{"ty":"tr","p":{"a":0,"k":[0,0],"ix":2},"a":{"a":0,"k":[0,0],"ix":1},"s":{"a":0,"k":[100,100],"ix":3},"r":{"a":0,"k":0,"ix":6},"o":{"a":0,"k":100,"ix":7},"sk":{"a":0,"k":0,"ix":4},"sa":{"a":0,"k":0,"ix":5},"nm":"Transform"}],"nm":"Shape 1","np":3,"cix":2,"bm":0,"ix":8,"mn":"ADBE Vector Group","hd":false},{"ty":"gr","it":[{"d":1,"ty":"el","s":{"a":0,"k":[140,21.5],"ix":2},"p":{"a":0,"k":[0,0],"ix":3},"nm":"Ellipse Path 1","mn":"ADBE Vector Shape - Ellipse","hd":false},{"ty":"fl","c":{"a":0,"k":[0,0,0,1],"ix":4},"o":{"a":0,"k":100,"ix":5},"r":1,"bm":0,"nm":"Fill 1","mn":"ADBE Vector Graphic - Fill","hd":false},{"ty":"tr","p":{"a":0,"k":[255,152.75],"ix":2},"a":{"a":0,"k":[0,0],"ix":1},"s":{"a":0,"k":[100,100],"ix":3},"r":{"a":0,"k":0,"ix":6},"o":{"a":0,"k":10,"ix":7},"sk":{"a":0,"k":0,"ix":4},"sa":{"a":0,"k":0,"ix":5},"nm":"Transform"}],"nm":"Ellipse 5","np":3,"cix":2,"bm":0,"ix":9,"mn":"ADBE Vector Group","hd":false}],"ip":0,"op":1050,"st":0,"bm":0},{"ddd":0,"ind":3,"ty":4,"nm":"Arm 2","parent":15,"sr":1,"ks":{"o":{"a":0,"k":100,"ix":11},"r":{"a":1,"k":[{"i":{"x":[0.667],"y":[1]},"o":{"x":[0.333],"y":[0]},"t":0,"s":[12]},{"i":{"x":[0.667],"y":[1]},"o":{"x":[0.333],"y":[0]},"t":12,"s":[-8]},{"i":{"x":[0.667],"y":[1]},"o":{"x":[0.333],"y":[0]},"t":25,"s":[35]},{"i":{"x":[0.667],"y":[1]},"o":{"x":[0.333],"y":[0]},"t":37,"s":[-8]},{"i":{"x":[0.833],"y":[1]},"o":{"x":[0.333],"y":[0]},"t":45,"s":[12]},{"i":{"x":[0.833],"y":[1]},"o":{"x":[0.167],"y":[0]},"t":61,"s":[12]},{"i":{"x":[0.833],"y":[1]},"o":{"x":[0.167],"y":[0]},"t":71,"s":[98]},{"i":{"x":[0.833],"y":[1]},"o":{"x":[0.167],"y":[0]},"t":150,"s":[98]},{"i":{"x":[0.833],"y":[1]},"o":{"x":[0.167],"y":[0]},"t":160,"s":[208]},{"i":{"x":[0.833],"y":[1]},"o":{"x":[0.167],"y":[0]},"t":161,"s":[208]},{"t":171,"s":[98]}],"ix":10},"p":{"a":0,"k":[126.829,63.357,0],"ix":2,"l":2},"a":{"a":0,"k":[-75.125,63.875,0],"ix":1,"l":2},"s":{"a":0,"k":[-100,100,100],"ix":6,"l":2}},"ao":0,"ef":[{"ty":21,"nm":"Fill","np":9,"mn":"ADBE Fill","ix":1,"en":1,"ef":[{"ty":10,"nm":"Fill Mask","mn":"ADBE Fill-0001","ix":1,"v":{"a":0,"k":0,"ix":1}},{"ty":7,"nm":"All Masks","mn":"ADBE Fill-0007","ix":2,"v":{"a":0,"k":0,"ix":2}},{"ty":2,"nm":"Color","mn":"ADBE Fill-0002","ix":3,"v":{"a":0,"k":[1,0,0,1],"ix":3,"x":"var $bm_rt;\nif (comp('i Miss Suit').layer('Local Color Control').effect('Global Colors')(1) == 1)\n    $bm_rt = comp('!Global Control').layer('Body').effect('Fill')('Color');\nelse\n    $bm_rt = comp('i Miss Suit').layer('Local Color Control').effect('Suit')('Color');"}},{"ty":7,"nm":"Invert","mn":"ADBE Fill-0006","ix":4,"v":{"a":0,"k":0,"ix":4}},{"ty":0,"nm":"Horizontal Feather","mn":"ADBE Fill-0003","ix":5,"v":{"a":0,"k":0,"ix":5}},{"ty":0,"nm":"Vertical Feather","mn":"ADBE Fill-0004","ix":6,"v":{"a":0,"k":0,"ix":6}},{"ty":0,"nm":"Opacity","mn":"ADBE Fill-0005","ix":7,"v":{"a":0,"k":1,"ix":7}}]}],"shapes":[{"ty":"gr","it":[{"ind":0,"ty":"sh","ix":1,"ks":{"a":1,"k":[{"i":{"x":0.833,"y":0.833},"o":{"x":0.167,"y":0.167},"t":61,"s":[{"i":[[0,0],[-4,-148]],"o":[[0,0],[4,148]],"v":[[-75.5,64],[-123.5,228.5]],"c":false}]},{"i":{"x":0.833,"y":0.833},"o":{"x":0.167,"y":0.167},"t":71,"s":[{"i":[[0,0],[-28.189,-145.346]],"o":[[0,0],[27.881,143.758]],"v":[[-74.647,64.12],[-112.379,339.439]],"c":false}]},{"i":{"x":0.833,"y":0.833},"o":{"x":0.167,"y":0.167},"t":76,"s":[{"i":[[0,0],[-28.189,-145.346]],"o":[[0,0],[27.881,143.758]],"v":[[-74.647,64.12],[-112.465,340.052]],"c":false}]},{"i":{"x":0.833,"y":0.833},"o":{"x":0.167,"y":0.167},"t":92,"s":[{"i":[[0,0],[-48.576,-193.737]],"o":[[0,0],[35.135,142.11]],"v":[[-74.647,64.12],[-129.69,238.198]],"c":false}]},{"i":{"x":0.833,"y":0.833},"o":{"x":0.167,"y":0.167},"t":161,"s":[{"i":[[0,0],[-48.576,-193.737]],"o":[[0,0],[35.135,142.11]],"v":[[-74.647,64.12],[-129.69,238.198]],"c":false}]},{"i":{"x":0.833,"y":0.833},"o":{"x":0.167,"y":0.167},"t":171,"s":[{"i":[[0,0],[-28.189,-145.346]],"o":[[0,0],[27.881,143.758]],"v":[[-74.647,64.12],[-112.462,342.01]],"c":false}]},{"t":187,"s":[{"i":[[0,0],[-48.576,-193.737]],"o":[[0,0],[35.135,142.11]],"v":[[-74.647,64.12],[-129.865,238.33]],"c":false}]}],"ix":2},"nm":"Path 1","mn":"ADBE Vector Shape - Group","hd":false},{"ty":"st","c":{"a":0,"k":[0.992156862745,0.862745098039,0.745098039216,1],"ix":3},"o":{"a":0,"k":100,"ix":4},"w":{"a":0,"k":25,"ix":5},"lc":1,"lj":1,"ml":4,"bm":0,"nm":"Stroke 1","mn":"ADBE Vector Graphic - Stroke","hd":false},{"ty":"tr","p":{"a":0,"k":[0,0],"ix":2},"a":{"a":0,"k":[0,0],"ix":1},"s":{"a":0,"k":[100,100],"ix":3},"r":{"a":0,"k":0,"ix":6},"o":{"a":0,"k":100,"ix":7},"sk":{"a":0,"k":0,"ix":4},"sa":{"a":0,"k":0,"ix":5},"nm":"Transform"}],"nm":"Shape 1","np":3,"cix":2,"bm":0,"ix":1,"mn":"ADBE Vector Group","hd":false}],"ip":0,"op":1071.07107107107,"st":0,"bm":0},{"ddd":0,"ind":4,"ty":4,"nm":"Contur","parent":15,"sr":1,"ks":{"o":{"a":0,"k":100,"ix":11},"r":{"a":1,"k":[{"i":{"x":[0.667],"y":[1]},"o":{"x":[0.333],"y":[0]},"t":0,"s":[12]},{"i":{"x":[0.667],"y":[1]},"o":{"x":[0.333],"y":[0]},"t":12,"s":[-8]},{"i":{"x":[0.667],"y":[1]},"o":{"x":[0.333],"y":[0]},"t":25,"s":[35]},{"i":{"x":[0.667],"y":[1]},"o":{"x":[0.333],"y":[0]},"t":37,"s":[-8]},{"i":{"x":[0.833],"y":[1]},"o":{"x":[0.333],"y":[0]},"t":45,"s":[12]},{"i":{"x":[0.833],"y":[1]},"o":{"x":[0.167],"y":[0]},"t":61,"s":[12]},{"i":{"x":[0.833],"y":[1]},"o":{"x":[0.167],"y":[0]},"t":71,"s":[98]},{"i":{"x":[0.833],"y":[1]},"o":{"x":[0.167],"y":[0]},"t":150,"s":[98]},{"i":{"x":[0.833],"y":[1]},"o":{"x":[0.167],"y":[0]},"t":160,"s":[208]},{"i":{"x":[0.833],"y":[1]},"o":{"x":[0.167],"y":[0]},"t":161,"s":[208]},{"t":171,"s":[98]}],"ix":10},"p":{"a":0,"k":[126.829,63.357,0],"ix":2,"l":2},"a":{"a":0,"k":[-75.125,63.875,0],"ix":1,"l":2},"s":{"a":0,"k":[-100,100,100],"ix":6,"l":2}},"ao":0,"shapes":[{"ty":"gr","it":[{"ind":0,"ty":"sh","ix":1,"ks":{"a":1,"k":[{"i":{"x":0.833,"y":0.833},"o":{"x":0.167,"y":0.167},"t":61,"s":[{"i":[[0,0],[-4,-148]],"o":[[0,0],[4,148]],"v":[[-76.305,64.703],[-123.5,228.5]],"c":false}]},{"i":{"x":0.833,"y":0.833},"o":{"x":0.167,"y":0.167},"t":71,"s":[{"i":[[0,0],[-28.189,-145.346]],"o":[[0,0],[27.881,143.758]],"v":[[-74.825,65.389],[-112.379,339.439]],"c":false}]},{"i":{"x":0.833,"y":0.833},"o":{"x":0.167,"y":0.167},"t":76,"s":[{"i":[[0,0],[-28.189,-145.346]],"o":[[0,0],[27.881,143.758]],"v":[[-74.885,65.813],[-112.465,340.052]],"c":false}]},{"i":{"x":0.833,"y":0.833},"o":{"x":0.167,"y":0.167},"t":92,"s":[{"i":[[0,0],[-48.576,-193.737]],"o":[[0,0],[35.135,142.11]],"v":[[-75.282,64.031],[-129.69,238.198]],"c":false}]},{"i":{"x":0.833,"y":0.833},"o":{"x":0.167,"y":0.167},"t":161,"s":[{"i":[[0,0],[-48.576,-193.737]],"o":[[0,0],[35.135,142.11]],"v":[[-75.992,64.373],[-129.69,238.198]],"c":false}]},{"i":{"x":0.833,"y":0.833},"o":{"x":0.167,"y":0.167},"t":171,"s":[{"i":[[0,0],[-28.189,-145.346]],"o":[[0,0],[27.881,143.758]],"v":[[-74.974,66.447],[-112.462,342.01]],"c":false}]},{"t":187,"s":[{"i":[[0,0],[-48.576,-193.737]],"o":[[0,0],[35.135,142.11]],"v":[[-75.705,63.971],[-129.865,238.33]],"c":false}]}],"ix":2},"nm":"Path 1","mn":"ADBE Vector Shape - Group","hd":false},{"ty":"st","c":{"a":0,"k":[0.258823529412,0.258823529412,0.258823529412,1],"ix":3},"o":{"a":0,"k":100,"ix":4},"w":{"a":0,"k":26,"ix":5},"lc":1,"lj":1,"ml":4,"bm":0,"nm":"Stroke 1","mn":"ADBE Vector Graphic - Stroke","hd":false},{"ty":"tr","p":{"a":0,"k":[0,0],"ix":2},"a":{"a":0,"k":[0,0],"ix":1},"s":{"a":0,"k":[100,100],"ix":3},"r":{"a":0,"k":0,"ix":6},"o":{"a":0,"k":100,"ix":7},"sk":{"a":0,"k":0,"ix":4},"sa":{"a":0,"k":0,"ix":5},"nm":"Transform"}],"nm":"Shape 1","np":3,"cix":2,"bm":0,"ix":1,"mn":"ADBE Vector Group","hd":false}],"ip":0,"op":1071.07107107107,"st":0,"bm":0},{"ddd":0,"ind":5,"ty":4,"nm":"Sleeve 2","parent":6,"sr":1,"ks":{"o":{"a":0,"k":100,"ix":11},"r":{"a":0,"k":4.358,"ix":10},"p":{"a":0,"k":[168.912,226.265,0],"ix":2,"l":2},"a":{"a":0,"k":[169.875,219.875,0],"ix":1,"l":2},"s":{"a":0,"k":[95.732,98.082,100],"ix":6,"l":2}},"ao":0,"ef":[{"ty":21,"nm":"Fill","np":9,"mn":"ADBE Fill","ix":1,"en":1,"ef":[{"ty":10,"nm":"Fill Mask","mn":"ADBE Fill-0001","ix":1,"v":{"a":0,"k":0,"ix":1}},{"ty":7,"nm":"All Masks","mn":"ADBE Fill-0007","ix":2,"v":{"a":0,"k":0,"ix":2}},{"ty":2,"nm":"Color","mn":"ADBE Fill-0002","ix":3,"v":{"a":0,"k":[1,0,0,1],"ix":3,"x":"var $bm_rt;\nif (comp('i Miss Suit').layer('Local Color Control').effect('Global Colors')(1) == 1)\n    $bm_rt = comp('!Global Control').layer('Shirt').effect('Fill')('Color');\nelse\n    $bm_rt = comp('i Miss Suit').layer('Local Color Control').effect('Shirt')('Color');"}},{"ty":7,"nm":"Invert","mn":"ADBE Fill-0006","ix":4,"v":{"a":0,"k":0,"ix":4}},{"ty":0,"nm":"Horizontal Feather","mn":"ADBE Fill-0003","ix":5,"v":{"a":0,"k":0,"ix":5}},{"ty":0,"nm":"Vertical Feather","mn":"ADBE Fill-0004","ix":6,"v":{"a":0,"k":0,"ix":6}},{"ty":0,"nm":"Opacity","mn":"ADBE Fill-0005","ix":7,"v":{"a":0,"k":1,"ix":7}}]}],"shapes":[{"ty":"gr","it":[{"ty":"rc","d":1,"s":{"a":0,"k":[25.25,8.25],"ix":2},"p":{"a":0,"k":[0,0],"ix":3},"r":{"a":0,"k":0,"ix":4},"nm":"Rectangle Path 1","mn":"ADBE Vector Shape - Rect","hd":false},{"ty":"fl","c":{"a":0,"k":[1,1,1,1],"ix":4},"o":{"a":0,"k":100,"ix":5},"r":1,"bm":0,"nm":"Fill 1","mn":"ADBE Vector Graphic - Fill","hd":false},{"ty":"tr","p":{"a":0,"k":[169.875,219.875],"ix":2},"a":{"a":0,"k":[0,0],"ix":1},"s":{"a":0,"k":[100,100],"ix":3},"r":{"a":0,"k":0,"ix":6},"o":{"a":0,"k":100,"ix":7},"sk":{"a":0,"k":0,"ix":4},"sa":{"a":0,"k":0,"ix":5},"nm":"Transform"}],"nm":"Rectangle 1","np":3,"cix":2,"bm":0,"ix":1,"mn":"ADBE Vector Group","hd":false}],"ip":0,"op":1071.07107107107,"st":0,"bm":0},{"ddd":0,"ind":6,"ty":4,"nm":"Hand 2","parent":3,"sr":1,"ks":{"o":{"a":0,"k":100,"ix":11},"r":{"a":1,"k":[{"i":{"x":[0.833],"y":[0.833]},"o":{"x":[0.167],"y":[0.167]},"t":61,"s":[-12]},{"i":{"x":[0.833],"y":[0.833]},"o":{"x":[0.167],"y":[0.167]},"t":71,"s":[-18]},{"i":{"x":[0.833],"y":[0.833]},"o":{"x":[0.167],"y":[0.167]},"t":97,"s":[-18]},{"i":{"x":[0.833],"y":[0.833]},"o":{"x":[0.167],"y":[0.167]},"t":161,"s":[-18]},{"t":171,"s":[-18]}],"ix":10},"p":{"a":1,"k":[{"i":{"x":0.833,"y":0.833},"o":{"x":0.167,"y":0.167},"t":61,"s":[-123.625,232.711,0],"to":[1.931,18.754,0],"ti":[-1.931,-18.754,0]},{"i":{"x":0.833,"y":0.833},"o":{"x":0.167,"y":0.167},"t":71,"s":[-112.041,345.238,0],"to":[0,0,0],"ti":[0,0,0]},{"i":{"x":0.833,"y":0.833},"o":{"x":0.167,"y":0.167},"t":76,"s":[-112.041,345.238,0],"to":[0,0,0],"ti":[0,0,0]},{"i":{"x":0.833,"y":0.833},"o":{"x":0.167,"y":0.167},"t":92,"s":[-130.065,239.549,0],"to":[0,0,0],"ti":[0,0,0]},{"i":{"x":0.833,"y":0.833},"o":{"x":0.167,"y":0.167},"t":97,"s":[-130.065,239.549,0],"to":[0,0,0],"ti":[0,0,0]},{"i":{"x":0.833,"y":0.833},"o":{"x":0.167,"y":0.167},"t":161,"s":[-130.065,239.549,0],"to":[0,0,0],"ti":[-1.931,-18.754,0]},{"i":{"x":0.833,"y":0.833},"o":{"x":0.167,"y":0.167},"t":171,"s":[-112.041,345.238,0],"to":[0,0,0],"ti":[0,0,0]},{"t":187,"s":[-130.065,239.549,0]}],"ix":2,"l":2},"a":{"a":0,"k":[168.269,227.381,0],"ix":1,"l":2},"s":{"a":0,"k":[99.911,97.087,100],"ix":6,"l":2}},"ao":0,"ef":[{"ty":21,"nm":"Fill","np":9,"mn":"ADBE Fill","ix":1,"en":1,"ef":[{"ty":10,"nm":"Fill Mask","mn":"ADBE Fill-0001","ix":1,"v":{"a":0,"k":0,"ix":1}},{"ty":7,"nm":"All Masks","mn":"ADBE Fill-0007","ix":2,"v":{"a":0,"k":0,"ix":2}},{"ty":2,"nm":"Color","mn":"ADBE Fill-0002","ix":3,"v":{"a":0,"k":[1,0,0,1],"ix":3,"x":"var $bm_rt;\nif (comp('i Miss Suit').layer('Local Color Control').effect('Global Colors')(1) == 1)\n    $bm_rt = comp('!Global Control').layer('Skin 2').effect('Fill')('Color');\nelse\n    $bm_rt = comp('i Miss Suit').layer('Local Color Control').effect('Skin')('Color');"}},{"ty":7,"nm":"Invert","mn":"ADBE Fill-0006","ix":4,"v":{"a":0,"k":0,"ix":4}},{"ty":0,"nm":"Horizontal Feather","mn":"ADBE Fill-0003","ix":5,"v":{"a":0,"k":0,"ix":5}},{"ty":0,"nm":"Vertical Feather","mn":"ADBE Fill-0004","ix":6,"v":{"a":0,"k":0,"ix":6}},{"ty":0,"nm":"Opacity","mn":"ADBE Fill-0005","ix":7,"v":{"a":0,"k":1,"ix":7}}]}],"shapes":[{"ty":"gr","it":[{"ind":0,"ty":"sh","ix":1,"ks":{"a":0,"k":{"i":[[0,0],[-3.922,-1.02],[0,0],[-2.125,-1.625],[0,0],[-3.242,-0.903],[0,0],[-2.806,-0.623],[0,0],[0,0]],"o":[[0,0],[2.215,0.576],[0,0],[2.125,1.625],[0,0],[3.089,0.861],[0,0],[3.929,0.873],[0,0],[0,0]],"v":[[159.1,220.591],[156.448,244.143],[160.323,240.687],[161.135,245.619],[166.073,242.482],[168.277,247.602],[172.381,243.842],[174.743,248.795],[178.684,245.113],[180.766,224.028]],"c":true},"ix":2},"nm":"Path 1","mn":"ADBE Vector Shape - Group","hd":false},{"ty":"fl","c":{"a":0,"k":[0.992156862745,0.862745098039,0.745098039216,1],"ix":4},"o":{"a":0,"k":100,"ix":5},"r":1,"bm":0,"nm":"Fill 1","mn":"ADBE Vector Graphic - Fill","hd":false},{"ty":"tr","p":{"a":0,"k":[0,0],"ix":2},"a":{"a":0,"k":[0,0],"ix":1},"s":{"a":0,"k":[100,100],"ix":3},"r":{"a":0,"k":0,"ix":6},"o":{"a":0,"k":100,"ix":7},"sk":{"a":0,"k":0,"ix":4},"sa":{"a":0,"k":0,"ix":5},"nm":"Transform"}],"nm":"Hand","np":3,"cix":2,"bm":0,"ix":1,"mn":"ADBE Vector Group","hd":false}],"ip":0,"op":1071.07107107107,"st":0,"bm":0},{"ddd":0,"ind":7,"ty":4,"nm":"Arrow","parent":6,"sr":1,"ks":{"o":{"a":0,"k":100,"ix":11},"r":{"a":1,"k":[{"i":{"x":[0.833],"y":[0.833]},"o":{"x":[0.167],"y":[0.167]},"t":61,"s":[141.616]},{"i":{"x":[0.833],"y":[0.833]},"o":{"x":[0.167],"y":[0.167]},"t":71,"s":[178.616]},{"i":{"x":[0.833],"y":[0.833]},"o":{"x":[0.167],"y":[0.167]},"t":97,"s":[178.616]},{"i":{"x":[0.833],"y":[0.833]},"o":{"x":[0.167],"y":[0.167]},"t":117,"s":[254.616]},{"i":{"x":[0.833],"y":[0.833]},"o":{"x":[0.167],"y":[0.167]},"t":160,"s":[254.616]},{"i":{"x":[0.833],"y":[0.833]},"o":{"x":[0.167],"y":[0.167]},"t":161,"s":[29.616]},{"i":{"x":[0.833],"y":[0.833]},"o":{"x":[0.167],"y":[0.167]},"t":171,"s":[178.616]},{"i":{"x":[0.833],"y":[0.833]},"o":{"x":[0.167],"y":[0.167]},"t":192,"s":[178.616]},{"t":212,"s":[254.616]}],"ix":10},"p":{"a":1,"k":[{"i":{"x":0.833,"y":0.833},"o":{"x":0.167,"y":0.167},"t":97,"s":[172.031,238.492,0],"to":[1.8,308.541,0],"ti":[634.539,-291.193,0]},{"i":{"x":0.833,"y":0.833},"o":{"x":0.167,"y":0.167},"t":117,"s":[-486.661,1268.065,0],"to":[-185.144,84.963,0],"ti":[0,0,0]},{"i":{"x":0.833,"y":0.833},"o":{"x":0.167,"y":0.167},"t":160,"s":[-486.661,1268.065,0],"to":[0,0,0],"ti":[0,0,0]},{"i":{"x":0.833,"y":0.833},"o":{"x":0.167,"y":0.167},"t":161,"s":[164.202,235.749,0],"to":[0,0,0],"ti":[0,0,0]},{"t":171,"s":[172.031,238.492,0],"h":1},{"i":{"x":0.833,"y":0.833},"o":{"x":0.167,"y":0.167},"t":192,"s":[172.031,238.492,0],"to":[1.8,308.541,0],"ti":[634.539,-291.193,0]},{"t":212,"s":[-486.661,1268.065,0]}],"ix":2,"l":2},"a":{"a":0,"k":[111.188,-112.449,0],"ix":1,"l":2},"s":{"a":0,"k":[175.896,173.927,100],"ix":6,"l":2}},"ao":0,"hasMask":true,"masksProperties":[{"inv":false,"mode":"s","pt":{"a":1,"k":[{"i":{"x":0.833,"y":0.833},"o":{"x":0.167,"y":0.167},"t":160,"s":[{"i":[[0,0],[0,0],[0,0],[0,0]],"o":[[0,0],[0,0],[0,0],[0,0]],"v":[[93.84,-254.884],[96.61,-255.225],[132.917,-245.859],[134.324,-245.874]],"c":true}]},{"i":{"x":0.833,"y":0.833},"o":{"x":0.167,"y":0.167},"t":161,"s":[{"i":[[0,0],[0,0],[0,0],[0,0]],"o":[[0,0],[0,0],[0,0],[0,0]],"v":[[93.84,-254.884],[93.84,-124.111],[112.934,-128.583],[138.989,-219.098]],"c":true}]},{"t":162,"s":[{"i":[[0,0],[0,0],[0,0],[0,0]],"o":[[0,0],[0,0],[0,0],[0,0]],"v":[[93.84,-254.884],[95.646,-250.56],[96.304,-255.053],[95.912,-254.768]],"c":true}]}],"ix":1},"o":{"a":0,"k":100,"ix":3},"x":{"a":0,"k":0,"ix":4},"nm":"Mask 1"}],"shapes":[{"ty":"gr","it":[{"ty":"sr","sy":2,"d":1,"pt":{"a":0,"k":3,"ix":3},"p":{"a":0,"k":[0,0],"ix":4},"r":{"a":0,"k":0,"ix":5},"or":{"a":0,"k":7.649,"ix":7},"os":{"a":0,"k":0,"ix":9},"ix":1,"nm":"Polystar Path 1","mn":"ADBE Vector Shape - Star","hd":false},{"ty":"fl","c":{"a":0,"k":[0.333333333333,0.211764705882,0.145098039216,1],"ix":4},"o":{"a":0,"k":100,"ix":5},"r":1,"bm":0,"nm":"Fill 1","mn":"ADBE Vector Graphic - Fill","hd":false},{"ty":"tr","p":{"a":0,"k":[111.25,-228.5],"ix":2},"a":{"a":0,"k":[0,0],"ix":1},"s":{"a":0,"k":[100,100],"ix":3},"r":{"a":0,"k":0,"ix":6},"o":{"a":0,"k":100,"ix":7},"sk":{"a":0,"k":0,"ix":4},"sa":{"a":0,"k":0,"ix":5},"nm":"Transform"}],"nm":"Polystar 1","np":3,"cix":2,"bm":0,"ix":1,"mn":"ADBE Vector Group","hd":false},{"ty":"gr","it":[{"ind":0,"ty":"sh","ix":1,"ks":{"a":0,"k":{"i":[[0,0],[0,0]],"o":[[0,0],[0,0]],"v":[[111,-228.25],[111,-112.75]],"c":false},"ix":2},"nm":"Path 1","mn":"ADBE Vector Shape - Group","hd":false},{"ty":"st","c":{"a":0,"k":[0.333333333333,0.211764705882,0.145098039216,1],"ix":3},"o":{"a":0,"k":100,"ix":4},"w":{"a":0,"k":3,"ix":5},"lc":2,"lj":1,"ml":4,"bm":0,"nm":"Stroke 1","mn":"ADBE Vector Graphic - Stroke","hd":false},{"ty":"tr","p":{"a":0,"k":[0,0],"ix":2},"a":{"a":0,"k":[0,0],"ix":1},"s":{"a":0,"k":[100,100],"ix":3},"r":{"a":0,"k":0,"ix":6},"o":{"a":0,"k":100,"ix":7},"sk":{"a":0,"k":0,"ix":4},"sa":{"a":0,"k":0,"ix":5},"nm":"Transform"}],"nm":"Shape 2","np":3,"cix":2,"bm":0,"ix":2,"mn":"ADBE Vector Group","hd":false},{"ty":"gr","it":[{"ind":0,"ty":"sh","ix":1,"ks":{"a":0,"k":{"i":[[0,0],[0,0],[0,0],[0,0]],"o":[[0,0],[0,0],[0,0],[0,0]],"v":[[2.625,-4.75],[2.625,18.5],[-6.5,11.625],[-6.5,-11.625]],"c":true},"ix":2},"nm":"Path 1","mn":"ADBE Vector Shape - Group","hd":false},{"ty":"fl","c":{"a":0,"k":[0.690196078431,0.282352941176,0.2,1],"ix":4},"o":{"a":0,"k":100,"ix":5},"r":1,"bm":0,"nm":"Fill 1","mn":"ADBE Vector Graphic - Fill","hd":false},{"ty":"tr","p":{"a":0,"k":[104.625,-124],"ix":2},"a":{"a":0,"k":[0,0],"ix":1},"s":{"a":0,"k":[-100,100],"ix":3},"r":{"a":0,"k":0,"ix":6},"o":{"a":0,"k":100,"ix":7},"sk":{"a":0,"k":0,"ix":4},"sa":{"a":0,"k":0,"ix":5},"nm":"Transform"}],"nm":"Rectangle 2","np":3,"cix":2,"bm":0,"ix":3,"mn":"ADBE Vector Group","hd":false},{"ty":"gr","it":[{"ind":0,"ty":"sh","ix":1,"ks":{"a":0,"k":{"i":[[0,0],[0,0],[0,0],[0,0]],"o":[[0,0],[0,0],[0,0],[0,0]],"v":[[2.625,-4.75],[2.625,18.5],[-6.5,11.625],[-6.5,-11.625]],"c":true},"ix":2},"nm":"Path 1","mn":"ADBE Vector Shape - Group","hd":false},{"ty":"fl","c":{"a":0,"k":[0.690196078431,0.282352941176,0.2,1],"ix":4},"o":{"a":0,"k":100,"ix":5},"r":1,"bm":0,"nm":"Fill 1","mn":"ADBE Vector Graphic - Fill","hd":false},{"ty":"tr","p":{"a":0,"k":[117.75,-123.875],"ix":2},"a":{"a":0,"k":[0,0],"ix":1},"s":{"a":0,"k":[100,100],"ix":3},"r":{"a":0,"k":0,"ix":6},"o":{"a":0,"k":100,"ix":7},"sk":{"a":0,"k":0,"ix":4},"sa":{"a":0,"k":0,"ix":5},"nm":"Transform"}],"nm":"Rectangle 1","np":3,"cix":2,"bm":0,"ix":4,"mn":"ADBE Vector Group","hd":false}],"ip":0,"op":1050,"st":0,"bm":0},{"ddd":0,"ind":8,"ty":4,"nm":"Fingers","parent":18,"sr":1,"ks":{"o":{"a":0,"k":100,"ix":11},"r":{"a":0,"k":130.186,"ix":10},"p":{"a":0,"k":[86.583,298.294,0],"ix":2,"l":2},"a":{"a":0,"k":[0,0,0],"ix":1,"l":2},"s":{"a":0,"k":[176.359,173.471,100],"ix":6,"l":2}},"ao":0,"ef":[{"ty":21,"nm":"Fill","np":9,"mn":"ADBE Fill","ix":1,"en":1,"ef":[{"ty":10,"nm":"Fill Mask","mn":"ADBE Fill-0001","ix":1,"v":{"a":0,"k":0,"ix":1}},{"ty":7,"nm":"All Masks","mn":"ADBE Fill-0007","ix":2,"v":{"a":0,"k":0,"ix":2}},{"ty":2,"nm":"Color","mn":"ADBE Fill-0002","ix":3,"v":{"a":0,"k":[1,0,0,1],"ix":3,"x":"var $bm_rt;\nif (comp('i Miss Suit').layer('Local Color Control').effect('Global Colors')(1) == 1)\n    $bm_rt = comp('!Global Control').layer('Skin 2').effect('Fill')('Color');\nelse\n    $bm_rt = comp('i Miss Suit').layer('Local Color Control').effect('Skin')('Color');"}},{"ty":7,"nm":"Invert","mn":"ADBE Fill-0006","ix":4,"v":{"a":0,"k":0,"ix":4}},{"ty":0,"nm":"Horizontal Feather","mn":"ADBE Fill-0003","ix":5,"v":{"a":0,"k":0,"ix":5}},{"ty":0,"nm":"Vertical Feather","mn":"ADBE Fill-0004","ix":6,"v":{"a":0,"k":0,"ix":6}},{"ty":0,"nm":"Opacity","mn":"ADBE Fill-0005","ix":7,"v":{"a":0,"k":1,"ix":7}}]}],"shapes":[{"ty":"gr","it":[{"ind":0,"ty":"sh","ix":1,"ks":{"a":0,"k":{"i":[[2.75,-0.5],[-0.752,-1.754],[0,0],[-0.875,-1.875],[0,0],[-1,-1.625],[0,0],[-0.75,-1.875],[-0.5,0.75]],"o":[[-1.375,0.5],[0.75,1.75],[0,0],[0.875,1.875],[0,0],[1,1.625],[0,0],[0.75,1.875],[1.375,-6.625]],"v":[[-57.75,-20.875],[-61.5,-17.188],[-58.188,-16.688],[-60,-13.75],[-56.625,-13],[-58.062,-10.062],[-54.75,-9.562],[-56.75,-6.188],[-52,-7]],"c":true},"ix":2},"nm":"Path 1","mn":"ADBE Vector Shape - Group","hd":false},{"ty":"fl","c":{"a":0,"k":[0.788234994926,0.282353001015,0.16470600203,1],"ix":4},"o":{"a":0,"k":100,"ix":5},"r":1,"bm":0,"nm":"Fill 1","mn":"ADBE Vector Graphic - Fill","hd":false},{"ty":"tr","p":{"a":0,"k":[0,0],"ix":2},"a":{"a":0,"k":[0,0],"ix":1},"s":{"a":0,"k":[100,100],"ix":3},"r":{"a":0,"k":0,"ix":6},"o":{"a":0,"k":100,"ix":7},"sk":{"a":0,"k":0,"ix":4},"sa":{"a":0,"k":0,"ix":5},"nm":"Transform"}],"nm":"Shape 1","np":3,"cix":2,"bm":0,"ix":1,"mn":"ADBE Vector Group","hd":false}],"ip":0,"op":1050,"st":0,"bm":0},{"ddd":0,"ind":9,"ty":4,"nm":"Bow","parent":8,"sr":1,"ks":{"o":{"a":0,"k":100,"ix":11},"r":{"a":0,"k":-1.01,"ix":10},"p":{"a":0,"k":[-93.628,8.942,0],"ix":2,"l":2},"a":{"a":0,"k":[-88.461,5.5,0],"ix":1,"l":2},"s":{"a":0,"k":[99.445,100.558,100],"ix":6,"l":2}},"ao":0,"shapes":[{"ty":"gr","it":[{"ind":0,"ty":"sh","ix":1,"ks":{"a":1,"k":[{"i":{"x":0.833,"y":0.833},"o":{"x":0.167,"y":0.167},"t":76,"s":[{"i":[[0,0],[0,0],[0,0]],"o":[[0,0],[0,0],[0,0]],"v":[[-129.5,-71.5],[-95.5,8],[-66.5,82.5]],"c":false}]},{"i":{"x":0.833,"y":0.833},"o":{"x":0.167,"y":0.167},"t":92,"s":[{"i":[[0,0],[0,0],[0,0]],"o":[[0,0],[0,0],[0,0]],"v":[[-129.5,-71.5],[-153.966,24.25],[-66.5,82.5]],"c":false}]},{"i":{"x":0.833,"y":0.833},"o":{"x":0.167,"y":0.167},"t":97,"s":[{"i":[[0,0],[0,0],[0,0]],"o":[[0,0],[0,0],[0,0]],"v":[[-129.5,-71.5],[-153.966,24.25],[-66.5,82.5]],"c":false}]},{"i":{"x":0.833,"y":0.833},"o":{"x":0.167,"y":0.167},"t":99,"s":[{"i":[[0,0],[0,0],[0,0]],"o":[[0,0],[0,0],[0,0]],"v":[[-129.5,-71.5],[-95.5,8],[-66.5,82.5]],"c":false}]},{"i":{"x":0.833,"y":0.833},"o":{"x":0.167,"y":0.167},"t":171,"s":[{"i":[[0,0],[0,0],[0,0]],"o":[[0,0],[0,0],[0,0]],"v":[[-129.5,-71.5],[-95.5,8],[-66.5,82.5]],"c":false}]},{"i":{"x":0.833,"y":0.833},"o":{"x":0.167,"y":0.167},"t":187,"s":[{"i":[[0,0],[0,0],[0,0]],"o":[[0,0],[0,0],[0,0]],"v":[[-129.5,-71.5],[-153.966,24.25],[-66.5,82.5]],"c":false}]},{"i":{"x":0.833,"y":0.833},"o":{"x":0.167,"y":0.167},"t":192,"s":[{"i":[[0,0],[0,0],[0,0]],"o":[[0,0],[0,0],[0,0]],"v":[[-129.5,-71.5],[-153.966,24.25],[-66.5,82.5]],"c":false}]},{"t":194,"s":[{"i":[[0,0],[0,0],[0,0]],"o":[[0,0],[0,0],[0,0]],"v":[[-129.5,-71.5],[-95.5,8],[-66.5,82.5]],"c":false}]}],"ix":2},"nm":"Path 1","mn":"ADBE Vector Shape - Group","hd":false},{"ty":"st","c":{"a":0,"k":[0.333333333333,0.211764705882,0.145098039216,1],"ix":3},"o":{"a":0,"k":100,"ix":4},"w":{"a":0,"k":2,"ix":5},"lc":1,"lj":1,"ml":4,"bm":0,"nm":"Stroke 1","mn":"ADBE Vector Graphic - Stroke","hd":false},{"ty":"tr","p":{"a":0,"k":[0,0],"ix":2},"a":{"a":0,"k":[0,0],"ix":1},"s":{"a":0,"k":[100,100],"ix":3},"r":{"a":0,"k":0,"ix":6},"o":{"a":0,"k":100,"ix":7},"sk":{"a":0,"k":0,"ix":4},"sa":{"a":0,"k":0,"ix":5},"nm":"Transform"}],"nm":"Shape 2","np":3,"cix":2,"bm":0,"ix":1,"mn":"ADBE Vector Group","hd":false},{"ty":"gr","it":[{"ind":0,"ty":"sh","ix":1,"ks":{"a":0,"k":{"i":[[0,0],[67,-129]],"o":[[0,0],[-67,129]],"v":[[-130,-72],[-66,83]],"c":false},"ix":2},"nm":"Path 1","mn":"ADBE Vector Shape - Group","hd":false},{"ty":"st","c":{"a":0,"k":[0.333333333333,0.211764705882,0.145098039216,1],"ix":3},"o":{"a":0,"k":100,"ix":4},"w":{"a":0,"k":7,"ix":5},"lc":2,"lj":2,"bm":0,"nm":"Stroke 1","mn":"ADBE Vector Graphic - Stroke","hd":false},{"ty":"tr","p":{"a":0,"k":[0,0],"ix":2},"a":{"a":0,"k":[0,0],"ix":1},"s":{"a":0,"k":[100,100],"ix":3},"r":{"a":0,"k":0,"ix":6},"o":{"a":0,"k":100,"ix":7},"sk":{"a":0,"k":0,"ix":4},"sa":{"a":0,"k":0,"ix":5},"nm":"Transform"}],"nm":"Shape 1","np":3,"cix":2,"bm":0,"ix":2,"mn":"ADBE Vector Group","hd":false}],"ip":0,"op":1050,"st":0,"bm":0},{"ddd":0,"ind":10,"ty":4,"nm":"Buttons","parent":15,"sr":1,"ks":{"o":{"a":0,"k":100,"ix":11},"r":{"a":0,"k":0,"ix":10},"p":{"a":0,"k":[2.562,183.33,0],"ix":2,"l":2},"a":{"a":0,"k":[-28.688,126.938,0],"ix":1,"l":2},"s":{"a":0,"k":[100,100,100],"ix":6,"l":2}},"ao":0,"ef":[{"ty":21,"nm":"Fill","np":9,"mn":"ADBE Fill","ix":1,"en":1,"ef":[{"ty":10,"nm":"Fill Mask","mn":"ADBE Fill-0001","ix":1,"v":{"a":0,"k":0,"ix":1}},{"ty":7,"nm":"All Masks","mn":"ADBE Fill-0007","ix":2,"v":{"a":0,"k":0,"ix":2}},{"ty":2,"nm":"Color","mn":"ADBE Fill-0002","ix":3,"v":{"a":0,"k":[1,0,0,1],"ix":3,"x":"var $bm_rt;\nif (comp('i Miss Suit').layer('Local Color Control').effect('Global Colors')(1) == 1)\n    $bm_rt = comp('!Global Control').layer('Buttons').effect('Fill')('Color');\nelse\n    $bm_rt = comp('i Miss Suit').layer('Local Color Control').effect('Buttons')('Color');"}},{"ty":7,"nm":"Invert","mn":"ADBE Fill-0006","ix":4,"v":{"a":0,"k":0,"ix":4}},{"ty":0,"nm":"Horizontal Feather","mn":"ADBE Fill-0003","ix":5,"v":{"a":0,"k":0,"ix":5}},{"ty":0,"nm":"Vertical Feather","mn":"ADBE Fill-0004","ix":6,"v":{"a":0,"k":0,"ix":6}},{"ty":0,"nm":"Opacity","mn":"ADBE Fill-0005","ix":7,"v":{"a":0,"k":1,"ix":7}}]}],"shapes":[{"ty":"gr","it":[{"d":1,"ty":"el","s":{"a":0,"k":[12.25,12.25],"ix":2},"p":{"a":0,"k":[0,0],"ix":3},"nm":"Ellipse Path 1","mn":"ADBE Vector Shape - Ellipse","hd":false},{"ty":"fl","c":{"a":0,"k":[0.282352941176,0.282352941176,0.282352941176,1],"ix":4},"o":{"a":0,"k":100,"ix":5},"r":1,"bm":0,"nm":"Fill 1","mn":"ADBE Vector Graphic - Fill","hd":false},{"ty":"tr","p":{"a":0,"k":[-28,141.25],"ix":2},"a":{"a":0,"k":[0,0],"ix":1},"s":{"a":0,"k":[100,100],"ix":3},"r":{"a":0,"k":0,"ix":6},"o":{"a":0,"k":100,"ix":7},"sk":{"a":0,"k":0,"ix":4},"sa":{"a":0,"k":0,"ix":5},"nm":"Transform"}],"nm":"Bot button","np":3,"cix":2,"bm":0,"ix":1,"mn":"ADBE Vector Group","hd":false},{"ty":"gr","it":[{"d":1,"ty":"el","s":{"a":0,"k":[12.25,12.25],"ix":2},"p":{"a":0,"k":[0,0],"ix":3},"nm":"Ellipse Path 1","mn":"ADBE Vector Shape - Ellipse","hd":false},{"ty":"fl","c":{"a":0,"k":[0.282352941176,0.282352941176,0.282352941176,1],"ix":4},"o":{"a":0,"k":100,"ix":5},"r":1,"bm":0,"nm":"Fill 1","mn":"ADBE Vector Graphic - Fill","hd":false},{"ty":"tr","p":{"a":0,"k":[-29.375,112.625],"ix":2},"a":{"a":0,"k":[0,0],"ix":1},"s":{"a":0,"k":[100,100],"ix":3},"r":{"a":0,"k":0,"ix":6},"o":{"a":0,"k":100,"ix":7},"sk":{"a":0,"k":0,"ix":4},"sa":{"a":0,"k":0,"ix":5},"nm":"Transform"}],"nm":"Top button","np":3,"cix":2,"bm":0,"ix":2,"mn":"ADBE Vector Group","hd":false}],"ip":0,"op":1071.07107107107,"st":0,"bm":0},{"ddd":0,"ind":11,"ty":4,"nm":"Collar","parent":15,"sr":1,"ks":{"o":{"a":0,"k":100,"ix":11},"r":{"a":0,"k":0,"ix":10},"p":{"a":0,"k":[0.347,91.643,0],"ix":2,"l":2},"a":{"a":0,"k":[2.25,91.75,0],"ix":1,"l":2},"s":{"a":0,"k":[100,100,100],"ix":6,"l":2}},"ao":0,"ef":[{"ty":21,"nm":"Fill","np":9,"mn":"ADBE Fill","ix":1,"en":1,"ef":[{"ty":10,"nm":"Fill Mask","mn":"ADBE Fill-0001","ix":1,"v":{"a":0,"k":0,"ix":1}},{"ty":7,"nm":"All Masks","mn":"ADBE Fill-0007","ix":2,"v":{"a":0,"k":0,"ix":2}},{"ty":2,"nm":"Color","mn":"ADBE Fill-0002","ix":3,"v":{"a":0,"k":[1,0,0,1],"ix":3,"x":"var $bm_rt;\nif (comp('i Miss Suit').layer('Local Color Control').effect('Global Colors')(1) == 1)\n    $bm_rt = comp('!Global Control').layer('Collar').effect('Fill')('Color');\nelse\n    $bm_rt = comp('i Miss Suit').layer('Local Color Control').effect('Collar')('Color');"}},{"ty":7,"nm":"Invert","mn":"ADBE Fill-0006","ix":4,"v":{"a":0,"k":0,"ix":4}},{"ty":0,"nm":"Horizontal Feather","mn":"ADBE Fill-0003","ix":5,"v":{"a":0,"k":0,"ix":5}},{"ty":0,"nm":"Vertical Feather","mn":"ADBE Fill-0004","ix":6,"v":{"a":0,"k":0,"ix":6}},{"ty":0,"nm":"Opacity","mn":"ADBE Fill-0005","ix":7,"v":{"a":0,"k":1,"ix":7}}]}],"shapes":[{"ty":"gr","it":[{"ind":0,"ty":"sh","ix":1,"ks":{"a":0,"k":{"i":[[0,0],[0,0],[0,0],[0,0],[0,0]],"o":[[0,0],[0,0],[0,0],[0,0],[0,0]],"v":[[-66.125,46.5],[-66.75,85.125],[-45.25,90.125],[-48.625,119],[-0.312,136.125]],"c":true},"ix":2},"nm":"Path 1","mn":"ADBE Vector Shape - Group","hd":false},{"ty":"fl","c":{"a":0,"k":[0.2588239782,0.2588239782,0.2588239782,1],"ix":4},"o":{"a":0,"k":100,"ix":5},"r":1,"bm":0,"nm":"Fill 1","mn":"ADBE Vector Graphic - Fill","hd":false},{"ty":"tr","p":{"a":0,"k":[0,0],"ix":2},"a":{"a":0,"k":[0,0],"ix":1},"s":{"a":0,"k":[100,100],"ix":3},"r":{"a":0,"k":0,"ix":6},"o":{"a":0,"k":100,"ix":7},"sk":{"a":0,"k":0,"ix":4},"sa":{"a":0,"k":0,"ix":5},"nm":"Transform"}],"nm":"Left collar","np":3,"cix":2,"bm":0,"ix":1,"mn":"ADBE Vector Group","hd":false},{"ty":"gr","it":[{"ind":0,"ty":"sh","ix":1,"ks":{"a":0,"k":{"i":[[0,0],[0,0],[0,0],[0,0],[0,0]],"o":[[0,0],[0,0],[0,0],[0,0],[0,0]],"v":[[71.25,47.375],[0.5,137],[47.875,114.375],[47.5,93.25],[69.625,85.25]],"c":true},"ix":2},"nm":"Path 1","mn":"ADBE Vector Shape - Group","hd":false},{"ty":"fl","c":{"a":0,"k":[0.282352941176,0.282352941176,0.282352941176,1],"ix":4},"o":{"a":0,"k":100,"ix":5},"r":1,"bm":0,"nm":"Fill 1","mn":"ADBE Vector Graphic - Fill","hd":false},{"ty":"tr","p":{"a":0,"k":[0,0],"ix":2},"a":{"a":0,"k":[0,0],"ix":1},"s":{"a":0,"k":[100,100],"ix":3},"r":{"a":0,"k":0,"ix":6},"o":{"a":0,"k":100,"ix":7},"sk":{"a":0,"k":0,"ix":4},"sa":{"a":0,"k":0,"ix":5},"nm":"Transform"}],"nm":"Right collar","np":3,"cix":2,"bm":0,"ix":2,"mn":"ADBE Vector Group","hd":false}],"ip":0,"op":1071.07107107107,"st":0,"bm":0},{"ddd":0,"ind":12,"ty":4,"nm":"Mask tie","parent":15,"td":1,"sr":1,"ks":{"o":{"a":0,"k":100,"ix":11},"r":{"a":0,"k":0,"ix":10},"p":{"a":0,"k":[0.518,91.08,0],"ix":2,"l":2},"a":{"a":0,"k":[2.422,91.188,0],"ix":1,"l":2},"s":{"a":0,"k":[100,100,100],"ix":6,"l":2}},"ao":0,"shapes":[{"ty":"gr","it":[{"ind":0,"ty":"sh","ix":1,"ks":{"a":0,"k":{"i":[[0,0],[0,0],[0,0]],"o":[[0,0],[0,0],[0,0]],"v":[[-66.219,45.688],[0.438,136.688],[71.062,47.062]],"c":true},"ix":2},"nm":"Path 1","mn":"ADBE Vector Shape - Group","hd":false},{"ty":"fl","c":{"a":0,"k":[1,1,1,1],"ix":4},"o":{"a":0,"k":100,"ix":5},"r":1,"bm":0,"nm":"Fill 1","mn":"ADBE Vector Graphic - Fill","hd":false},{"ty":"tr","p":{"a":0,"k":[0,0],"ix":2},"a":{"a":0,"k":[0,0],"ix":1},"s":{"a":0,"k":[100,100],"ix":3},"r":{"a":0,"k":0,"ix":6},"o":{"a":0,"k":100,"ix":7},"sk":{"a":0,"k":0,"ix":4},"sa":{"a":0,"k":0,"ix":5},"nm":"Transform"}],"nm":"Suit Shirt","np":3,"cix":2,"bm":0,"ix":1,"mn":"ADBE Vector Group","hd":false}],"ip":0,"op":1071.07107107107,"st":0,"bm":0},{"ddd":0,"ind":13,"ty":4,"nm":"Tie 2","parent":15,"tt":1,"sr":1,"ks":{"o":{"a":0,"k":100,"ix":11},"r":{"a":0,"k":0,"ix":10},"p":{"a":0,"k":[1.222,111.768,0],"ix":2,"l":2},"a":{"a":0,"k":[3.125,111.875,0],"ix":1,"l":2},"s":{"a":0,"k":[100,100,100],"ix":6,"l":2}},"ao":0,"ef":[{"ty":21,"nm":"Fill","np":9,"mn":"ADBE Fill","ix":1,"en":1,"ef":[{"ty":10,"nm":"Fill Mask","mn":"ADBE Fill-0001","ix":1,"v":{"a":0,"k":0,"ix":1}},{"ty":7,"nm":"All Masks","mn":"ADBE Fill-0007","ix":2,"v":{"a":0,"k":0,"ix":2}},{"ty":2,"nm":"Color","mn":"ADBE Fill-0002","ix":3,"v":{"a":0,"k":[1,0,0,1],"ix":3,"x":"var $bm_rt;\nif (comp('i Miss Suit').layer('Local Color Control').effect('Global Colors')(1) == 1)\n    $bm_rt = comp('!Global Control').layer('Tie').effect('Fill')('Color');\nelse\n    $bm_rt = comp('i Miss Suit').layer('Local Color Control').effect('Tie')('Color');"}},{"ty":7,"nm":"Invert","mn":"ADBE Fill-0006","ix":4,"v":{"a":0,"k":0,"ix":4}},{"ty":0,"nm":"Horizontal Feather","mn":"ADBE Fill-0003","ix":5,"v":{"a":0,"k":0,"ix":5}},{"ty":0,"nm":"Vertical Feather","mn":"ADBE Fill-0004","ix":6,"v":{"a":0,"k":0,"ix":6}},{"ty":0,"nm":"Opacity","mn":"ADBE Fill-0005","ix":7,"v":{"a":0,"k":1,"ix":7}}]}],"shapes":[{"ty":"gr","it":[{"ind":0,"ty":"sh","ix":1,"ks":{"a":0,"k":{"i":[[0,0],[0,0],[0,0],[0,0],[0,0],[0,0],[0,0],[0,0],[0,0]],"o":[[0,0],[0,0],[0,0],[0,0],[0,0],[0,0],[0,0],[0,0],[0,0]],"v":[[-30.5,104.625],[-34.75,111.875],[-28.875,120.75],[-40.25,201],[-18.625,219.125],[0.5,200.625],[-17.125,121.625],[-10.5,112.5],[-14.125,105.75]],"c":true},"ix":2},"nm":"Path 1","mn":"ADBE Vector Shape - Group","hd":false},{"ty":"fl","c":{"a":0,"k":[0.325490196078,0.243137254902,0.160784313725,1],"ix":4},"o":{"a":0,"k":100,"ix":5},"r":1,"bm":0,"nm":"Fill 1","mn":"ADBE Vector Graphic - Fill","hd":false},{"ty":"tr","p":{"a":0,"k":[23,-50],"ix":2},"a":{"a":0,"k":[0,0],"ix":1},"s":{"a":0,"k":[100,100],"ix":3},"r":{"a":0,"k":0,"ix":6},"o":{"a":0,"k":100,"ix":7},"sk":{"a":0,"k":0,"ix":4},"sa":{"a":0,"k":0,"ix":5},"nm":"Transform"}],"nm":"Shape 1","np":3,"cix":2,"bm":0,"ix":1,"mn":"ADBE Vector Group","hd":false}],"ip":0,"op":1071.07107107107,"st":0,"bm":0},{"ddd":0,"ind":14,"ty":4,"nm":"Shirt","parent":15,"sr":1,"ks":{"o":{"a":0,"k":100,"ix":11},"r":{"a":0,"k":0,"ix":10},"p":{"a":0,"k":[0.518,91.08,0],"ix":2,"l":2},"a":{"a":0,"k":[2.422,91.188,0],"ix":1,"l":2},"s":{"a":0,"k":[100,100,100],"ix":6,"l":2}},"ao":0,"ef":[{"ty":21,"nm":"Fill","np":9,"mn":"ADBE Fill","ix":1,"en":1,"ef":[{"ty":10,"nm":"Fill Mask","mn":"ADBE Fill-0001","ix":1,"v":{"a":0,"k":0,"ix":1}},{"ty":7,"nm":"All Masks","mn":"ADBE Fill-0007","ix":2,"v":{"a":0,"k":0,"ix":2}},{"ty":2,"nm":"Color","mn":"ADBE Fill-0002","ix":3,"v":{"a":0,"k":[1,0,0,1],"ix":3,"x":"var $bm_rt;\nif (comp('i Miss Suit').layer('Local Color Control').effect('Global Colors')(1) == 1)\n    $bm_rt = comp('!Global Control').layer('Shirt').effect('Fill')('Color');\nelse\n    $bm_rt = comp('i Miss Suit').layer('Local Color Control').effect('Shirt')('Color');"}},{"ty":7,"nm":"Invert","mn":"ADBE Fill-0006","ix":4,"v":{"a":0,"k":0,"ix":4}},{"ty":0,"nm":"Horizontal Feather","mn":"ADBE Fill-0003","ix":5,"v":{"a":0,"k":0,"ix":5}},{"ty":0,"nm":"Vertical Feather","mn":"ADBE Fill-0004","ix":6,"v":{"a":0,"k":0,"ix":6}},{"ty":0,"nm":"Opacity","mn":"ADBE Fill-0005","ix":7,"v":{"a":0,"k":1,"ix":7}}]}],"shapes":[{"ty":"gr","it":[{"ind":0,"ty":"sh","ix":1,"ks":{"a":0,"k":{"i":[[0,0],[0,0],[0,0]],"o":[[0,0],[0,0],[0,0]],"v":[[-66.219,45.688],[0.438,136.688],[71.062,47.062]],"c":true},"ix":2},"nm":"Path 1","mn":"ADBE Vector Shape - Group","hd":false},{"ty":"fl","c":{"a":0,"k":[1,1,1,1],"ix":4},"o":{"a":0,"k":100,"ix":5},"r":1,"bm":0,"nm":"Fill 1","mn":"ADBE Vector Graphic - Fill","hd":false},{"ty":"tr","p":{"a":0,"k":[0,0],"ix":2},"a":{"a":0,"k":[0,0],"ix":1},"s":{"a":0,"k":[100,100],"ix":3},"r":{"a":0,"k":0,"ix":6},"o":{"a":0,"k":100,"ix":7},"sk":{"a":0,"k":0,"ix":4},"sa":{"a":0,"k":0,"ix":5},"nm":"Transform"}],"nm":"Suit Shirt","np":3,"cix":2,"bm":0,"ix":1,"mn":"ADBE Vector Group","hd":false}],"ip":0,"op":1071.07107107107,"st":0,"bm":0},{"ddd":0,"ind":15,"ty":4,"nm":"Suit","parent":1,"sr":1,"ks":{"o":{"a":0,"k":100,"ix":11},"r":{"a":0,"k":0,"ix":10},"p":{"a":0,"k":[29.364,38.182,0],"ix":2,"l":2},"a":{"a":0,"k":[-58.889,244.444,0],"ix":1,"l":2},"s":{"a":0,"k":[-45,45,100],"ix":6,"l":2}},"ao":0,"ef":[{"ty":21,"nm":"Fill","np":9,"mn":"ADBE Fill","ix":1,"en":1,"ef":[{"ty":10,"nm":"Fill Mask","mn":"ADBE Fill-0001","ix":1,"v":{"a":0,"k":0,"ix":1}},{"ty":7,"nm":"All Masks","mn":"ADBE Fill-0007","ix":2,"v":{"a":0,"k":0,"ix":2}},{"ty":2,"nm":"Color","mn":"ADBE Fill-0002","ix":3,"v":{"a":0,"k":[1,0,0,1],"ix":3,"x":"var $bm_rt;\nif (comp('i Miss Suit').layer('Local Color Control').effect('Global Colors')(1) == 1)\n    $bm_rt = comp('!Global Control').layer('Body').effect('Fill')('Color');\nelse\n    $bm_rt = comp('i Miss Suit').layer('Local Color Control').effect('Suit')('Color');"}},{"ty":7,"nm":"Invert","mn":"ADBE Fill-0006","ix":4,"v":{"a":0,"k":0,"ix":4}},{"ty":0,"nm":"Horizontal Feather","mn":"ADBE Fill-0003","ix":5,"v":{"a":0,"k":0,"ix":5}},{"ty":0,"nm":"Vertical Feather","mn":"ADBE Fill-0004","ix":6,"v":{"a":0,"k":0,"ix":6}},{"ty":0,"nm":"Opacity","mn":"ADBE Fill-0005","ix":7,"v":{"a":0,"k":1,"ix":7}}]}],"shapes":[{"ty":"gr","it":[{"ind":0,"ty":"sh","ix":1,"ks":{"a":0,"k":{"i":[[0,0],[-1.625,-19.625],[0,0],[0,0],[38.448,0.536],[54.553,-31.703],[0.775,1.058]],"o":[[0,0],[14,14.5],[0,0],[0,0],[-45.139,25.333],[-20.552,11.944],[-2.876,0.127]],"v":[[-85.25,45.5],[-73.75,223],[122,231.25],[140.75,47.75],[69.16,46.899],[-8.157,94.878],[-66.656,45.685]],"c":true},"ix":2},"nm":"Path 1","mn":"ADBE Vector Shape - Group","hd":false},{"ty":"fl","c":{"a":0,"k":[0.101960784314,0.101960784314,0.101960784314,1],"ix":4},"o":{"a":0,"k":100,"ix":5},"r":1,"bm":0,"nm":"Fill 1","mn":"ADBE Vector Graphic - Fill","hd":false},{"ty":"tr","p":{"a":0,"k":[0,0],"ix":2},"a":{"a":0,"k":[0,0],"ix":1},"s":{"a":0,"k":[100,100],"ix":3},"r":{"a":0,"k":0,"ix":6},"o":{"a":0,"k":100,"ix":7},"sk":{"a":0,"k":0,"ix":4},"sa":{"a":0,"k":0,"ix":5},"nm":"Transform"}],"nm":"Suit","np":3,"cix":2,"bm":0,"ix":1,"mn":"ADBE Vector Group","hd":false}],"ip":0,"op":1071.07107107107,"st":0,"bm":0},{"ddd":0,"ind":16,"ty":4,"nm":"Arm","parent":15,"sr":1,"ks":{"o":{"a":0,"k":100,"ix":11},"r":{"a":0,"k":120,"ix":10},"p":{"a":0,"k":[-66.556,57.944,0],"ix":2,"l":2},"a":{"a":0,"k":[-76,63.5,0],"ix":1,"l":2},"s":{"a":0,"k":[-100,100,100],"ix":6,"l":2}},"ao":0,"ef":[{"ty":21,"nm":"Fill","np":9,"mn":"ADBE Fill","ix":1,"en":1,"ef":[{"ty":10,"nm":"Fill Mask","mn":"ADBE Fill-0001","ix":1,"v":{"a":0,"k":0,"ix":1}},{"ty":7,"nm":"All Masks","mn":"ADBE Fill-0007","ix":2,"v":{"a":0,"k":0,"ix":2}},{"ty":2,"nm":"Color","mn":"ADBE Fill-0002","ix":3,"v":{"a":0,"k":[1,0,0,1],"ix":3,"x":"var $bm_rt;\nif (comp('i Miss Suit').layer('Local Color Control').effect('Global Colors')(1) == 1)\n    $bm_rt = comp('!Global Control').layer('Body').effect('Fill')('Color');\nelse\n    $bm_rt = comp('i Miss Suit').layer('Local Color Control').effect('Suit')('Color');"}},{"ty":7,"nm":"Invert","mn":"ADBE Fill-0006","ix":4,"v":{"a":0,"k":0,"ix":4}},{"ty":0,"nm":"Horizontal Feather","mn":"ADBE Fill-0003","ix":5,"v":{"a":0,"k":0,"ix":5}},{"ty":0,"nm":"Vertical Feather","mn":"ADBE Fill-0004","ix":6,"v":{"a":0,"k":0,"ix":6}},{"ty":0,"nm":"Opacity","mn":"ADBE Fill-0005","ix":7,"v":{"a":0,"k":1,"ix":7}}]}],"shapes":[{"ty":"gr","it":[{"ty":"st","c":{"a":0,"k":[0.992156862745,0.862745098039,0.745098039216,1],"ix":3},"o":{"a":0,"k":100,"ix":4},"w":{"a":0,"k":25,"ix":5},"lc":1,"lj":1,"ml":4,"bm":0,"nm":"Stroke 1","mn":"ADBE Vector Graphic - Stroke","hd":false},{"ty":"tr","p":{"a":0,"k":[0,0],"ix":2},"a":{"a":0,"k":[0,0],"ix":1},"s":{"a":0,"k":[100,100],"ix":3},"r":{"a":0,"k":0,"ix":6},"o":{"a":0,"k":100,"ix":7},"sk":{"a":0,"k":0,"ix":4},"sa":{"a":0,"k":0,"ix":5},"nm":"Transform"}],"nm":"Shape 2","np":2,"cix":2,"bm":0,"ix":1,"mn":"ADBE Vector Group","hd":false},{"ty":"gr","it":[{"ind":0,"ty":"sh","ix":1,"ks":{"a":0,"k":{"i":[[0,0],[-1.079,-147.444]],"o":[[0,0],[1.084,148.05]],"v":[[-75.5,64],[-122.781,218.14]],"c":false},"ix":2},"nm":"Path 1","mn":"ADBE Vector Shape - Group","hd":false},{"ty":"st","c":{"a":0,"k":[0.992156862745,0.862745098039,0.745098039216,1],"ix":3},"o":{"a":0,"k":100,"ix":4},"w":{"a":0,"k":25,"ix":5},"lc":1,"lj":1,"ml":4,"bm":0,"nm":"Stroke 1","mn":"ADBE Vector Graphic - Stroke","hd":false},{"ty":"tr","p":{"a":0,"k":[0,0],"ix":2},"a":{"a":0,"k":[0,0],"ix":1},"s":{"a":0,"k":[100,100],"ix":3},"r":{"a":0,"k":0,"ix":6},"o":{"a":0,"k":100,"ix":7},"sk":{"a":0,"k":0,"ix":4},"sa":{"a":0,"k":0,"ix":5},"nm":"Transform"}],"nm":"Shape 1","np":3,"cix":2,"bm":0,"ix":2,"mn":"ADBE Vector Group","hd":false}],"ip":0,"op":1071.07107107107,"st":0,"bm":0},{"ddd":0,"ind":17,"ty":4,"nm":"Sleeve","parent":18,"sr":1,"ks":{"o":{"a":0,"k":100,"ix":11},"r":{"a":0,"k":11.285,"ix":10},"p":{"a":0,"k":[169.996,223.679,0],"ix":2,"l":2},"a":{"a":0,"k":[169.875,219.875,0],"ix":1,"l":2},"s":{"a":0,"k":[-94.746,95.86,100],"ix":6,"l":2}},"ao":0,"ef":[{"ty":21,"nm":"Fill","np":9,"mn":"ADBE Fill","ix":1,"en":1,"ef":[{"ty":10,"nm":"Fill Mask","mn":"ADBE Fill-0001","ix":1,"v":{"a":0,"k":0,"ix":1}},{"ty":7,"nm":"All Masks","mn":"ADBE Fill-0007","ix":2,"v":{"a":0,"k":0,"ix":2}},{"ty":2,"nm":"Color","mn":"ADBE Fill-0002","ix":3,"v":{"a":0,"k":[1,0,0,1],"ix":3,"x":"var $bm_rt;\nif (comp('i Miss Suit').layer('Local Color Control').effect('Global Colors')(1) == 1)\n    $bm_rt = comp('!Global Control').layer('Shirt').effect('Fill')('Color');\nelse\n    $bm_rt = comp('i Miss Suit').layer('Local Color Control').effect('Shirt')('Color');"}},{"ty":7,"nm":"Invert","mn":"ADBE Fill-0006","ix":4,"v":{"a":0,"k":0,"ix":4}},{"ty":0,"nm":"Horizontal Feather","mn":"ADBE Fill-0003","ix":5,"v":{"a":0,"k":0,"ix":5}},{"ty":0,"nm":"Vertical Feather","mn":"ADBE Fill-0004","ix":6,"v":{"a":0,"k":0,"ix":6}},{"ty":0,"nm":"Opacity","mn":"ADBE Fill-0005","ix":7,"v":{"a":0,"k":1,"ix":7}}]}],"shapes":[{"ty":"gr","it":[{"ty":"rc","d":1,"s":{"a":0,"k":[25.25,8.25],"ix":2},"p":{"a":0,"k":[0,0],"ix":3},"r":{"a":0,"k":0,"ix":4},"nm":"Rectangle Path 1","mn":"ADBE Vector Shape - Rect","hd":false},{"ty":"fl","c":{"a":0,"k":[1,1,1,1],"ix":4},"o":{"a":0,"k":100,"ix":5},"r":1,"bm":0,"nm":"Fill 1","mn":"ADBE Vector Graphic - Fill","hd":false},{"ty":"tr","p":{"a":0,"k":[169.875,219.875],"ix":2},"a":{"a":0,"k":[0,0],"ix":1},"s":{"a":0,"k":[100,100],"ix":3},"r":{"a":0,"k":0,"ix":6},"o":{"a":0,"k":100,"ix":7},"sk":{"a":0,"k":0,"ix":4},"sa":{"a":0,"k":0,"ix":5},"nm":"Transform"}],"nm":"Rectangle 1","np":3,"cix":2,"bm":0,"ix":1,"mn":"ADBE Vector Group","hd":false}],"ip":0,"op":1071.07107107107,"st":0,"bm":0},{"ddd":0,"ind":18,"ty":4,"nm":"Hand","parent":16,"sr":1,"ks":{"o":{"a":0,"k":100,"ix":11},"r":{"a":0,"k":-10,"ix":10},"p":{"a":0,"k":[-123.5,228.5,0],"ix":2,"l":2},"a":{"a":0,"k":[167.434,235.08,0],"ix":1,"l":2},"s":{"a":0,"k":[99.911,97.087,100],"ix":6,"l":2}},"ao":0,"ef":[{"ty":21,"nm":"Fill","np":9,"mn":"ADBE Fill","ix":1,"en":1,"ef":[{"ty":10,"nm":"Fill Mask","mn":"ADBE Fill-0001","ix":1,"v":{"a":0,"k":0,"ix":1}},{"ty":7,"nm":"All Masks","mn":"ADBE Fill-0007","ix":2,"v":{"a":0,"k":0,"ix":2}},{"ty":2,"nm":"Color","mn":"ADBE Fill-0002","ix":3,"v":{"a":0,"k":[1,0,0,1],"ix":3,"x":"var $bm_rt;\nif (comp('i Miss Suit').layer('Local Color Control').effect('Global Colors')(1) == 1)\n    $bm_rt = comp('!Global Control').layer('Skin 2').effect('Fill')('Color');\nelse\n    $bm_rt = comp('i Miss Suit').layer('Local Color Control').effect('Skin')('Color');"}},{"ty":7,"nm":"Invert","mn":"ADBE Fill-0006","ix":4,"v":{"a":0,"k":0,"ix":4}},{"ty":0,"nm":"Horizontal Feather","mn":"ADBE Fill-0003","ix":5,"v":{"a":0,"k":0,"ix":5}},{"ty":0,"nm":"Vertical Feather","mn":"ADBE Fill-0004","ix":6,"v":{"a":0,"k":0,"ix":6}},{"ty":0,"nm":"Opacity","mn":"ADBE Fill-0005","ix":7,"v":{"a":0,"k":1,"ix":7}}]}],"shapes":[{"ty":"gr","it":[{"ind":0,"ty":"sh","ix":1,"ks":{"a":0,"k":{"i":[[0,0],[-3.952,-0.898],[0,0],[-2.125,-1.625],[0,0],[-3.125,-1.25],[0,0],[-2.75,-0.838],[0,0],[0,0]],"o":[[0,0],[2.709,0.615],[0,0],[2.125,1.625],[0,0],[3.125,1.25],[0,0],[3.873,1.18],[0,0],[0,0]],"v":[[157.285,219.807],[154.75,243.375],[159.375,240.424],[160.188,245.356],[165.125,242.219],[167,247.598],[172,243.863],[174.25,249.227],[178.438,245.371],[181.612,224.07]],"c":true},"ix":2},"nm":"Path 1","mn":"ADBE Vector Shape - Group","hd":false},{"ty":"fl","c":{"a":0,"k":[0.992156862745,0.862745098039,0.745098039216,1],"ix":4},"o":{"a":0,"k":100,"ix":5},"r":1,"bm":0,"nm":"Fill 1","mn":"ADBE Vector Graphic - Fill","hd":false},{"ty":"tr","p":{"a":0,"k":[0,0],"ix":2},"a":{"a":0,"k":[0,0],"ix":1},"s":{"a":0,"k":[100,100],"ix":3},"r":{"a":0,"k":0,"ix":6},"o":{"a":0,"k":100,"ix":7},"sk":{"a":0,"k":0,"ix":4},"sa":{"a":0,"k":0,"ix":5},"nm":"Transform"}],"nm":"Hand","np":3,"cix":2,"bm":0,"ix":1,"mn":"ADBE Vector Group","hd":false}],"ip":0,"op":1071.07107107107,"st":0,"bm":0},{"ddd":0,"ind":19,"ty":4,"nm":"Pants","parent":15,"sr":1,"ks":{"o":{"a":0,"k":100,"ix":11},"r":{"a":0,"k":0,"ix":10},"p":{"a":0,"k":[-27.75,58,0],"ix":2,"l":2},"a":{"a":0,"k":[0,0,0],"ix":1,"l":2},"s":{"a":0,"k":[-100,100,100],"ix":6,"l":2}},"ao":0,"ef":[{"ty":21,"nm":"Fill","np":9,"mn":"ADBE Fill","ix":1,"en":1,"ef":[{"ty":10,"nm":"Fill Mask","mn":"ADBE Fill-0001","ix":1,"v":{"a":0,"k":0,"ix":1}},{"ty":7,"nm":"All Masks","mn":"ADBE Fill-0007","ix":2,"v":{"a":0,"k":0,"ix":2}},{"ty":2,"nm":"Color","mn":"ADBE Fill-0002","ix":3,"v":{"a":0,"k":[1,0,0,1],"ix":3,"x":"var $bm_rt;\nif (comp('i Miss Suit').layer('Local Color Control').effect('Global Colors')(1) == 1)\n    $bm_rt = comp('!Global Control').layer('Pants').effect('Fill')('Color');\nelse\n    $bm_rt = comp('i Miss Suit').layer('Local Color Control').effect('Pants')('Color');"}},{"ty":7,"nm":"Invert","mn":"ADBE Fill-0006","ix":4,"v":{"a":0,"k":0,"ix":4}},{"ty":0,"nm":"Horizontal Feather","mn":"ADBE Fill-0003","ix":5,"v":{"a":0,"k":0,"ix":5}},{"ty":0,"nm":"Vertical Feather","mn":"ADBE Fill-0004","ix":6,"v":{"a":0,"k":0,"ix":6}},{"ty":0,"nm":"Opacity","mn":"ADBE Fill-0005","ix":7,"v":{"a":0,"k":1,"ix":7}}]}],"shapes":[{"ty":"gr","it":[{"ind":0,"ty":"sh","ix":1,"ks":{"a":0,"k":{"i":[[0,0],[0,0],[-2.25,-9.75],[-37.375,12.25]],"o":[[0,0],[0,0],[47.75,16.375],[1.25,-14.125]],"v":[[45.75,163.375],[-149.25,173.125],[-147.625,185.25],[45.625,179]],"c":true},"ix":2},"nm":"Path 1","mn":"ADBE Vector Shape - Group","hd":false},{"ty":"fl","c":{"a":0,"k":[0.101960784314,0.101960784314,0.101960784314,1],"ix":4},"o":{"a":0,"k":100,"ix":5},"r":1,"bm":0,"nm":"Fill 1","mn":"ADBE Vector Graphic - Fill","hd":false},{"ty":"tr","p":{"a":0,"k":[0,0],"ix":2},"a":{"a":0,"k":[0,0],"ix":1},"s":{"a":0,"k":[100,100],"ix":3},"r":{"a":0,"k":0,"ix":6},"o":{"a":0,"k":100,"ix":7},"sk":{"a":0,"k":0,"ix":4},"sa":{"a":0,"k":0,"ix":5},"nm":"Transform"}],"nm":"Shape 1","np":3,"cix":2,"bm":0,"ix":1,"mn":"ADBE Vector Group","hd":false}],"ip":0,"op":1051.05105105105,"st":0,"bm":0},{"ddd":0,"ind":20,"ty":4,"nm":"Right thigh","parent":19,"sr":1,"ks":{"o":{"a":0,"k":100,"ix":11},"r":{"a":1,"k":[{"i":{"x":[0.833],"y":[0.833]},"o":{"x":[0.167],"y":[0.167]},"t":0,"s":[-21]},{"i":{"x":[0.833],"y":[0.833]},"o":{"x":[0.167],"y":[0.167]},"t":12.012,"s":[21]},{"i":{"x":[0.833],"y":[0.833]},"o":{"x":[0.167],"y":[0.167]},"t":25.025,"s":[-21]},{"i":{"x":[0.833],"y":[0.833]},"o":{"x":[0.167],"y":[0.167]},"t":37.023,"s":[21]},{"t":45.044921875,"s":[-6.3]}],"ix":10},"p":{"a":0,"k":[32.302,175.424,0],"ix":2,"l":2},"a":{"a":0,"k":[-134.948,181.549,0],"ix":1,"l":2},"s":{"a":0,"k":[100,100,100],"ix":6,"l":2}},"ao":0,"ef":[{"ty":21,"nm":"Fill","np":9,"mn":"ADBE Fill","ix":1,"en":1,"ef":[{"ty":10,"nm":"Fill Mask","mn":"ADBE Fill-0001","ix":1,"v":{"a":0,"k":0,"ix":1}},{"ty":7,"nm":"All Masks","mn":"ADBE Fill-0007","ix":2,"v":{"a":0,"k":0,"ix":2}},{"ty":2,"nm":"Color","mn":"ADBE Fill-0002","ix":3,"v":{"a":0,"k":[1,0,0,1],"ix":3,"x":"var $bm_rt;\nif (comp('i Miss Suit').layer('Local Color Control').effect('Global Colors')(1) == 1)\n    $bm_rt = comp('!Global Control').layer('Pants').effect('Fill')('Color');\nelse\n    $bm_rt = comp('i Miss Suit').layer('Local Color Control').effect('Pants')('Color');"}},{"ty":7,"nm":"Invert","mn":"ADBE Fill-0006","ix":4,"v":{"a":0,"k":0,"ix":4}},{"ty":0,"nm":"Horizontal Feather","mn":"ADBE Fill-0003","ix":5,"v":{"a":0,"k":0,"ix":5}},{"ty":0,"nm":"Vertical Feather","mn":"ADBE Fill-0004","ix":6,"v":{"a":0,"k":0,"ix":6}},{"ty":0,"nm":"Opacity","mn":"ADBE Fill-0005","ix":7,"v":{"a":0,"k":1,"ix":7}}]}],"shapes":[{"ty":"gr","it":[{"ind":0,"ty":"sh","ix":1,"ks":{"a":0,"k":{"i":[[0.392,10.493],[-2.375,-14.125],[-0.625,-12.625],[-1.125,14.625]],"o":[[-0.625,-16.75],[1.582,9.408],[0.625,12.625],[1.125,-14.625]],"v":[[-122.5,186],[-147.875,187.375],[-143.625,230.625],[-125.25,230.375]],"c":true},"ix":2},"nm":"Path 1","mn":"ADBE Vector Shape - Group","hd":false},{"ty":"fl","c":{"a":0,"k":[0.101960784314,0.101960784314,0.101960784314,1],"ix":4},"o":{"a":0,"k":100,"ix":5},"r":1,"bm":0,"nm":"Fill 1","mn":"ADBE Vector Graphic - Fill","hd":false},{"ty":"tr","p":{"a":0,"k":[0,0],"ix":2},"a":{"a":0,"k":[0,0],"ix":1},"s":{"a":0,"k":[100,100],"ix":3},"r":{"a":0,"k":0,"ix":6},"o":{"a":0,"k":100,"ix":7},"sk":{"a":0,"k":0,"ix":4},"sa":{"a":0,"k":0,"ix":5},"nm":"Transform"}],"nm":"Shape 1","np":3,"cix":2,"bm":0,"ix":1,"mn":"ADBE Vector Group","hd":false}],"ip":0,"op":1051.05105105105,"st":0,"bm":0},{"ddd":0,"ind":21,"ty":4,"nm":"Right leg","parent":20,"sr":1,"ks":{"o":{"a":0,"k":100,"ix":11},"r":{"a":1,"k":[{"i":{"x":[0.833],"y":[0.833]},"o":{"x":[0.167],"y":[0.167]},"t":0,"s":[-8]},{"i":{"x":[0.833],"y":[0.833]},"o":{"x":[0.167],"y":[0.167]},"t":12.012,"s":[23]},{"i":{"x":[0.833],"y":[0.833]},"o":{"x":[0.167],"y":[0.167]},"t":25.025,"s":[-8]},{"i":{"x":[0.833],"y":[0.833]},"o":{"x":[0.167],"y":[0.167]},"t":37.023,"s":[23]},{"t":45.044921875,"s":[2.85]}],"ix":10},"p":{"a":0,"k":[-134.56,233.48,0],"ix":2,"l":2},"a":{"a":0,"k":[-134.185,234.105,0],"ix":1,"l":2},"s":{"a":0,"k":[100,100,100],"ix":6,"l":2}},"ao":0,"ef":[{"ty":21,"nm":"Fill","np":9,"mn":"ADBE Fill","ix":1,"en":1,"ef":[{"ty":10,"nm":"Fill Mask","mn":"ADBE Fill-0001","ix":1,"v":{"a":0,"k":0,"ix":1}},{"ty":7,"nm":"All Masks","mn":"ADBE Fill-0007","ix":2,"v":{"a":0,"k":0,"ix":2}},{"ty":2,"nm":"Color","mn":"ADBE Fill-0002","ix":3,"v":{"a":0,"k":[1,0,0,1],"ix":3,"x":"var $bm_rt;\nif (comp('i Miss Suit').layer('Local Color Control').effect('Global Colors')(1) == 1)\n    $bm_rt = comp('!Global Control').layer('Pants').effect('Fill')('Color');\nelse\n    $bm_rt = comp('i Miss Suit').layer('Local Color Control').effect('Pants')('Color');"}},{"ty":7,"nm":"Invert","mn":"ADBE Fill-0006","ix":4,"v":{"a":0,"k":0,"ix":4}},{"ty":0,"nm":"Horizontal Feather","mn":"ADBE Fill-0003","ix":5,"v":{"a":0,"k":0,"ix":5}},{"ty":0,"nm":"Vertical Feather","mn":"ADBE Fill-0004","ix":6,"v":{"a":0,"k":0,"ix":6}},{"ty":0,"nm":"Opacity","mn":"ADBE Fill-0005","ix":7,"v":{"a":0,"k":1,"ix":7}}]}],"shapes":[{"ty":"gr","it":[{"ind":0,"ty":"sh","ix":1,"ks":{"a":0,"k":{"i":[[-1.76,6.747],[0.5,-13.625],[0,0],[3.375,11.625],[0,0]],"o":[[2.25,-8.625],[-0.276,7.512],[0,0],[-11.462,-39.48],[0,0]],"v":[[-125.5,233.75],[-144,234.5],[-151.5,299.25],[-91,300],[-138,284]],"c":true},"ix":2},"nm":"Path 1","mn":"ADBE Vector Shape - Group","hd":false},{"ty":"fl","c":{"a":0,"k":[0.101960784314,0.101960784314,0.101960784314,1],"ix":4},"o":{"a":0,"k":100,"ix":5},"r":1,"bm":0,"nm":"Fill 1","mn":"ADBE Vector Graphic - Fill","hd":false},{"ty":"tr","p":{"a":0,"k":[0,0],"ix":2},"a":{"a":0,"k":[0,0],"ix":1},"s":{"a":0,"k":[100,100],"ix":3},"r":{"a":0,"k":0,"ix":6},"o":{"a":0,"k":100,"ix":7},"sk":{"a":0,"k":0,"ix":4},"sa":{"a":0,"k":0,"ix":5},"nm":"Transform"}],"nm":"Shape 1","np":3,"cix":2,"bm":0,"ix":1,"mn":"ADBE Vector Group","hd":false}],"ip":0,"op":1051.05105105105,"st":0,"bm":0},{"ddd":0,"ind":22,"ty":4,"nm":"Left thigh","parent":19,"sr":1,"ks":{"o":{"a":0,"k":100,"ix":11},"r":{"a":1,"k":[{"i":{"x":[0.833],"y":[0.833]},"o":{"x":[0.167],"y":[0.167]},"t":0,"s":[21]},{"i":{"x":[0.833],"y":[0.833]},"o":{"x":[0.167],"y":[0.167]},"t":12.012,"s":[-21]},{"i":{"x":[0.833],"y":[0.833]},"o":{"x":[0.167],"y":[0.167]},"t":25.025,"s":[21]},{"i":{"x":[0.833],"y":[0.833]},"o":{"x":[0.167],"y":[0.167]},"t":37.023,"s":[-21]},{"t":41.958984375,"s":[-4.2]}],"ix":10},"p":{"a":0,"k":[-132.948,180.549,0],"ix":2,"l":2},"a":{"a":0,"k":[-134.948,181.549,0],"ix":1,"l":2},"s":{"a":0,"k":[100,100,100],"ix":6,"l":2}},"ao":0,"ef":[{"ty":21,"nm":"Fill","np":9,"mn":"ADBE Fill","ix":1,"en":1,"ef":[{"ty":10,"nm":"Fill Mask","mn":"ADBE Fill-0001","ix":1,"v":{"a":0,"k":0,"ix":1}},{"ty":7,"nm":"All Masks","mn":"ADBE Fill-0007","ix":2,"v":{"a":0,"k":0,"ix":2}},{"ty":2,"nm":"Color","mn":"ADBE Fill-0002","ix":3,"v":{"a":0,"k":[1,0,0,1],"ix":3,"x":"var $bm_rt;\nif (comp('i Miss Suit').layer('Local Color Control').effect('Global Colors')(1) == 1)\n    $bm_rt = comp('!Global Control').layer('Pants').effect('Fill')('Color');\nelse\n    $bm_rt = comp('i Miss Suit').layer('Local Color Control').effect('Pants')('Color');"}},{"ty":7,"nm":"Invert","mn":"ADBE Fill-0006","ix":4,"v":{"a":0,"k":0,"ix":4}},{"ty":0,"nm":"Horizontal Feather","mn":"ADBE Fill-0003","ix":5,"v":{"a":0,"k":0,"ix":5}},{"ty":0,"nm":"Vertical Feather","mn":"ADBE Fill-0004","ix":6,"v":{"a":0,"k":0,"ix":6}},{"ty":0,"nm":"Opacity","mn":"ADBE Fill-0005","ix":7,"v":{"a":0,"k":1,"ix":7}}]}],"shapes":[{"ty":"gr","it":[{"ind":0,"ty":"sh","ix":1,"ks":{"a":0,"k":{"i":[[0.392,10.493],[-2.375,-14.125],[-0.625,-12.625],[-1.125,14.625]],"o":[[-0.625,-16.75],[1.582,9.408],[0.625,12.625],[1.125,-14.625]],"v":[[-122.5,186],[-147.875,187.375],[-143.625,230.625],[-125.25,230.375]],"c":true},"ix":2},"nm":"Path 1","mn":"ADBE Vector Shape - Group","hd":false},{"ty":"fl","c":{"a":0,"k":[0.101960784314,0.101960784314,0.101960784314,1],"ix":4},"o":{"a":0,"k":100,"ix":5},"r":1,"bm":0,"nm":"Fill 1","mn":"ADBE Vector Graphic - Fill","hd":false},{"ty":"tr","p":{"a":0,"k":[0,0],"ix":2},"a":{"a":0,"k":[0,0],"ix":1},"s":{"a":0,"k":[100,100],"ix":3},"r":{"a":0,"k":0,"ix":6},"o":{"a":0,"k":100,"ix":7},"sk":{"a":0,"k":0,"ix":4},"sa":{"a":0,"k":0,"ix":5},"nm":"Transform"}],"nm":"Shape 1","np":3,"cix":2,"bm":0,"ix":1,"mn":"ADBE Vector Group","hd":false}],"ip":0,"op":1051.05105105105,"st":0,"bm":0},{"ddd":0,"ind":23,"ty":4,"nm":"Left leg","parent":22,"sr":1,"ks":{"o":{"a":0,"k":100,"ix":11},"r":{"a":1,"k":[{"i":{"x":[0.833],"y":[0.833]},"o":{"x":[0.167],"y":[0.167]},"t":0,"s":[23]},{"i":{"x":[0.833],"y":[0.833]},"o":{"x":[0.167],"y":[0.167]},"t":12.012,"s":[-8]},{"i":{"x":[0.833],"y":[0.833]},"o":{"x":[0.167],"y":[0.167]},"t":25.025,"s":[23]},{"i":{"x":[0.833],"y":[0.833]},"o":{"x":[0.167],"y":[0.167]},"t":37.023,"s":[-8]},{"t":41.958984375,"s":[4.4]}],"ix":10},"p":{"a":0,"k":[-134.185,231.73,0],"ix":2,"l":2},"a":{"a":0,"k":[-134.185,231.73,0],"ix":1,"l":2},"s":{"a":0,"k":[100,100,100],"ix":6,"l":2}},"ao":0,"ef":[{"ty":21,"nm":"Fill","np":9,"mn":"ADBE Fill","ix":1,"en":1,"ef":[{"ty":10,"nm":"Fill Mask","mn":"ADBE Fill-0001","ix":1,"v":{"a":0,"k":0,"ix":1}},{"ty":7,"nm":"All Masks","mn":"ADBE Fill-0007","ix":2,"v":{"a":0,"k":0,"ix":2}},{"ty":2,"nm":"Color","mn":"ADBE Fill-0002","ix":3,"v":{"a":0,"k":[1,0,0,1],"ix":3,"x":"var $bm_rt;\nif (comp('i Miss Suit').layer('Local Color Control').effect('Global Colors')(1) == 1)\n    $bm_rt = comp('!Global Control').layer('Pants').effect('Fill')('Color');\nelse\n    $bm_rt = comp('i Miss Suit').layer('Local Color Control').effect('Pants')('Color');"}},{"ty":7,"nm":"Invert","mn":"ADBE Fill-0006","ix":4,"v":{"a":0,"k":0,"ix":4}},{"ty":0,"nm":"Horizontal Feather","mn":"ADBE Fill-0003","ix":5,"v":{"a":0,"k":0,"ix":5}},{"ty":0,"nm":"Vertical Feather","mn":"ADBE Fill-0004","ix":6,"v":{"a":0,"k":0,"ix":6}},{"ty":0,"nm":"Opacity","mn":"ADBE Fill-0005","ix":7,"v":{"a":0,"k":1,"ix":7}}]}],"shapes":[{"ty":"gr","it":[{"ind":0,"ty":"sh","ix":1,"ks":{"a":0,"k":{"i":[[-1.76,6.747],[0.5,-13.625],[0,0],[3.375,11.625],[0,0]],"o":[[2.25,-8.625],[-0.276,7.512],[0,0],[-11.462,-39.48],[0,0]],"v":[[-125.5,233.75],[-144,234.5],[-151.5,299.25],[-91,300],[-138,284]],"c":true},"ix":2,"x":"var $bm_rt;\nvar t1, t2, span, delta, t;\nif (numKeys > 1 && time > key(numKeys).time) {\n    t1 = key(1).time;\n    t2 = key(numKeys).time;\n    span = $bm_sub(t2, t1);\n    delta = $bm_sub(time, t2);\n    t = $bm_mod(delta, span);\n    $bm_rt = valueAtTime($bm_sum(t1, t));\n} else\n    $bm_rt = value;"},"nm":"Path 1","mn":"ADBE Vector Shape - Group","hd":false},{"ty":"fl","c":{"a":0,"k":[0.101960784314,0.101960784314,0.101960784314,1],"ix":4},"o":{"a":0,"k":100,"ix":5},"r":1,"bm":0,"nm":"Fill 1","mn":"ADBE Vector Graphic - Fill","hd":false},{"ty":"tr","p":{"a":0,"k":[0,0],"ix":2},"a":{"a":0,"k":[0,0],"ix":1},"s":{"a":0,"k":[100,100],"ix":3},"r":{"a":0,"k":0,"ix":6},"o":{"a":0,"k":100,"ix":7},"sk":{"a":0,"k":0,"ix":4},"sa":{"a":0,"k":0,"ix":5},"nm":"Transform"}],"nm":"Shape 1","np":3,"cix":2,"bm":0,"ix":1,"mn":"ADBE Vector Group","hd":false}],"ip":0,"op":1051.05105105105,"st":0,"bm":0},{"ddd":0,"ind":24,"ty":4,"nm":"Blind","parent":29,"sr":1,"ks":{"o":{"a":0,"k":100,"ix":11},"r":{"a":0,"k":0,"ix":10},"p":{"a":0,"k":[-332.137,39.011,0],"ix":2,"l":2},"a":{"a":0,"k":[0,0,0],"ix":1,"l":2},"s":{"a":0,"k":[-172.265,172.265,100],"ix":6,"l":2}},"ao":0,"shapes":[{"ty":"gr","it":[{"ind":0,"ty":"sh","ix":1,"ks":{"a":0,"k":{"i":[[0.25,6.25],[-1.75,-6.25]],"o":[[-12.25,1],[13.5,-4.75]],"v":[[-281.25,-39.5],[-293,-19.5]],"c":true},"ix":2},"nm":"Path 1","mn":"ADBE Vector Shape - Group","hd":false},{"ty":"fl","c":{"a":0,"k":[0.941176470588,0.941176470588,0.941176470588,1],"ix":4},"o":{"a":0,"k":100,"ix":5},"r":1,"bm":0,"nm":"Fill 1","mn":"ADBE Vector Graphic - Fill","hd":false},{"ty":"tr","p":{"a":0,"k":[0,0],"ix":2},"a":{"a":0,"k":[0,0],"ix":1},"s":{"a":0,"k":[100,100],"ix":3},"r":{"a":0,"k":0,"ix":6},"o":{"a":0,"k":100,"ix":7},"sk":{"a":0,"k":0,"ix":4},"sa":{"a":0,"k":0,"ix":5},"nm":"Transform"}],"nm":"Shape 3","np":3,"cix":2,"bm":0,"ix":1,"mn":"ADBE Vector Group","hd":false},{"ty":"gr","it":[{"ind":0,"ty":"sh","ix":1,"ks":{"a":0,"k":{"i":[[8,3.5],[-9.75,-4.25]],"o":[[-4.25,9.5],[2,-14.75]],"v":[[-291.25,-67.75],[-280.75,-40]],"c":true},"ix":2},"nm":"Path 1","mn":"ADBE Vector Shape - Group","hd":false},{"ty":"fl","c":{"a":0,"k":[0.941176470588,0.941176470588,0.941176470588,1],"ix":4},"o":{"a":0,"k":100,"ix":5},"r":1,"bm":0,"nm":"Fill 1","mn":"ADBE Vector Graphic - Fill","hd":false},{"ty":"tr","p":{"a":0,"k":[0,0],"ix":2},"a":{"a":0,"k":[0,0],"ix":1},"s":{"a":0,"k":[100,100],"ix":3},"r":{"a":0,"k":0,"ix":6},"o":{"a":0,"k":100,"ix":7},"sk":{"a":0,"k":0,"ix":4},"sa":{"a":0,"k":0,"ix":5},"nm":"Transform"}],"nm":"Shape 2","np":3,"cix":2,"bm":0,"ix":2,"mn":"ADBE Vector Group","hd":false},{"ty":"gr","it":[{"ind":0,"ty":"sh","ix":1,"ks":{"a":0,"k":{"i":[[2.75,6.25],[0,0],[-0.5,-5.5],[0,0],[-2.75,1.5]],"o":[[-6.75,-4.25],[0,0],[0.5,5.5],[0,0],[1.125,-4.625]],"v":[[-144.25,-57.25],[-281,-45],[-286.5,-40],[-281.75,-35.25],[-141.5,-37.019]],"c":true},"ix":2},"nm":"Path 1","mn":"ADBE Vector Shape - Group","hd":false},{"ty":"fl","c":{"a":0,"k":[0.941176470588,0.941176470588,0.941176470588,1],"ix":4},"o":{"a":0,"k":100,"ix":5},"r":1,"bm":0,"nm":"Fill 1","mn":"ADBE Vector Graphic - Fill","hd":false},{"ty":"tr","p":{"a":0,"k":[0,0],"ix":2},"a":{"a":0,"k":[0,0],"ix":1},"s":{"a":0,"k":[100,100],"ix":3},"r":{"a":0,"k":0,"ix":6},"o":{"a":0,"k":100,"ix":7},"sk":{"a":0,"k":0,"ix":4},"sa":{"a":0,"k":0,"ix":5},"nm":"Transform"}],"nm":"Shape 1","np":3,"cix":2,"bm":0,"ix":3,"mn":"ADBE Vector Group","hd":false}],"ip":0,"op":1050,"st":0,"bm":0},{"ddd":0,"ind":25,"ty":4,"nm":"Hair","parent":29,"sr":1,"ks":{"o":{"a":0,"k":100,"ix":11},"r":{"a":0,"k":0,"ix":10},"p":{"a":0,"k":[0,0,0],"ix":2,"l":2},"a":{"a":0,"k":[0,0,0],"ix":1,"l":2},"s":{"a":0,"k":[100,100,100],"ix":6,"l":2}},"ao":0,"ef":[{"ty":21,"nm":"Fill","np":9,"mn":"ADBE Fill","ix":1,"en":1,"ef":[{"ty":10,"nm":"Fill Mask","mn":"ADBE Fill-0001","ix":1,"v":{"a":0,"k":0,"ix":1}},{"ty":7,"nm":"All Masks","mn":"ADBE Fill-0007","ix":2,"v":{"a":0,"k":0,"ix":2}},{"ty":2,"nm":"Color","mn":"ADBE Fill-0002","ix":3,"v":{"a":0,"k":[1,0,0,1],"ix":3,"x":"var $bm_rt;\nif (comp('i Miss Suit').layer('Local Color Control').effect('Global Colors')(1) == 1)\n    $bm_rt = comp('!Global Control').layer('Hair').effect('Fill')('Color');\nelse\n    $bm_rt = comp('i Miss Suit').layer('Local Color Control').effect('Hair')('Color');"}},{"ty":7,"nm":"Invert","mn":"ADBE Fill-0006","ix":4,"v":{"a":0,"k":0,"ix":4}},{"ty":0,"nm":"Horizontal Feather","mn":"ADBE Fill-0003","ix":5,"v":{"a":0,"k":0,"ix":5}},{"ty":0,"nm":"Vertical Feather","mn":"ADBE Fill-0004","ix":6,"v":{"a":0,"k":0,"ix":6}},{"ty":0,"nm":"Opacity","mn":"ADBE Fill-0005","ix":7,"v":{"a":0,"k":1,"ix":7}}]}],"shapes":[{"ty":"gr","it":[{"ind":0,"ty":"sh","ix":1,"ks":{"a":0,"k":{"i":[[15,12.75],[0,0],[-0.75,2.75],[-3.5,1],[-0.174,-7.317],[23,0.25],[0,0.25],[27.759,40.25],[11,-1],[28.5,-0.75],[29.5,0.75]],"o":[[32.25,147.75],[0,0],[0.75,-2.75],[3.5,-1],[0.25,10.5],[23,53.75],[0,-0.25],[-20,-29],[-16,-34.25],[-27.242,0.717],[-19.5,0.5]],"v":[[-119.5,-192.5],[59,-86.75],[83,-42.75],[98.25,-50.75],[109.5,-39.5],[88.25,-25.25],[141,48.5],[149,-137.25],[100.5,-153.75],[20,-190.25],[-71.25,-164.25]],"c":true},"ix":2},"nm":"Path 1","mn":"ADBE Vector Shape - Group","hd":false},{"ty":"fl","c":{"a":0,"k":[0.196078431373,0.098039215686,0.03137254902,1],"ix":4},"o":{"a":0,"k":100,"ix":5},"r":1,"bm":0,"nm":"Fill 1","mn":"ADBE Vector Graphic - Fill","hd":false},{"ty":"tr","p":{"a":0,"k":[0,0],"ix":2},"a":{"a":0,"k":[0,0],"ix":1},"s":{"a":0,"k":[100,100],"ix":3},"r":{"a":0,"k":0,"ix":6},"o":{"a":0,"k":100,"ix":7},"sk":{"a":0,"k":0,"ix":4},"sa":{"a":0,"k":0,"ix":5},"nm":"Transform"}],"nm":"Shape 1","np":3,"cix":2,"bm":0,"ix":1,"mn":"ADBE Vector Group","hd":false}],"ip":0,"op":1071.07107107107,"st":0,"bm":0},{"ddd":0,"ind":26,"ty":4,"nm":"Eyebrows","parent":29,"sr":1,"ks":{"o":{"a":0,"k":0,"ix":11},"r":{"a":0,"k":15,"ix":10},"p":{"a":0,"k":[-453.632,42.205,0],"ix":2,"l":2},"a":{"a":0,"k":[0,0,0],"ix":1,"l":2},"s":{"a":0,"k":[-222.222,222.222,100],"ix":6,"l":2}},"ao":0,"ef":[{"ty":21,"nm":"Fill","np":9,"mn":"ADBE Fill","ix":1,"en":1,"ef":[{"ty":10,"nm":"Fill Mask","mn":"ADBE Fill-0001","ix":1,"v":{"a":0,"k":0,"ix":1}},{"ty":7,"nm":"All Masks","mn":"ADBE Fill-0007","ix":2,"v":{"a":0,"k":0,"ix":2}},{"ty":2,"nm":"Color","mn":"ADBE Fill-0002","ix":3,"v":{"a":0,"k":[1,0,0,1],"ix":3,"x":"var $bm_rt;\nif (comp('i Miss Suit').layer('Local Color Control').effect('Global Colors')(1) == 1)\n    $bm_rt = comp('!Global Control').layer('Hair').effect('Fill')('Color');\nelse\n    $bm_rt = comp('i Miss Suit').layer('Local Color Control').effect('Hair')('Color');"}},{"ty":7,"nm":"Invert","mn":"ADBE Fill-0006","ix":4,"v":{"a":0,"k":0,"ix":4}},{"ty":0,"nm":"Horizontal Feather","mn":"ADBE Fill-0003","ix":5,"v":{"a":0,"k":0,"ix":5}},{"ty":0,"nm":"Vertical Feather","mn":"ADBE Fill-0004","ix":6,"v":{"a":0,"k":0,"ix":6}},{"ty":0,"nm":"Opacity","mn":"ADBE Fill-0005","ix":7,"v":{"a":0,"k":1,"ix":7}}]}],"shapes":[{"ty":"gr","it":[{"ind":0,"ty":"sh","ix":1,"ks":{"a":0,"k":{"i":[[0,0]],"o":[[0,0]],"v":[[-336.625,-64.875]],"c":false},"ix":2},"nm":"Path 1","mn":"ADBE Vector Shape - Group","hd":false},{"ty":"st","c":{"a":0,"k":[0.196078431373,0.098039215686,0.03137254902,1],"ix":3},"o":{"a":0,"k":100,"ix":4},"w":{"a":0,"k":1,"ix":5},"lc":1,"lj":1,"ml":4,"bm":0,"nm":"Stroke 1","mn":"ADBE Vector Graphic - Stroke","hd":false},{"ty":"tr","p":{"a":0,"k":[0,0],"ix":2},"a":{"a":0,"k":[0,0],"ix":1},"s":{"a":0,"k":[100,100],"ix":3},"r":{"a":0,"k":0,"ix":6},"o":{"a":0,"k":100,"ix":7},"sk":{"a":0,"k":0,"ix":4},"sa":{"a":0,"k":0,"ix":5},"nm":"Transform"}],"nm":"Shape 3","np":3,"cix":2,"bm":0,"ix":1,"mn":"ADBE Vector Group","hd":false},{"ty":"gr","it":[{"ind":0,"ty":"sh","ix":1,"ks":{"a":0,"k":{"i":[[0,0],[0,0]],"o":[[0,0],[0,0]],"v":[[-169.066,-102.012],[-160.75,-93.125]],"c":false},"ix":2},"nm":"Path 1","mn":"ADBE Vector Shape - Group","hd":false},{"ty":"st","c":{"a":0,"k":[0.196078431373,0.098039215686,0.03137254902,1],"ix":3},"o":{"a":0,"k":100,"ix":4},"w":{"a":0,"k":1,"ix":5},"lc":1,"lj":1,"ml":4,"bm":0,"nm":"Stroke 1","mn":"ADBE Vector Graphic - Stroke","hd":false},{"ty":"tr","p":{"a":0,"k":[0,0],"ix":2},"a":{"a":0,"k":[0,0],"ix":1},"s":{"a":0,"k":[100,100],"ix":3},"r":{"a":0,"k":0,"ix":6},"o":{"a":0,"k":100,"ix":7},"sk":{"a":0,"k":0,"ix":4},"sa":{"a":0,"k":0,"ix":5},"nm":"Transform"}],"nm":"Shape 2","np":3,"cix":2,"bm":0,"ix":2,"mn":"ADBE Vector Group","hd":false},{"ty":"gr","it":[{"ind":0,"ty":"sh","ix":1,"ks":{"a":0,"k":{"i":[[0,0],[0,0]],"o":[[0,0],[0,0]],"v":[[-197.5,-108],[-210.125,-104]],"c":false},"ix":2},"nm":"Path 1","mn":"ADBE Vector Shape - Group","hd":false},{"ty":"st","c":{"a":0,"k":[0.196078431373,0.098039215686,0.03137254902,1],"ix":3},"o":{"a":0,"k":100,"ix":4},"w":{"a":0,"k":1,"ix":5},"lc":1,"lj":1,"ml":4,"bm":0,"nm":"Stroke 1","mn":"ADBE Vector Graphic - Stroke","hd":false},{"ty":"tr","p":{"a":0,"k":[0,0],"ix":2},"a":{"a":0,"k":[0,0],"ix":1},"s":{"a":0,"k":[100,100],"ix":3},"r":{"a":0,"k":0,"ix":6},"o":{"a":0,"k":100,"ix":7},"sk":{"a":0,"k":0,"ix":4},"sa":{"a":0,"k":0,"ix":5},"nm":"Transform"}],"nm":"Shape 1","np":3,"cix":2,"bm":0,"ix":3,"mn":"ADBE Vector Group","hd":false}],"ip":90.0900900900901,"op":1051.05105105105,"st":0,"bm":0},{"ddd":0,"ind":27,"ty":4,"nm":"Mouth","parent":29,"sr":1,"ks":{"o":{"a":0,"k":100,"ix":11},"r":{"a":0,"k":0,"ix":10},"p":{"a":0,"k":[-3.5,2.431,0],"ix":2,"l":2},"a":{"a":0,"k":[-3.5,2.431,0],"ix":1,"l":2},"s":{"a":0,"k":[100,100,100],"ix":6,"l":2}},"ao":0,"ef":[{"ty":21,"nm":"Fill","np":9,"mn":"ADBE Fill","ix":1,"en":1,"ef":[{"ty":10,"nm":"Fill Mask","mn":"ADBE Fill-0001","ix":1,"v":{"a":0,"k":0,"ix":1}},{"ty":7,"nm":"All Masks","mn":"ADBE Fill-0007","ix":2,"v":{"a":0,"k":0,"ix":2}},{"ty":2,"nm":"Color","mn":"ADBE Fill-0002","ix":3,"v":{"a":0,"k":[1,0,0,1],"ix":3,"x":"var $bm_rt;\nif (comp('i Miss Suit').layer('Local Color Control').effect('Global Colors')(1) == 1)\n    $bm_rt = comp('!Global Control').layer('Mouth').effect('Fill')('Color');\nelse\n    $bm_rt = comp('i Miss Suit').layer('Local Color Control').effect('Mouth')('Color');"}},{"ty":7,"nm":"Invert","mn":"ADBE Fill-0006","ix":4,"v":{"a":0,"k":0,"ix":4}},{"ty":0,"nm":"Horizontal Feather","mn":"ADBE Fill-0003","ix":5,"v":{"a":0,"k":0,"ix":5}},{"ty":0,"nm":"Vertical Feather","mn":"ADBE Fill-0004","ix":6,"v":{"a":0,"k":0,"ix":6}},{"ty":0,"nm":"Opacity","mn":"ADBE Fill-0005","ix":7,"v":{"a":0,"k":1,"ix":7}}]}],"shapes":[{"ty":"gr","it":[{"ind":0,"ty":"sh","ix":1,"ks":{"a":0,"k":{"i":[[25,-4.312],[-1.5,31]],"o":[[0.25,36.75],[-32.812,-6.312]],"v":[[-34,-2.75],[27,-1.5]],"c":true},"ix":2},"nm":"Path 1","mn":"ADBE Vector Shape - Group","hd":false},{"ty":"fl","c":{"a":0,"k":[0.196078431373,0.098039215686,0.03137254902,1],"ix":4},"o":{"a":0,"k":100,"ix":5},"r":1,"bm":0,"nm":"Fill 1","mn":"ADBE Vector Graphic - Fill","hd":false},{"ty":"tr","p":{"a":0,"k":[0,0],"ix":2},"a":{"a":0,"k":[0,0],"ix":1},"s":{"a":0,"k":[100,100],"ix":3},"r":{"a":0,"k":0,"ix":6},"o":{"a":0,"k":100,"ix":7},"sk":{"a":0,"k":0,"ix":4},"sa":{"a":0,"k":0,"ix":5},"nm":"Transform"}],"nm":"Shape 1","np":3,"cix":2,"bm":0,"ix":1,"mn":"ADBE Vector Group","hd":false}],"ip":0,"op":1071.07107107107,"st":0,"bm":0},{"ddd":0,"ind":28,"ty":4,"nm":"Eyes","parent":29,"sr":1,"ks":{"o":{"a":0,"k":100,"ix":11},"r":{"a":0,"k":0,"ix":10},"p":{"a":0,"k":[-1.625,-36.5,0],"ix":2,"l":2},"a":{"a":0,"k":[-1.625,-36.5,0],"ix":1,"l":2},"s":{"a":1,"k":[{"i":{"x":[0.667,0.667,0.667],"y":[1,1,1]},"o":{"x":[0.333,0.333,0.333],"y":[0,0,0]},"t":0,"s":[100,100,100]},{"i":{"x":[0.667,0.667,0.667],"y":[1,1,1]},"o":{"x":[0.333,0.333,0.333],"y":[0,0,0]},"t":50.05,"s":[100,100,100]},{"i":{"x":[0.667,0.667,0.667],"y":[1,1,1]},"o":{"x":[0.333,0.333,0.333],"y":[0,0,0]},"t":55.055,"s":[100,25,100]},{"t":60.060546875,"s":[100,100,100]}],"ix":6,"l":2,"x":"var $bm_rt;\n$bm_rt = loopOut('cycle', 0);"}},"ao":0,"ef":[{"ty":21,"nm":"Fill","np":9,"mn":"ADBE Fill","ix":1,"en":1,"ef":[{"ty":10,"nm":"Fill Mask","mn":"ADBE Fill-0001","ix":1,"v":{"a":0,"k":0,"ix":1}},{"ty":7,"nm":"All Masks","mn":"ADBE Fill-0007","ix":2,"v":{"a":0,"k":0,"ix":2}},{"ty":2,"nm":"Color","mn":"ADBE Fill-0002","ix":3,"v":{"a":0,"k":[1,0,0,1],"ix":3,"x":"var $bm_rt;\nif (comp('i Miss Suit').layer('Local Color Control').effect('Global Colors')(1) == 1)\n    $bm_rt = comp('!Global Control').layer('Eyes').effect('Fill')('Color');\nelse\n    $bm_rt = comp('i Miss Suit').layer('Local Color Control').effect('Eyes')('Color');"}},{"ty":7,"nm":"Invert","mn":"ADBE Fill-0006","ix":4,"v":{"a":0,"k":0,"ix":4}},{"ty":0,"nm":"Horizontal Feather","mn":"ADBE Fill-0003","ix":5,"v":{"a":0,"k":0,"ix":5}},{"ty":0,"nm":"Vertical Feather","mn":"ADBE Fill-0004","ix":6,"v":{"a":0,"k":0,"ix":6}},{"ty":0,"nm":"Opacity","mn":"ADBE Fill-0005","ix":7,"v":{"a":0,"k":1,"ix":7}}]}],"shapes":[{"ty":"gr","it":[{"ind":0,"ty":"sh","ix":1,"ks":{"a":0,"k":{"i":[[0,0]],"o":[[0,0]],"v":[[-1522.491,-150.481]],"c":false},"ix":2},"nm":"Path 1","mn":"ADBE Vector Shape - Group","hd":false},{"ty":"st","c":{"a":0,"k":[0.2588239782,0.2588239782,0.2588239782,1],"ix":3},"o":{"a":0,"k":100,"ix":4},"w":{"a":0,"k":2,"ix":5},"lc":1,"lj":1,"ml":4,"bm":0,"nm":"Stroke 1","mn":"ADBE Vector Graphic - Stroke","hd":false},{"ty":"fl","c":{"a":0,"k":[0.196078431373,0.098039215686,0.03137254902,1],"ix":4},"o":{"a":0,"k":100,"ix":5},"r":1,"bm":0,"nm":"Fill 1","mn":"ADBE Vector Graphic - Fill","hd":false},{"ty":"tr","p":{"a":0,"k":[0,0],"ix":2},"a":{"a":0,"k":[0,0],"ix":1},"s":{"a":0,"k":[100,100],"ix":3},"r":{"a":0,"k":0,"ix":6},"o":{"a":0,"k":100,"ix":7},"sk":{"a":0,"k":0,"ix":4},"sa":{"a":0,"k":0,"ix":5},"nm":"Transform"}],"nm":"Shape 1","np":3,"cix":2,"bm":0,"ix":1,"mn":"ADBE Vector Group","hd":false},{"ty":"gr","it":[{"d":1,"ty":"el","s":{"a":0,"k":[12,21.25],"ix":2},"p":{"a":0,"k":[0,0],"ix":3},"nm":"Ellipse Path 1","mn":"ADBE Vector Shape - Ellipse","hd":false},{"ty":"st","c":{"a":0,"k":[0.2588239782,0.2588239782,0.2588239782,1],"ix":3},"o":{"a":0,"k":100,"ix":4},"w":{"a":0,"k":2,"ix":5},"lc":1,"lj":1,"ml":4,"bm":0,"nm":"Stroke 1","mn":"ADBE Vector Graphic - Stroke","hd":false},{"ty":"fl","c":{"a":0,"k":[0.196078431373,0.098039215686,0.03137254902,1],"ix":4},"o":{"a":0,"k":100,"ix":5},"r":1,"bm":0,"nm":"Fill 1","mn":"ADBE Vector Graphic - Fill","hd":false},{"ty":"tr","p":{"a":0,"k":[37.5,-35.625],"ix":2},"a":{"a":0,"k":[0,0],"ix":1},"s":{"a":0,"k":[100,100],"ix":3},"r":{"a":0,"k":0,"ix":6},"o":{"a":0,"k":100,"ix":7},"sk":{"a":0,"k":0,"ix":4},"sa":{"a":0,"k":0,"ix":5},"nm":"Transform"}],"nm":"Ellipse 2","np":3,"cix":2,"bm":0,"ix":2,"mn":"ADBE Vector Group","hd":false},{"ty":"gr","it":[{"d":1,"ty":"el","s":{"a":0,"k":[12,21.25],"ix":2},"p":{"a":0,"k":[0,0],"ix":3},"nm":"Ellipse Path 1","mn":"ADBE Vector Shape - Ellipse","hd":false},{"ty":"st","c":{"a":0,"k":[0.2588239782,0.2588239782,0.2588239782,1],"ix":3},"o":{"a":0,"k":100,"ix":4},"w":{"a":0,"k":2,"ix":5},"lc":1,"lj":1,"ml":4,"bm":0,"nm":"Stroke 1","mn":"ADBE Vector Graphic - Stroke","hd":false},{"ty":"fl","c":{"a":0,"k":[0.196078431373,0.098039215686,0.03137254902,1],"ix":4},"o":{"a":0,"k":100,"ix":5},"r":1,"bm":0,"nm":"Fill 1","mn":"ADBE Vector Graphic - Fill","hd":false},{"ty":"tr","p":{"a":0,"k":[-40.75,-37.375],"ix":2},"a":{"a":0,"k":[0,0],"ix":1},"s":{"a":0,"k":[100,100],"ix":3},"r":{"a":0,"k":0,"ix":6},"o":{"a":0,"k":100,"ix":7},"sk":{"a":0,"k":0,"ix":4},"sa":{"a":0,"k":0,"ix":5},"nm":"Transform"}],"nm":"Ellipse 1","np":3,"cix":2,"bm":0,"ix":3,"mn":"ADBE Vector Group","hd":false}],"ip":0,"op":1071.07107107107,"st":0,"bm":0},{"ddd":0,"ind":29,"ty":4,"nm":"Face","parent":15,"sr":1,"ks":{"o":{"a":0,"k":100,"ix":11},"r":{"a":0,"k":0,"ix":10},"p":{"a":0,"k":[0,0,0],"ix":2,"l":2},"a":{"a":0,"k":[0,0,0],"ix":1,"l":2},"s":{"a":0,"k":[100,100,100],"ix":6,"l":2}},"ao":0,"ef":[{"ty":21,"nm":"Fill","np":9,"mn":"ADBE Fill","ix":1,"en":1,"ef":[{"ty":10,"nm":"Fill Mask","mn":"ADBE Fill-0001","ix":1,"v":{"a":0,"k":0,"ix":1}},{"ty":7,"nm":"All Masks","mn":"ADBE Fill-0007","ix":2,"v":{"a":0,"k":0,"ix":2}},{"ty":2,"nm":"Color","mn":"ADBE Fill-0002","ix":3,"v":{"a":0,"k":[1,0,0,1],"ix":3,"x":"var $bm_rt;\nif (comp('i Miss Suit').layer('Local Color Control').effect('Global Colors')(1) == 1)\n    $bm_rt = comp('!Global Control').layer('Skin 2').effect('Fill')('Color');\nelse\n    $bm_rt = comp('i Miss Suit').layer('Local Color Control').effect('Skin')('Color');"}},{"ty":7,"nm":"Invert","mn":"ADBE Fill-0006","ix":4,"v":{"a":0,"k":0,"ix":4}},{"ty":0,"nm":"Horizontal Feather","mn":"ADBE Fill-0003","ix":5,"v":{"a":0,"k":0,"ix":5}},{"ty":0,"nm":"Vertical Feather","mn":"ADBE Fill-0004","ix":6,"v":{"a":0,"k":0,"ix":6}},{"ty":0,"nm":"Opacity","mn":"ADBE Fill-0005","ix":7,"v":{"a":0,"k":1,"ix":7}}]}],"shapes":[{"ty":"gr","it":[{"ind":0,"ty":"sh","ix":1,"ks":{"a":0,"k":{"i":[[114.003,15.314],[0,0],[0,0]],"o":[[-167.5,-22.5],[0,0],[0,0]],"v":[[50.5,-131],[-85,45.719],[140.5,47.5]],"c":true},"ix":2},"nm":"Path 1","mn":"ADBE Vector Shape - Group","hd":false},{"ty":"fl","c":{"a":0,"k":[0.992156862745,0.862745098039,0.745098039216,1],"ix":4},"o":{"a":0,"k":100,"ix":5},"r":1,"bm":0,"nm":"Fill 1","mn":"ADBE Vector Graphic - Fill","hd":false},{"ty":"tr","p":{"a":0,"k":[0,0],"ix":2},"a":{"a":0,"k":[0,0],"ix":1},"s":{"a":0,"k":[100,100],"ix":3},"r":{"a":0,"k":0,"ix":6},"o":{"a":0,"k":100,"ix":7},"sk":{"a":0,"k":0,"ix":4},"sa":{"a":0,"k":0,"ix":5},"nm":"Transform"}],"nm":"Shape 1","np":3,"cix":2,"bm":0,"ix":1,"mn":"ADBE Vector Group","hd":false}],"ip":0,"op":1071.07107107107,"st":0,"bm":0},{"ddd":0,"ind":30,"ty":4,"nm":"Shadow","parent":19,"sr":1,"ks":{"o":{"a":0,"k":20,"ix":11},"r":{"a":0,"k":0,"ix":10},"p":{"a":0,"k":[-32.391,301.424,0],"ix":2,"l":2},"a":{"a":0,"k":[-136,137.75,0],"ix":1,"l":2},"s":{"a":1,"k":[{"i":{"x":[0.833,0.833,0.833],"y":[0.833,0.833,0.833]},"o":{"x":[0.167,0.167,0.167],"y":[0.167,0.167,0.167]},"t":12,"s":[147.656,172.265,100]},{"i":{"x":[0.833,0.833,0.833],"y":[0.833,0.833,0.833]},"o":{"x":[0.167,0.167,0.167],"y":[0.167,0.167,0.167]},"t":25,"s":[243.75,172.265,100]},{"i":{"x":[0.833,0.833,0.833],"y":[0.833,0.833,0.833]},"o":{"x":[0.167,0.167,0.167],"y":[0.167,0.167,0.167]},"t":37,"s":[147.656,172.265,100]},{"t":45,"s":[165.234,172.265,100]}],"ix":6,"l":2}},"ao":0,"shapes":[{"ty":"gr","it":[{"d":1,"ty":"el","s":{"a":0,"k":[147,31.5],"ix":2},"p":{"a":0,"k":[0,0],"ix":3},"nm":"Ellipse Path 1","mn":"ADBE Vector Shape - Ellipse","hd":false},{"ty":"fl","c":{"a":0,"k":[0,0,0,1],"ix":4},"o":{"a":0,"k":100,"ix":5},"r":1,"bm":0,"nm":"Fill 1","mn":"ADBE Vector Graphic - Fill","hd":false},{"ty":"tr","p":{"a":0,"k":[-136,137.75],"ix":2},"a":{"a":0,"k":[0,0],"ix":1},"s":{"a":0,"k":[100,100],"ix":3},"r":{"a":0,"k":0,"ix":6},"o":{"a":0,"k":100,"ix":7},"sk":{"a":0,"k":0,"ix":4},"sa":{"a":0,"k":0,"ix":5},"nm":"Transform"}],"nm":"Ellipse 1","np":3,"cix":2,"bm":0,"ix":1,"mn":"ADBE Vector Group","hd":false}],"ip":0,"op":1050,"st":0,"bm":0}],"markers":[]}