{"v":"5.8.1","fr":29.9700012207031,"ip":0,"op":40.0000016292334,"w":512,"h":512,"nm":"GIANT PANDA","ddd":0,"assets":[],"layers":[{"ddd":0,"ind":5,"ty":4,"nm":"EYE","parent":6,"sr":1,"ks":{"o":{"a":0,"k":100,"ix":11},"r":{"a":0,"k":0,"ix":10},"p":{"a":0,"k":[48.266,28.211,0],"ix":2,"l":2},"a":{"a":0,"k":[21.625,4.25,0],"ix":1,"l":2},"s":{"a":1,"k":[{"i":{"x":[0.667,0.667,0.667],"y":[1,1,1]},"o":{"x":[0.333,0.333,0.333],"y":[0,0,0]},"t":0,"s":[100,100,100]},{"i":{"x":[0.667,0.667,0.667],"y":[1,1,1]},"o":{"x":[0.333,0.333,0.333],"y":[0,0,0]},"t":10,"s":[100,10,100]},{"i":{"x":[0.667,0.667,0.667],"y":[1,1,1]},"o":{"x":[0.333,0.333,0.333],"y":[0,0,0]},"t":20,"s":[100,100,100]},{"i":{"x":[0.667,0.667,0.667],"y":[1,1,1]},"o":{"x":[0.333,0.333,0.333],"y":[0,0,0]},"t":30,"s":[100,10,100]},{"t":40.0000016292334,"s":[100,100,100]}],"ix":6,"l":2,"x":"var $bm_rt;\n$bm_rt = loopOut('cycle', 0);"}},"ao":0,"shapes":[{"ty":"gr","it":[{"ind":0,"ty":"sh","ix":1,"ks":{"a":0,"k":{"i":[[0,-2.209],[-2.209,0],[0,2.209],[2.209,0]],"o":[[0,2.209],[2.209,0],[0,-2.209],[-2.209,0]],"v":[[-4,0],[0,4],[4,0],[0,-4]],"c":true},"ix":2},"nm":"Path 1","mn":"ADBE Vector Shape - Group","hd":false},{"ty":"fl","c":{"a":0,"k":[0.250999989229,0.161000001197,0.263000009574,1],"ix":4},"o":{"a":0,"k":100,"ix":5},"r":1,"bm":0,"nm":"Fill 1","mn":"ADBE Vector Graphic - Fill","hd":false},{"ty":"tr","p":{"a":0,"k":[4.25,4.25],"ix":2},"a":{"a":0,"k":[0,0],"ix":1},"s":{"a":0,"k":[100,100],"ix":3},"r":{"a":0,"k":0,"ix":6},"o":{"a":0,"k":100,"ix":7},"sk":{"a":0,"k":0,"ix":4},"sa":{"a":0,"k":0,"ix":5},"nm":"Transform"}],"nm":"Group 1","np":2,"cix":2,"bm":0,"ix":1,"mn":"ADBE Vector Group","hd":false},{"ty":"gr","it":[{"ind":0,"ty":"sh","ix":1,"ks":{"a":0,"k":{"i":[[0,-2.209],[-2.209,0],[0,2.209],[2.209,0]],"o":[[0,2.209],[2.209,0],[0,-2.209],[-2.209,0]],"v":[[-4,0],[0,4],[4,0],[0,-4]],"c":true},"ix":2},"nm":"Path 1","mn":"ADBE Vector Shape - Group","hd":false},{"ty":"fl","c":{"a":0,"k":[0.250999989229,0.161000001197,0.263000009574,1],"ix":4},"o":{"a":0,"k":100,"ix":5},"r":1,"bm":0,"nm":"Fill 1","mn":"ADBE Vector Graphic - Fill","hd":false},{"ty":"tr","p":{"a":0,"k":[39.001,4.25],"ix":2},"a":{"a":0,"k":[0,0],"ix":1},"s":{"a":0,"k":[100,100],"ix":3},"r":{"a":0,"k":0,"ix":6},"o":{"a":0,"k":100,"ix":7},"sk":{"a":0,"k":0,"ix":4},"sa":{"a":0,"k":0,"ix":5},"nm":"Transform"}],"nm":"Group 2","np":2,"cix":2,"bm":0,"ix":2,"mn":"ADBE Vector Group","hd":false}],"ip":0,"op":120.0000048877,"st":0,"bm":0},{"ddd":0,"ind":6,"ty":4,"nm":"FACE","parent":7,"sr":1,"ks":{"o":{"a":0,"k":100,"ix":11},"r":{"a":0,"k":0,"ix":10},"p":{"a":0,"k":[-132.358,-52.304,0],"ix":2,"l":2},"a":{"a":0,"k":[47.338,39.975,0],"ix":1,"l":2},"s":{"a":0,"k":[100,100,100],"ix":6,"l":2}},"ao":0,"shapes":[{"ty":"gr","it":[{"ind":0,"ty":"sh","ix":1,"ks":{"a":0,"k":{"i":[[4.598,0],[0,0],[0,4.597],[-4.598,0],[0,0],[0,-4.598]],"o":[[0,0],[-4.598,0],[0,-4.598],[0,0],[4.598,0],[0,4.597]],"v":[[2.463,16.447],[-2.736,16.447],[-11.061,8.122],[-2.736,-0.203],[2.463,-0.203],[10.788,8.122]],"c":true},"ix":2},"nm":"Path 1","mn":"ADBE Vector Shape - Group","hd":false},{"ind":1,"ty":"sh","ix":2,"ks":{"a":0,"k":{"i":[[0.013,0.988],[1.646,7.99],[0.44,0.668],[0.924,1.05],[1.274,1.041],[3.624,1.152],[1.653,0.239],[1.424,0.008],[0.058,0],[0,0],[0.676,-0.045],[1.403,-0.301],[1.694,-0.711],[2.203,-1.78],[1.208,-1.409],[0.781,-1.231],[0,-5.93],[0,0],[-3.722,-5.125],[-23.694,0],[-6.914,1.234],[0.282,13.48]],"o":[[-0.091,-6.421],[-0.39,-0.708],[-0.777,-1.184],[-1.095,-1.246],[-2.918,-2.383],[-1.565,-0.498],[-1.379,-0.199],[-0.058,0],[0,0],[-0.687,0],[-1.467,0.099],[-1.835,0.394],[-2.648,1.111],[-1.444,1.167],[-0.945,1.103],[-2.963,4.672],[0,0],[0,6.423],[3.311,2.778],[5.458,0],[13.245,-2.362],[-0.017,-0.818]],"v":[[42.743,3.808],[40.874,-20.081],[39.632,-22.146],[37.077,-25.497],[33.521,-28.934],[23.631,-34.294],[18.799,-35.405],[14.592,-35.719],[14.419,-35.725],[-12.846,-35.725],[-14.889,-35.649],[-19.199,-35.048],[-24.501,-33.385],[-31.807,-29.014],[-35.79,-25.141],[-38.382,-21.636],[-43.068,-5.503],[-43.068,6.702],[-37.285,24.47],[1.77,35.725],[20.415,33.865],[42.786,6.525]],"c":true},"ix":2},"nm":"Path 2","mn":"ADBE Vector Shape - Group","hd":false},{"ty":"mm","mm":1,"nm":"Merge Paths 1","mn":"ADBE Vector Filter - Merge","hd":false},{"ty":"fl","c":{"a":0,"k":[0.976000019148,0.969000004787,0.929000016755,1],"ix":4},"o":{"a":0,"k":100,"ix":5},"r":1,"bm":0,"nm":"Fill 1","mn":"ADBE Vector Graphic - Fill","hd":false},{"ty":"tr","p":{"a":0,"k":[47.318,39.975],"ix":2},"a":{"a":0,"k":[0,0],"ix":1},"s":{"a":0,"k":[100,100],"ix":3},"r":{"a":0,"k":0,"ix":6},"o":{"a":0,"k":100,"ix":7},"sk":{"a":0,"k":0,"ix":4},"sa":{"a":0,"k":0,"ix":5},"nm":"Transform"}],"nm":"Group 1","np":4,"cix":2,"bm":0,"ix":1,"mn":"ADBE Vector Group","hd":false},{"ty":"gr","it":[{"ind":0,"ty":"sh","ix":1,"ks":{"a":0,"k":{"i":[[0,0],[0.118,0.107],[0.975,1.2],[0,0],[0,0],[-2.444,-1.035]],"o":[[-0.105,-0.12],[-1.162,-1.049],[0,0],[0,0],[1.696,1.009],[0,0]],"v":[[-0.268,-0.479],[-0.603,-0.819],[-3.808,-4.199],[-3.832,-4.224],[-2.366,1.109],[3.832,4.224]],"c":true},"ix":2},"nm":"Path 1","mn":"ADBE Vector Shape - Group","hd":false},{"ty":"fl","c":{"a":0,"k":[0.250999989229,0.161000001197,0.263000009574,1],"ix":4},"o":{"a":0,"k":100,"ix":5},"r":1,"bm":0,"nm":"Fill 1","mn":"ADBE Vector Graphic - Fill","hd":false},{"ty":"tr","p":{"a":0,"k":[14.837,69.939],"ix":2},"a":{"a":0,"k":[0,0],"ix":1},"s":{"a":0,"k":[100,100],"ix":3},"r":{"a":0,"k":0,"ix":6},"o":{"a":0,"k":100,"ix":7},"sk":{"a":0,"k":0,"ix":4},"sa":{"a":0,"k":0,"ix":5},"nm":"Transform"}],"nm":"Group 2","np":2,"cix":2,"bm":0,"ix":2,"mn":"ADBE Vector Group","hd":false},{"ty":"gr","it":[{"ind":0,"ty":"sh","ix":1,"ks":{"a":0,"k":{"i":[[0,0],[0,0]],"o":[[-0.016,-0.016],[0,0]],"v":[[0.012,0.012],[-0.012,-0.012]],"c":true},"ix":2},"nm":"Path 1","mn":"ADBE Vector Shape - Group","hd":false},{"ty":"fl","c":{"a":0,"k":[0.250999989229,0.161000001197,0.263000009574,1],"ix":4},"o":{"a":0,"k":100,"ix":5},"r":1,"bm":0,"nm":"Fill 1","mn":"ADBE Vector Graphic - Fill","hd":false},{"ty":"tr","p":{"a":0,"k":[11.017,65.727],"ix":2},"a":{"a":0,"k":[0,0],"ix":1},"s":{"a":0,"k":[100,100],"ix":3},"r":{"a":0,"k":0,"ix":6},"o":{"a":0,"k":100,"ix":7},"sk":{"a":0,"k":0,"ix":4},"sa":{"a":0,"k":0,"ix":5},"nm":"Transform"}],"nm":"Group 3","np":2,"cix":2,"bm":0,"ix":3,"mn":"ADBE Vector Group","hd":false},{"ty":"gr","it":[{"ind":0,"ty":"sh","ix":1,"ks":{"a":0,"k":{"i":[[-1.496,-0.122],[0.125,0.853],[0.002,0]],"o":[[-0.101,-0.862],[-1.931,0.064],[0.571,1.408]],"v":[[1.692,1.286],[1.352,-1.286],[-1.692,-1.185]],"c":true},"ix":2},"nm":"Path 1","mn":"ADBE Vector Shape - Group","hd":false},{"ty":"fl","c":{"a":0,"k":[0.250999989229,0.161000001197,0.263000009574,1],"ix":4},"o":{"a":0,"k":100,"ix":5},"r":1,"bm":0,"nm":"Fill 1","mn":"ADBE Vector Graphic - Fill","hd":false},{"ty":"tr","p":{"a":0,"k":[91.443,24.316],"ix":2},"a":{"a":0,"k":[0,0],"ix":1},"s":{"a":0,"k":[100,100],"ix":3},"r":{"a":0,"k":0,"ix":6},"o":{"a":0,"k":100,"ix":7},"sk":{"a":0,"k":0,"ix":4},"sa":{"a":0,"k":0,"ix":5},"nm":"Transform"}],"nm":"Group 4","np":2,"cix":2,"bm":0,"ix":4,"mn":"ADBE Vector Group","hd":false},{"ty":"gr","it":[{"ind":0,"ty":"sh","ix":1,"ks":{"a":0,"k":{"i":[[0.381,-0.093],[0.077,-0.827],[-0.873,0.569],[0.047,0.071]],"o":[[-0.853,0.206],[0.965,-0.419],[-0.046,-0.072],[-0.346,-0.118]],"v":[[0.133,-0.833],[-1.38,0.926],[1.38,-0.565],[1.242,-0.78]],"c":true},"ix":2},"nm":"Path 1","mn":"ADBE Vector Shape - Group","hd":false},{"ty":"fl","c":{"a":0,"k":[0.250999989229,0.161000001197,0.263000009574,1],"ix":4},"o":{"a":0,"k":100,"ix":5},"r":1,"bm":0,"nm":"Fill 1","mn":"ADBE Vector Graphic - Fill","hd":false},{"ty":"tr","p":{"a":0,"k":[89.148,16.584],"ix":2},"a":{"a":0,"k":[0,0],"ix":1},"s":{"a":0,"k":[100,100],"ix":3},"r":{"a":0,"k":0,"ix":6},"o":{"a":0,"k":100,"ix":7},"sk":{"a":0,"k":0,"ix":4},"sa":{"a":0,"k":0,"ix":5},"nm":"Transform"}],"nm":"Group 5","np":2,"cix":2,"bm":0,"ix":5,"mn":"ADBE Vector Group","hd":false},{"ty":"gr","it":[{"ind":0,"ty":"sh","ix":1,"ks":{"a":0,"k":{"i":[[0,0],[-0.016,-0.016],[0.319,0.44],[0.018,0.02],[0.804,-0.753],[-0.039,-0.579],[-0.524,-0.696],[-2.612,-1.553]],"o":[[0,0],[-0.343,-0.423],[-0.629,-0.527],[-0.755,-0.801],[-0.457,0.427],[0.47,0.735],[0.986,0.872],[0,0]],"v":[[1.976,-1.176],[1.999,-1.15],[1.005,-2.445],[0.04,-3.316],[-2.782,-3.406],[-3.403,-1.809],[-1.911,0.337],[3.441,4.158]],"c":true},"ix":2},"nm":"Path 1","mn":"ADBE Vector Shape - Group","hd":false},{"ty":"fl","c":{"a":0,"k":[0.250999989229,0.161000001197,0.263000009574,1],"ix":4},"o":{"a":0,"k":100,"ix":5},"r":1,"bm":0,"nm":"Fill 1","mn":"ADBE Vector Graphic - Fill","hd":false},{"ty":"tr","p":{"a":0,"k":[9.029,66.89],"ix":2},"a":{"a":0,"k":[0,0],"ix":1},"s":{"a":0,"k":[100,100],"ix":3},"r":{"a":0,"k":0,"ix":6},"o":{"a":0,"k":100,"ix":7},"sk":{"a":0,"k":0,"ix":4},"sa":{"a":0,"k":0,"ix":5},"nm":"Transform"}],"nm":"Group 6","np":2,"cix":2,"bm":0,"ix":6,"mn":"ADBE Vector Group","hd":false},{"ty":"gr","it":[{"ind":0,"ty":"sh","ix":1,"ks":{"a":0,"k":{"i":[[0.965,-0.419],[-0.054,-0.221],[-0.12,-0.584],[-0.455,-1.123],[0,-0.001],[-1.93,0.064],[0.318,1.469],[0.52,0.809]],"o":[[-0.02,0.214],[0.137,0.567],[0.572,1.042],[0,0],[0.002,0],[-0.224,-1.535],[-0.451,-0.854],[-0.873,0.569]],"v":[[-2.503,-2.065],[-2.464,-1.409],[-2.08,0.319],[-0.52,3.555],[-0.52,3.556],[2.523,3.454],[1.714,-1.061],[0.256,-3.556]],"c":true},"ix":2},"nm":"Path 1","mn":"ADBE Vector Shape - Group","hd":false},{"ty":"fl","c":{"a":0,"k":[0.250999989229,0.161000001197,0.263000009574,1],"ix":4},"o":{"a":0,"k":100,"ix":5},"r":1,"bm":0,"nm":"Fill 1","mn":"ADBE Vector Graphic - Fill","hd":false},{"ty":"tr","p":{"a":0,"k":[90.271,19.575],"ix":2},"a":{"a":0,"k":[0,0],"ix":1},"s":{"a":0,"k":[100,100],"ix":3},"r":{"a":0,"k":0,"ix":6},"o":{"a":0,"k":100,"ix":7},"sk":{"a":0,"k":0,"ix":4},"sa":{"a":0,"k":0,"ix":5},"nm":"Transform"}],"nm":"Group 7","np":2,"cix":2,"bm":0,"ix":7,"mn":"ADBE Vector Group","hd":false},{"ty":"gr","it":[{"ind":0,"ty":"sh","ix":1,"ks":{"a":0,"k":{"i":[[-0.046,-0.072],[-0.047,0.031],[0.099,0.033]],"o":[[0.048,-0.031],[-0.092,-0.049],[0.047,0.071]],"v":[[-0.005,0.107],[0.143,0.019],[-0.143,-0.107]],"c":true},"ix":2},"nm":"Path 1","mn":"ADBE Vector Shape - Group","hd":false},{"ty":"fl","c":{"a":0,"k":[0.250999989229,0.161000001197,0.263000009574,1],"ix":4},"o":{"a":0,"k":100,"ix":5},"r":1,"bm":0,"nm":"Fill 1","mn":"ADBE Vector Graphic - Fill","hd":false},{"ty":"tr","p":{"a":0,"k":[90.532,15.912],"ix":2},"a":{"a":0,"k":[0,0],"ix":1},"s":{"a":0,"k":[100,100],"ix":3},"r":{"a":0,"k":0,"ix":6},"o":{"a":0,"k":100,"ix":7},"sk":{"a":0,"k":0,"ix":4},"sa":{"a":0,"k":0,"ix":5},"nm":"Transform"}],"nm":"Group 8","np":2,"cix":2,"bm":0,"ix":8,"mn":"ADBE Vector Group","hd":false},{"ty":"gr","it":[{"ind":0,"ty":"sh","ix":1,"ks":{"a":0,"k":{"i":[[-0.327,-0.35],[-0.571,-0.505],[0.47,0.734]],"o":[[0.073,0.078],[-0.524,-0.696],[0.03,0.442]],"v":[[-0.221,0.156],[0.745,1.073],[-0.745,-1.073]],"c":true},"ix":2},"nm":"Path 1","mn":"ADBE Vector Shape - Group","hd":false},{"ty":"fl","c":{"a":0,"k":[0.250999989229,0.161000001197,0.263000009574,1],"ix":4},"o":{"a":0,"k":100,"ix":5},"r":1,"bm":0,"nm":"Fill 1","mn":"ADBE Vector Graphic - Fill","hd":false},{"ty":"tr","p":{"a":0,"k":[6.372,66.155],"ix":2},"a":{"a":0,"k":[0,0],"ix":1},"s":{"a":0,"k":[100,100],"ix":3},"r":{"a":0,"k":0,"ix":6},"o":{"a":0,"k":100,"ix":7},"sk":{"a":0,"k":0,"ix":4},"sa":{"a":0,"k":0,"ix":5},"nm":"Transform"}],"nm":"Group 9","np":2,"cix":2,"bm":0,"ix":9,"mn":"ADBE Vector Group","hd":false},{"ty":"gr","it":[{"ind":0,"ty":"sh","ix":1,"ks":{"a":0,"k":{"i":[[0.009,0.01],[-1.162,-1.048],[-0.105,-0.12],[0,0],[-9.378,-0.809],[0,0],[2.154,1.904],[0.006,0.006],[0.055,0.051],[0.015,0.013],[0.037,0.036],[0.014,0.013],[0.023,0.023],[0.011,0.01]],"o":[[0.974,1.2],[0.119,0.107],[0,0],[5.38,2.28],[0,0],[-16.541,-2.386],[-0.006,-0.005],[-0.068,-0.06],[-0.016,-0.014],[-0.048,-0.045],[-0.016,-0.015],[-0.032,-0.03],[-0.014,-0.014],[-0.017,-0.017]],"v":[[-14.822,-6.802],[-11.618,-3.422],[-11.282,-3.081],[-7.182,1.622],[14.822,6.802],[12.605,4.259],[-14.245,-6.263],[-14.264,-6.28],[-14.447,-6.444],[-14.493,-6.486],[-14.62,-6.605],[-14.663,-6.646],[-14.747,-6.727],[-14.781,-6.759]],"c":true},"ix":2},"nm":"Path 1","mn":"ADBE Vector Shape - Group","hd":false},{"ty":"fl","c":{"a":0,"k":[0.250999989229,0.161000001197,0.263000009574,1],"ix":4},"o":{"a":0,"k":100,"ix":5},"r":1,"bm":0,"nm":"Fill 1","mn":"ADBE Vector Graphic - Fill","hd":false},{"ty":"tr","p":{"a":0,"k":[25.851,72.541],"ix":2},"a":{"a":0,"k":[0,0],"ix":1},"s":{"a":0,"k":[100,100],"ix":3},"r":{"a":0,"k":0,"ix":6},"o":{"a":0,"k":100,"ix":7},"sk":{"a":0,"k":0,"ix":4},"sa":{"a":0,"k":0,"ix":5},"nm":"Transform"}],"nm":"Group 10","np":2,"cix":2,"bm":0,"ix":10,"mn":"ADBE Vector Group","hd":false},{"ty":"gr","it":[{"ind":0,"ty":"sh","ix":1,"ks":{"a":0,"k":{"i":[[0.056,0.051],[-0.068,-0.06]],"o":[[0.056,0.051],[-0.068,-0.06]],"v":[[-0.092,-0.083],[0.092,0.083]],"c":true},"ix":2},"nm":"Path 1","mn":"ADBE Vector Shape - Group","hd":false},{"ty":"fl","c":{"a":0,"k":[0.250999989229,0.161000001197,0.263000009574,1],"ix":4},"o":{"a":0,"k":100,"ix":5},"r":1,"bm":0,"nm":"Fill 1","mn":"ADBE Vector Graphic - Fill","hd":false},{"ty":"tr","p":{"a":0,"k":[11.496,66.179],"ix":2},"a":{"a":0,"k":[0,0],"ix":1},"s":{"a":0,"k":[100,100],"ix":3},"r":{"a":0,"k":0,"ix":6},"o":{"a":0,"k":100,"ix":7},"sk":{"a":0,"k":0,"ix":4},"sa":{"a":0,"k":0,"ix":5},"nm":"Transform"}],"nm":"Group 11","np":2,"cix":2,"bm":0,"ix":11,"mn":"ADBE Vector Group","hd":false},{"ty":"gr","it":[{"ind":0,"ty":"sh","ix":1,"ks":{"a":0,"k":{"i":[[-16.541,-2.386],[2.165,1.907]],"o":[[-16.527,-2.384],[2.154,1.903]],"v":[[13.425,5.26],[-13.425,-5.26]],"c":true},"ix":2},"nm":"Path 1","mn":"ADBE Vector Shape - Group","hd":false},{"ty":"fl","c":{"a":0,"k":[0.250999989229,0.161000001197,0.263000009574,1],"ix":4},"o":{"a":0,"k":100,"ix":5},"r":1,"bm":0,"nm":"Fill 1","mn":"ADBE Vector Graphic - Fill","hd":false},{"ty":"tr","p":{"a":0,"k":[25.031,71.539],"ix":2},"a":{"a":0,"k":[0,0],"ix":1},"s":{"a":0,"k":[100,100],"ix":3},"r":{"a":0,"k":0,"ix":6},"o":{"a":0,"k":100,"ix":7},"sk":{"a":0,"k":0,"ix":4},"sa":{"a":0,"k":0,"ix":5},"nm":"Transform"}],"nm":"Group 12","np":2,"cix":2,"bm":0,"ix":12,"mn":"ADBE Vector Group","hd":false},{"ty":"gr","it":[{"ind":0,"ty":"sh","ix":1,"ks":{"a":0,"k":{"i":[[0.038,0.036],[-0.047,-0.044]],"o":[[0.038,0.036],[-0.047,-0.044]],"v":[[-0.064,-0.06],[0.064,0.06]],"c":true},"ix":2},"nm":"Path 1","mn":"ADBE Vector Shape - Group","hd":false},{"ty":"fl","c":{"a":0,"k":[0.250999989229,0.161000001197,0.263000009574,1],"ix":4},"o":{"a":0,"k":100,"ix":5},"r":1,"bm":0,"nm":"Fill 1","mn":"ADBE Vector Graphic - Fill","hd":false},{"ty":"tr","p":{"a":0,"k":[11.294,65.995],"ix":2},"a":{"a":0,"k":[0,0],"ix":1},"s":{"a":0,"k":[100,100],"ix":3},"r":{"a":0,"k":0,"ix":6},"o":{"a":0,"k":100,"ix":7},"sk":{"a":0,"k":0,"ix":4},"sa":{"a":0,"k":0,"ix":5},"nm":"Transform"}],"nm":"Group 13","np":2,"cix":2,"bm":0,"ix":13,"mn":"ADBE Vector Group","hd":false},{"ty":"gr","it":[{"ind":0,"ty":"sh","ix":1,"ks":{"a":0,"k":{"i":[[-0.017,-0.017],[0,0],[0,0]],"o":[[0,0],[0,0],[0.009,0.01]],"v":[[0.021,0.021],[-0.021,-0.021],[-0.02,-0.021]],"c":true},"ix":2},"nm":"Path 1","mn":"ADBE Vector Shape - Group","hd":false},{"ty":"fl","c":{"a":0,"k":[0.250999989229,0.161000001197,0.263000009574,1],"ix":4},"o":{"a":0,"k":100,"ix":5},"r":1,"bm":0,"nm":"Fill 1","mn":"ADBE Vector Graphic - Fill","hd":false},{"ty":"tr","p":{"a":0,"k":[11.05,65.76],"ix":2},"a":{"a":0,"k":[0,0],"ix":1},"s":{"a":0,"k":[100,100],"ix":3},"r":{"a":0,"k":0,"ix":6},"o":{"a":0,"k":100,"ix":7},"sk":{"a":0,"k":0,"ix":4},"sa":{"a":0,"k":0,"ix":5},"nm":"Transform"}],"nm":"Group 14","np":2,"cix":2,"bm":0,"ix":14,"mn":"ADBE Vector Group","hd":false},{"ty":"gr","it":[{"ind":0,"ty":"sh","ix":1,"ks":{"a":0,"k":{"i":[[0.022,0.022],[-0.032,-0.03]],"o":[[0.023,0.022],[-0.031,-0.029]],"v":[[-0.042,-0.04],[0.042,0.04]],"c":true},"ix":2},"nm":"Path 1","mn":"ADBE Vector Shape - Group","hd":false},{"ty":"fl","c":{"a":0,"k":[0.250999989229,0.161000001197,0.263000009574,1],"ix":4},"o":{"a":0,"k":100,"ix":5},"r":1,"bm":0,"nm":"Fill 1","mn":"ADBE Vector Graphic - Fill","hd":false},{"ty":"tr","p":{"a":0,"k":[11.146,65.854],"ix":2},"a":{"a":0,"k":[0,0],"ix":1},"s":{"a":0,"k":[100,100],"ix":3},"r":{"a":0,"k":0,"ix":6},"o":{"a":0,"k":100,"ix":7},"sk":{"a":0,"k":0,"ix":4},"sa":{"a":0,"k":0,"ix":5},"nm":"Transform"}],"nm":"Group 15","np":2,"cix":2,"bm":0,"ix":15,"mn":"ADBE Vector Group","hd":false},{"ty":"gr","it":[{"ind":0,"ty":"sh","ix":1,"ks":{"a":0,"k":{"i":[[-0.154,-0.982],[-0.044,-0.296],[-0.096,-0.696],[-0.038,-0.284],[-0.103,-0.891],[-0.016,-0.136],[-0.074,-0.738],[-0.029,-0.314],[-0.044,-0.553],[-0.024,-0.306],[-0.044,-0.749],[0,0],[0.638,5.484],[0.572,1.407]],"o":[[0.046,0.298],[0.108,0.713],[0.04,0.287],[0.122,0.92],[0.017,0.137],[0.086,0.761],[0.031,0.319],[0.053,0.567],[0.026,0.311],[0.058,0.776],[0,0],[-0.078,-4.553],[-1.497,-0.122],[0.176,1.013]],"v":[[-1.645,-6.047],[-1.512,-5.16],[-1.206,-3.046],[-1.087,-2.187],[-0.747,0.534],[-0.702,0.94],[-0.462,3.189],[-0.374,4.136],[-0.227,5.817],[-0.152,6.745],[0.003,9.035],[2.135,9.035],[1.249,-6.563],[-2.135,-9.035]],"c":true},"ix":2},"nm":"Path 1","mn":"ADBE Vector Shape - Group","hd":false},{"ty":"fl","c":{"a":0,"k":[0.250999989229,0.161000001197,0.263000009574,1],"ix":4},"o":{"a":0,"k":100,"ix":5},"r":1,"bm":0,"nm":"Fill 1","mn":"ADBE Vector Graphic - Fill","hd":false},{"ty":"tr","p":{"a":0,"k":[91.887,32.166],"ix":2},"a":{"a":0,"k":[0,0],"ix":1},"s":{"a":0,"k":[100,100],"ix":3},"r":{"a":0,"k":0,"ix":6},"o":{"a":0,"k":100,"ix":7},"sk":{"a":0,"k":0,"ix":4},"sa":{"a":0,"k":0,"ix":5},"nm":"Transform"}],"nm":"Group 16","np":2,"cix":2,"bm":0,"ix":16,"mn":"ADBE Vector Group","hd":false},{"ty":"gr","it":[{"ind":0,"ty":"sh","ix":1,"ks":{"a":0,"k":{"i":[[-0.023,-0.306],[0.025,0.31]],"o":[[-0.023,-0.306],[0.025,0.31]],"v":[[0.038,0.464],[-0.038,-0.464]],"c":true},"ix":2},"nm":"Path 1","mn":"ADBE Vector Shape - Group","hd":false},{"ty":"fl","c":{"a":0,"k":[0.250999989229,0.161000001197,0.263000009574,1],"ix":4},"o":{"a":0,"k":100,"ix":5},"r":1,"bm":0,"nm":"Fill 1","mn":"ADBE Vector Graphic - Fill","hd":false},{"ty":"tr","p":{"a":0,"k":[91.697,38.447],"ix":2},"a":{"a":0,"k":[0,0],"ix":1},"s":{"a":0,"k":[100,100],"ix":3},"r":{"a":0,"k":0,"ix":6},"o":{"a":0,"k":100,"ix":7},"sk":{"a":0,"k":0,"ix":4},"sa":{"a":0,"k":0,"ix":5},"nm":"Transform"}],"nm":"Group 17","np":2,"cix":2,"bm":0,"ix":17,"mn":"ADBE Vector Group","hd":false},{"ty":"gr","it":[{"ind":0,"ty":"sh","ix":1,"ks":{"a":0,"k":{"i":[[-0.044,-0.295],[0.046,0.298]],"o":[[-0.044,-0.295],[0.046,0.298]],"v":[[0.067,0.443],[-0.067,-0.443]],"c":true},"ix":2},"nm":"Path 1","mn":"ADBE Vector Shape - Group","hd":false},{"ty":"fl","c":{"a":0,"k":[0.250999989229,0.161000001197,0.263000009574,1],"ix":4},"o":{"a":0,"k":100,"ix":5},"r":1,"bm":0,"nm":"Fill 1","mn":"ADBE Vector Graphic - Fill","hd":false},{"ty":"tr","p":{"a":0,"k":[90.308,26.562],"ix":2},"a":{"a":0,"k":[0,0],"ix":1},"s":{"a":0,"k":[100,100],"ix":3},"r":{"a":0,"k":0,"ix":6},"o":{"a":0,"k":100,"ix":7},"sk":{"a":0,"k":0,"ix":4},"sa":{"a":0,"k":0,"ix":5},"nm":"Transform"}],"nm":"Group 18","np":2,"cix":2,"bm":0,"ix":18,"mn":"ADBE Vector Group","hd":false},{"ty":"gr","it":[{"ind":0,"ty":"sh","ix":1,"ks":{"a":0,"k":{"i":[[-0.029,-0.314],[0.031,0.319]],"o":[[-0.029,-0.314],[0.031,0.319]],"v":[[0.045,0.473],[-0.045,-0.473]],"c":true},"ix":2},"nm":"Path 1","mn":"ADBE Vector Shape - Group","hd":false},{"ty":"fl","c":{"a":0,"k":[0.250999989229,0.161000001197,0.263000009574,1],"ix":4},"o":{"a":0,"k":100,"ix":5},"r":1,"bm":0,"nm":"Fill 1","mn":"ADBE Vector Graphic - Fill","hd":false},{"ty":"tr","p":{"a":0,"k":[91.469,35.828],"ix":2},"a":{"a":0,"k":[0,0],"ix":1},"s":{"a":0,"k":[100,100],"ix":3},"r":{"a":0,"k":0,"ix":6},"o":{"a":0,"k":100,"ix":7},"sk":{"a":0,"k":0,"ix":4},"sa":{"a":0,"k":0,"ix":5},"nm":"Transform"}],"nm":"Group 19","np":2,"cix":2,"bm":0,"ix":19,"mn":"ADBE Vector Group","hd":false},{"ty":"gr","it":[{"ind":0,"ty":"sh","ix":1,"ks":{"a":0,"k":{"i":[[-0.016,-0.137],[0.016,0.138]],"o":[[-0.016,-0.137],[0.016,0.138]],"v":[[0.022,0.203],[-0.022,-0.203]],"c":true},"ix":2},"nm":"Path 1","mn":"ADBE Vector Shape - Group","hd":false},{"ty":"fl","c":{"a":0,"k":[0.250999989229,0.161000001197,0.263000009574,1],"ix":4},"o":{"a":0,"k":100,"ix":5},"r":1,"bm":0,"nm":"Fill 1","mn":"ADBE Vector Graphic - Fill","hd":false},{"ty":"tr","p":{"a":0,"k":[91.163,32.902],"ix":2},"a":{"a":0,"k":[0,0],"ix":1},"s":{"a":0,"k":[100,100],"ix":3},"r":{"a":0,"k":0,"ix":6},"o":{"a":0,"k":100,"ix":7},"sk":{"a":0,"k":0,"ix":4},"sa":{"a":0,"k":0,"ix":5},"nm":"Transform"}],"nm":"Group 20","np":2,"cix":2,"bm":0,"ix":20,"mn":"ADBE Vector Group","hd":false},{"ty":"gr","it":[{"ind":0,"ty":"sh","ix":1,"ks":{"a":0,"k":{"i":[[-0.038,-0.284],[0.039,0.287]],"o":[[-0.038,-0.284],[0.039,0.287]],"v":[[0.059,0.429],[-0.059,-0.429]],"c":true},"ix":2},"nm":"Path 1","mn":"ADBE Vector Shape - Group","hd":false},{"ty":"fl","c":{"a":0,"k":[0.250999989229,0.161000001197,0.263000009574,1],"ix":4},"o":{"a":0,"k":100,"ix":5},"r":1,"bm":0,"nm":"Fill 1","mn":"ADBE Vector Graphic - Fill","hd":false},{"ty":"tr","p":{"a":0,"k":[90.741,29.549],"ix":2},"a":{"a":0,"k":[0,0],"ix":1},"s":{"a":0,"k":[100,100],"ix":3},"r":{"a":0,"k":0,"ix":6},"o":{"a":0,"k":100,"ix":7},"sk":{"a":0,"k":0,"ix":4},"sa":{"a":0,"k":0,"ix":5},"nm":"Transform"}],"nm":"Group 21","np":2,"cix":2,"bm":0,"ix":21,"mn":"ADBE Vector Group","hd":false},{"ty":"gr","it":[{"ind":0,"ty":"sh","ix":1,"ks":{"a":0,"k":{"i":[[-0.096,-0.696],[0.108,0.713]],"o":[[-0.096,-0.696],[0.108,0.713]],"v":[[0.153,1.057],[-0.153,-1.057]],"c":true},"ix":2},"nm":"Path 1","mn":"ADBE Vector Shape - Group","hd":false},{"ty":"fl","c":{"a":0,"k":[0.250999989229,0.161000001197,0.263000009574,1],"ix":4},"o":{"a":0,"k":100,"ix":5},"r":1,"bm":0,"nm":"Fill 1","mn":"ADBE Vector Graphic - Fill","hd":false},{"ty":"tr","p":{"a":0,"k":[90.529,28.063],"ix":2},"a":{"a":0,"k":[0,0],"ix":1},"s":{"a":0,"k":[100,100],"ix":3},"r":{"a":0,"k":0,"ix":6},"o":{"a":0,"k":100,"ix":7},"sk":{"a":0,"k":0,"ix":4},"sa":{"a":0,"k":0,"ix":5},"nm":"Transform"}],"nm":"Group 22","np":2,"cix":2,"bm":0,"ix":22,"mn":"ADBE Vector Group","hd":false},{"ty":"gr","it":[{"ind":0,"ty":"sh","ix":1,"ks":{"a":0,"k":{"i":[[-2.979,0],[-7.145,1.276],[0.323,15.462],[0.014,0.977],[0.015,0.881],[0,0],[0.058,0.776],[-0.05,-2.347],[14.144,-2.523],[6.3,0.181],[3.223,0.465],[0,0]],"o":[[5.693,0],[15.197,-2.71],[-0.017,-0.809],[-0.011,-0.798],[0,0],[-0.045,-0.748],[0.201,2.678],[0.3,14.364],[-6.049,1.079],[-3.878,-0.111],[0,0],[2.638,0.228]],"v":[[-17.354,20.395],[1.993,18.473],[27.662,-12.889],[27.619,-15.577],[27.581,-18.105],[25.449,-18.105],[25.293,-20.395],[25.663,-12.848],[1.642,16.505],[-17.354,18.395],[-27.985,17.495],[-25.77,20.037]],"c":true},"ix":2},"nm":"Path 1","mn":"ADBE Vector Shape - Group","hd":false},{"ty":"fl","c":{"a":0,"k":[0.250999989229,0.161000001197,0.263000009574,1],"ix":4},"o":{"a":0,"k":100,"ix":5},"r":1,"bm":0,"nm":"Fill 1","mn":"ADBE Vector Graphic - Fill","hd":false},{"ty":"tr","p":{"a":0,"k":[66.442,59.306],"ix":2},"a":{"a":0,"k":[0,0],"ix":1},"s":{"a":0,"k":[100,100],"ix":3},"r":{"a":0,"k":0,"ix":6},"o":{"a":0,"k":100,"ix":7},"sk":{"a":0,"k":0,"ix":4},"sa":{"a":0,"k":0,"ix":5},"nm":"Transform"}],"nm":"Group 23","np":2,"cix":2,"bm":0,"ix":23,"mn":"ADBE Vector Group","hd":false},{"ty":"gr","it":[{"ind":0,"ty":"sh","ix":1,"ks":{"a":0,"k":{"i":[[-0.154,-0.982],[0.176,1.013]],"o":[[-0.154,-0.982],[0.176,1.013]],"v":[[0.245,1.494],[-0.245,-1.494]],"c":true},"ix":2},"nm":"Path 1","mn":"ADBE Vector Shape - Group","hd":false},{"ty":"fl","c":{"a":0,"k":[0.250999989229,0.161000001197,0.263000009574,1],"ix":4},"o":{"a":0,"k":100,"ix":5},"r":1,"bm":0,"nm":"Fill 1","mn":"ADBE Vector Graphic - Fill","hd":false},{"ty":"tr","p":{"a":0,"k":[89.996,24.625],"ix":2},"a":{"a":0,"k":[0,0],"ix":1},"s":{"a":0,"k":[100,100],"ix":3},"r":{"a":0,"k":0,"ix":6},"o":{"a":0,"k":100,"ix":7},"sk":{"a":0,"k":0,"ix":4},"sa":{"a":0,"k":0,"ix":5},"nm":"Transform"}],"nm":"Group 24","np":2,"cix":2,"bm":0,"ix":24,"mn":"ADBE Vector Group","hd":false},{"ty":"gr","it":[{"ind":0,"ty":"sh","ix":1,"ks":{"a":0,"k":{"i":[[0.013,0.013],[-0.016,-0.015]],"o":[[0.014,0.014],[-0.015,-0.014]],"v":[[-0.021,-0.021],[0.021,0.021]],"c":true},"ix":2},"nm":"Path 1","mn":"ADBE Vector Shape - Group","hd":false},{"ty":"fl","c":{"a":0,"k":[0.250999989229,0.161000001197,0.263000009574,1],"ix":4},"o":{"a":0,"k":100,"ix":5},"r":1,"bm":0,"nm":"Fill 1","mn":"ADBE Vector Graphic - Fill","hd":false},{"ty":"tr","p":{"a":0,"k":[11.209,65.915],"ix":2},"a":{"a":0,"k":[0,0],"ix":1},"s":{"a":0,"k":[100,100],"ix":3},"r":{"a":0,"k":0,"ix":6},"o":{"a":0,"k":100,"ix":7},"sk":{"a":0,"k":0,"ix":4},"sa":{"a":0,"k":0,"ix":5},"nm":"Transform"}],"nm":"Group 25","np":2,"cix":2,"bm":0,"ix":25,"mn":"ADBE Vector Group","hd":false},{"ty":"gr","it":[{"ind":0,"ty":"sh","ix":1,"ks":{"a":0,"k":{"i":[[-0.015,-0.014],[0.01,0.011]],"o":[[-0.013,-0.013],[0.011,0.011]],"v":[[0.017,0.017],[-0.017,-0.017]],"c":true},"ix":2},"nm":"Path 1","mn":"ADBE Vector Shape - Group","hd":false},{"ty":"fl","c":{"a":0,"k":[0.250999989229,0.161000001197,0.263000009574,1],"ix":4},"o":{"a":0,"k":100,"ix":5},"r":1,"bm":0,"nm":"Fill 1","mn":"ADBE Vector Graphic - Fill","hd":false},{"ty":"tr","p":{"a":0,"k":[11.088,65.797],"ix":2},"a":{"a":0,"k":[0,0],"ix":1},"s":{"a":0,"k":[100,100],"ix":3},"r":{"a":0,"k":0,"ix":6},"o":{"a":0,"k":100,"ix":7},"sk":{"a":0,"k":0,"ix":4},"sa":{"a":0,"k":0,"ix":5},"nm":"Transform"}],"nm":"Group 26","np":2,"cix":2,"bm":0,"ix":26,"mn":"ADBE Vector Group","hd":false},{"ty":"gr","it":[{"ind":0,"ty":"sh","ix":1,"ks":{"a":0,"k":{"i":[[0.014,0.013],[-0.015,-0.014]],"o":[[0.015,0.013],[-0.015,-0.014]],"v":[[-0.023,-0.021],[0.023,0.021]],"c":true},"ix":2},"nm":"Path 1","mn":"ADBE Vector Shape - Group","hd":false},{"ty":"fl","c":{"a":0,"k":[0.250999989229,0.161000001197,0.263000009574,1],"ix":4},"o":{"a":0,"k":100,"ix":5},"r":1,"bm":0,"nm":"Fill 1","mn":"ADBE Vector Graphic - Fill","hd":false},{"ty":"tr","p":{"a":0,"k":[11.381,66.076],"ix":2},"a":{"a":0,"k":[0,0],"ix":1},"s":{"a":0,"k":[100,100],"ix":3},"r":{"a":0,"k":0,"ix":6},"o":{"a":0,"k":100,"ix":7},"sk":{"a":0,"k":0,"ix":4},"sa":{"a":0,"k":0,"ix":5},"nm":"Transform"}],"nm":"Group 27","np":2,"cix":2,"bm":0,"ix":27,"mn":"ADBE Vector Group","hd":false},{"ty":"gr","it":[{"ind":0,"ty":"sh","ix":1,"ks":{"a":0,"k":{"i":[[-0.103,-0.89],[0.122,0.921]],"o":[[-0.103,-0.89],[0.122,0.921]],"v":[[0.171,1.36],[-0.171,-1.36]],"c":true},"ix":2},"nm":"Path 1","mn":"ADBE Vector Shape - Group","hd":false},{"ty":"fl","c":{"a":0,"k":[0.250999989229,0.161000001197,0.263000009574,1],"ix":4},"o":{"a":0,"k":100,"ix":5},"r":1,"bm":0,"nm":"Fill 1","mn":"ADBE Vector Graphic - Fill","hd":false},{"ty":"tr","p":{"a":0,"k":[90.97,31.339],"ix":2},"a":{"a":0,"k":[0,0],"ix":1},"s":{"a":0,"k":[100,100],"ix":3},"r":{"a":0,"k":0,"ix":6},"o":{"a":0,"k":100,"ix":7},"sk":{"a":0,"k":0,"ix":4},"sa":{"a":0,"k":0,"ix":5},"nm":"Transform"}],"nm":"Group 28","np":2,"cix":2,"bm":0,"ix":28,"mn":"ADBE Vector Group","hd":false},{"ty":"gr","it":[{"ind":0,"ty":"sh","ix":1,"ks":{"a":0,"k":{"i":[[0.006,0.005],[-0.007,-0.005]],"o":[[0.006,0.006],[-0.007,-0.005]],"v":[[-0.01,-0.009],[0.01,0.009]],"c":true},"ix":2},"nm":"Path 1","mn":"ADBE Vector Shape - Group","hd":false},{"ty":"fl","c":{"a":0,"k":[0.250999989229,0.161000001197,0.263000009574,1],"ix":4},"o":{"a":0,"k":100,"ix":5},"r":1,"bm":0,"nm":"Fill 1","mn":"ADBE Vector Graphic - Fill","hd":false},{"ty":"tr","p":{"a":0,"k":[11.597,66.27],"ix":2},"a":{"a":0,"k":[0,0],"ix":1},"s":{"a":0,"k":[100,100],"ix":3},"r":{"a":0,"k":0,"ix":6},"o":{"a":0,"k":100,"ix":7},"sk":{"a":0,"k":0,"ix":4},"sa":{"a":0,"k":0,"ix":5},"nm":"Transform"}],"nm":"Group 29","np":2,"cix":2,"bm":0,"ix":29,"mn":"ADBE Vector Group","hd":false},{"ty":"gr","it":[{"ind":0,"ty":"sh","ix":1,"ks":{"a":0,"k":{"i":[[-0.045,-0.554],[0.052,0.567]],"o":[[-0.045,-0.554],[0.052,0.567]],"v":[[0.073,0.84],[-0.073,-0.84]],"c":true},"ix":2},"nm":"Path 1","mn":"ADBE Vector Shape - Group","hd":false},{"ty":"fl","c":{"a":0,"k":[0.250999989229,0.161000001197,0.263000009574,1],"ix":4},"o":{"a":0,"k":100,"ix":5},"r":1,"bm":0,"nm":"Fill 1","mn":"ADBE Vector Graphic - Fill","hd":false},{"ty":"tr","p":{"a":0,"k":[91.587,37.142],"ix":2},"a":{"a":0,"k":[0,0],"ix":1},"s":{"a":0,"k":[100,100],"ix":3},"r":{"a":0,"k":0,"ix":6},"o":{"a":0,"k":100,"ix":7},"sk":{"a":0,"k":0,"ix":4},"sa":{"a":0,"k":0,"ix":5},"nm":"Transform"}],"nm":"Group 30","np":2,"cix":2,"bm":0,"ix":30,"mn":"ADBE Vector Group","hd":false},{"ty":"gr","it":[{"ind":0,"ty":"sh","ix":1,"ks":{"a":0,"k":{"i":[[-0.073,-0.738],[0.086,0.761]],"o":[[-0.073,-0.738],[0.086,0.761]],"v":[[0.12,1.124],[-0.12,-1.124]],"c":true},"ix":2},"nm":"Path 1","mn":"ADBE Vector Shape - Group","hd":false},{"ty":"fl","c":{"a":0,"k":[0.250999989229,0.161000001197,0.263000009574,1],"ix":4},"o":{"a":0,"k":100,"ix":5},"r":1,"bm":0,"nm":"Fill 1","mn":"ADBE Vector Graphic - Fill","hd":false},{"ty":"tr","p":{"a":0,"k":[91.304,34.23],"ix":2},"a":{"a":0,"k":[0,0],"ix":1},"s":{"a":0,"k":[100,100],"ix":3},"r":{"a":0,"k":0,"ix":6},"o":{"a":0,"k":100,"ix":7},"sk":{"a":0,"k":0,"ix":4},"sa":{"a":0,"k":0,"ix":5},"nm":"Transform"}],"nm":"Group 31","np":2,"cix":2,"bm":0,"ix":31,"mn":"ADBE Vector Group","hd":false},{"ty":"gr","it":[{"ind":0,"ty":"sh","ix":1,"ks":{"a":0,"k":{"i":[[-0.017,-0.817],[13.246,-2.362],[5.458,0],[3.311,2.778],[-0.343,-0.423],[0,0],[-0.013,-0.012],[-0.031,-0.029],[-0.015,-0.014],[-0.047,-0.044],[-0.015,-0.013],[-0.067,-0.06],[-0.006,-0.005],[-16.528,-2.384],[-3.879,-0.111],[-6.049,1.079],[0.3,14.363],[0.201,2.678],[0.025,0.31],[0.053,0.567],[0.031,0.319],[0.086,0.761],[0.016,0.138],[0.122,0.92],[0.039,0.286],[0.107,0.713],[0.047,0.298],[0.176,1.014],[0,0.001],[0.572,1.042],[-0.091,-6.421]],"o":[[0.282,13.48],[-6.913,1.234],[-23.694,0],[0.319,0.439],[0,0],[0.01,0.01],[0.022,0.023],[0.013,0.013],[0.038,0.036],[0.014,0.013],[0.056,0.051],[0.007,0.006],[2.165,1.908],[3.223,0.465],[6.3,0.181],[14.144,-2.523],[-0.05,-2.348],[-0.024,-0.306],[-0.045,-0.554],[-0.029,-0.315],[-0.073,-0.738],[-0.016,-0.137],[-0.103,-0.89],[-0.038,-0.284],[-0.097,-0.697],[-0.045,-0.295],[-0.154,-0.983],[0,0],[-0.455,-1.122],[1.646,7.99],[0.013,0.987]],"v":[[38.886,-2.388],[16.513,24.953],[-2.132,26.812],[-41.186,15.559],[-40.19,16.852],[-40.148,16.893],[-40.115,16.927],[-40.031,17.007],[-39.99,17.048],[-39.861,17.168],[-39.815,17.208],[-39.632,17.374],[-39.613,17.391],[-12.763,27.913],[-2.132,28.812],[16.865,26.923],[40.886,-2.43],[40.516,-9.977],[40.441,-10.905],[40.294,-12.586],[40.204,-13.534],[39.965,-15.781],[39.922,-16.189],[39.581,-18.909],[39.463,-19.767],[39.157,-21.883],[39.021,-22.768],[38.532,-25.758],[38.532,-25.758],[36.972,-28.993],[38.842,-5.103]],"c":true},"ix":2},"nm":"Path 1","mn":"ADBE Vector Shape - Group","hd":false},{"ty":"fl","c":{"a":0,"k":[0.250999989229,0.161000001197,0.263000009574,1],"ix":4},"o":{"a":0,"k":100,"ix":5},"r":1,"bm":0,"nm":"Fill 1","mn":"ADBE Vector Graphic - Fill","hd":false},{"ty":"tr","p":{"a":0,"k":[51.219,48.887],"ix":2},"a":{"a":0,"k":[0,0],"ix":1},"s":{"a":0,"k":[100,100],"ix":3},"r":{"a":0,"k":0,"ix":6},"o":{"a":0,"k":100,"ix":7},"sk":{"a":0,"k":0,"ix":4},"sa":{"a":0,"k":0,"ix":5},"nm":"Transform"}],"nm":"Group 32","np":2,"cix":2,"bm":0,"ix":32,"mn":"ADBE Vector Group","hd":false},{"ty":"gr","it":[{"ind":0,"ty":"sh","ix":1,"ks":{"a":0,"k":{"i":[[4.598,0],[0,0],[0,-4.598],[-4.598,0],[0,0],[0,4.598]],"o":[[0,0],[-4.598,0],[0,4.598],[0,0],[4.598,0],[0,-4.598]],"v":[[2.599,-8.325],[-2.599,-8.325],[-10.924,0],[-2.599,8.325],[2.599,8.325],[10.924,0]],"c":true},"ix":2},"nm":"Path 1","mn":"ADBE Vector Shape - Group","hd":false},{"ty":"fl","c":{"a":0,"k":[0.250999989229,0.161000001197,0.263000009574,1],"ix":4},"o":{"a":0,"k":100,"ix":5},"r":1,"bm":0,"nm":"Fill 1","mn":"ADBE Vector Graphic - Fill","hd":false},{"ty":"tr","p":{"a":0,"k":[47.182,48.097],"ix":2},"a":{"a":0,"k":[0,0],"ix":1},"s":{"a":0,"k":[100,100],"ix":3},"r":{"a":0,"k":0,"ix":6},"o":{"a":0,"k":100,"ix":7},"sk":{"a":0,"k":0,"ix":4},"sa":{"a":0,"k":0,"ix":5},"nm":"Transform"}],"nm":"Group 33","np":2,"cix":2,"bm":0,"ix":33,"mn":"ADBE Vector Group","hd":false},{"ty":"gr","it":[{"ind":0,"ty":"sh","ix":1,"ks":{"a":0,"k":{"i":[[-1.565,-0.498],[0.135,1.646],[1.369,0.149],[-0.397,-1.298]],"o":[[-0.792,-1.356],[-1.315,-0.306],[0.022,1.421],[1.653,0.239]],"v":[[2.733,2.602],[1.301,-1.939],[-2.733,-2.602],[-2.098,1.491]],"c":true},"ix":2},"nm":"Path 1","mn":"ADBE Vector Shape - Group","hd":false},{"ty":"fl","c":{"a":0,"k":[0.250999989229,0.161000001197,0.263000009574,1],"ix":4},"o":{"a":0,"k":100,"ix":5},"r":1,"bm":0,"nm":"Fill 1","mn":"ADBE Vector Graphic - Fill","hd":false},{"ty":"tr","p":{"a":0,"k":[68.216,3.079],"ix":2},"a":{"a":0,"k":[0,0],"ix":1},"s":{"a":0,"k":[100,100],"ix":3},"r":{"a":0,"k":0,"ix":6},"o":{"a":0,"k":100,"ix":7},"sk":{"a":0,"k":0,"ix":4},"sa":{"a":0,"k":0,"ix":5},"nm":"Transform"}],"nm":"Group 34","np":2,"cix":2,"bm":0,"ix":34,"mn":"ADBE Vector Group","hd":false},{"ty":"gr","it":[{"ind":0,"ty":"sh","ix":1,"ks":{"a":0,"k":{"i":[[0.982,0.943],[1.642,-0.083],[-1.095,-1.246],[-1.164,0.736]],"o":[[-1.371,0.738],[1.274,1.041],[1.352,-0.391],[-0.865,-1.054]],"v":[[0.893,-2.349],[-3.671,-1.089],[-0.115,2.349],[3.671,0.643]],"c":true},"ix":2},"nm":"Path 1","mn":"ADBE Vector Shape - Group","hd":false},{"ty":"fl","c":{"a":0,"k":[0.250999989229,0.161000001197,0.263000009574,1],"ix":4},"o":{"a":0,"k":100,"ix":5},"r":1,"bm":0,"nm":"Fill 1","mn":"ADBE Vector Graphic - Fill","hd":false},{"ty":"tr","p":{"a":0,"k":[84.509,12.13],"ix":2},"a":{"a":0,"k":[0,0],"ix":1},"s":{"a":0,"k":[100,100],"ix":3},"r":{"a":0,"k":0,"ix":6},"o":{"a":0,"k":100,"ix":7},"sk":{"a":0,"k":0,"ix":4},"sa":{"a":0,"k":0,"ix":5},"nm":"Transform"}],"nm":"Group 35","np":2,"cix":2,"bm":0,"ix":35,"mn":"ADBE Vector Group","hd":false},{"ty":"gr","it":[{"ind":0,"ty":"sh","ix":1,"ks":{"a":0,"k":{"i":[[-0.282,-1.292],[-1.379,-0.199],[0.022,1.421],[1.268,0],[0,0]],"o":[[1.423,0.008],[-0.397,-1.298],[-1.232,-0.135],[0,0],[0,1.376]],"v":[[-1.884,1.846],[2.323,2.16],[1.688,-1.933],[-2.057,-2.16],[-2.323,-2.16]],"c":true},"ix":2},"nm":"Path 1","mn":"ADBE Vector Shape - Group","hd":false},{"ty":"fl","c":{"a":0,"k":[0.250999989229,0.161000001197,0.263000009574,1],"ix":4},"o":{"a":0,"k":100,"ix":5},"r":1,"bm":0,"nm":"Fill 1","mn":"ADBE Vector Graphic - Fill","hd":false},{"ty":"tr","p":{"a":0,"k":[63.795,2.41],"ix":2},"a":{"a":0,"k":[0,0],"ix":1},"s":{"a":0,"k":[100,100],"ix":3},"r":{"a":0,"k":0,"ix":6},"o":{"a":0,"k":100,"ix":7},"sk":{"a":0,"k":0,"ix":4},"sa":{"a":0,"k":0,"ix":5},"nm":"Transform"}],"nm":"Group 36","np":2,"cix":2,"bm":0,"ix":36,"mn":"ADBE Vector Group","hd":false},{"ty":"gr","it":[{"ind":0,"ty":"sh","ix":1,"ks":{"a":0,"k":{"i":[[-0.778,-1.184],[-0.268,0.116],[-0.852,0.206],[-0.346,-0.118],[0.794,0.966],[1.351,-0.391]],"o":[[0.274,-0.104],[0.077,-0.828],[0.381,-0.093],[-0.685,-1.05],[-1.163,0.736],[0.923,1.05]],"v":[[-0.442,2.528],[0.376,2.21],[1.888,0.451],[2.997,0.503],[0.787,-2.528],[-2.997,-0.822]],"c":true},"ix":2},"nm":"Path 1","mn":"ADBE Vector Shape - Group","hd":false},{"ty":"fl","c":{"a":0,"k":[0.250999989229,0.161000001197,0.263000009574,1],"ix":4},"o":{"a":0,"k":100,"ix":5},"r":1,"bm":0,"nm":"Fill 1","mn":"ADBE Vector Graphic - Fill","hd":false},{"ty":"tr","p":{"a":0,"k":[87.392,15.301],"ix":2},"a":{"a":0,"k":[0,0],"ix":1},"s":{"a":0,"k":[100,100],"ix":3},"r":{"a":0,"k":0,"ix":6},"o":{"a":0,"k":100,"ix":7},"sk":{"a":0,"k":0,"ix":4},"sa":{"a":0,"k":0,"ix":5},"nm":"Transform"}],"nm":"Group 37","np":2,"cix":2,"bm":0,"ix":37,"mn":"ADBE Vector Group","hd":false},{"ty":"gr","it":[{"ind":0,"ty":"sh","ix":1,"ks":{"a":0,"k":{"i":[[-1.371,0.738],[6.082,1.415],[-0.792,-1.356],[-2.918,-2.383]],"o":[[-4.356,-4.179],[0.135,1.646],[3.624,1.152],[1.642,-0.083]],"v":[[7.943,3.69],[-7.943,-4.951],[-6.51,-0.409],[3.38,4.951]],"c":true},"ix":2},"nm":"Path 1","mn":"ADBE Vector Shape - Group","hd":false},{"ty":"fl","c":{"a":0,"k":[0.250999989229,0.161000001197,0.263000009574,1],"ix":4},"o":{"a":0,"k":100,"ix":5},"r":1,"bm":0,"nm":"Fill 1","mn":"ADBE Vector Graphic - Fill","hd":false},{"ty":"tr","p":{"a":0,"k":[77.459,6.091],"ix":2},"a":{"a":0,"k":[0,0],"ix":1},"s":{"a":0,"k":[100,100],"ix":3},"r":{"a":0,"k":0,"ix":6},"o":{"a":0,"k":100,"ix":7},"sk":{"a":0,"k":0,"ix":4},"sa":{"a":0,"k":0,"ix":5},"nm":"Transform"}],"nm":"Group 38","np":2,"cix":2,"bm":0,"ix":38,"mn":"ADBE Vector Group","hd":false},{"ty":"gr","it":[{"ind":0,"ty":"sh","ix":1,"ks":{"a":0,"k":{"i":[[-1.444,1.167],[0.49,0],[1.202,0.462],[0.857,-1.103],[-1.443,-0.25]],"o":[[-0.474,0.063],[-1.362,0],[-0.983,0.989],[1.268,0.637],[1.207,-1.409]],"v":[[4.032,-1.628],[2.589,-1.52],[-1.274,-2.245],[-4.032,0.899],[0.048,2.245]],"c":true},"ix":2},"nm":"Path 1","mn":"ADBE Vector Shape - Group","hd":false},{"ty":"fl","c":{"a":0,"k":[0.250999989229,0.161000001197,0.263000009574,1],"ix":4},"o":{"a":0,"k":100,"ix":5},"r":1,"bm":0,"nm":"Fill 1","mn":"ADBE Vector Graphic - Fill","hd":false},{"ty":"tr","p":{"a":0,"k":[11.48,12.589],"ix":2},"a":{"a":0,"k":[0,0],"ix":1},"s":{"a":0,"k":[100,100],"ix":3},"r":{"a":0,"k":0,"ix":6},"o":{"a":0,"k":100,"ix":7},"sk":{"a":0,"k":0,"ix":4},"sa":{"a":0,"k":0,"ix":5},"nm":"Transform"}],"nm":"Group 39","np":2,"cix":2,"bm":0,"ix":39,"mn":"ADBE Vector Group","hd":false},{"ty":"gr","it":[{"ind":0,"ty":"sh","ix":1,"ks":{"a":0,"k":{"i":[[1.037,-1.426],[-1.834,0.394],[-0.046,1.468],[1.328,-0.391]],"o":[[1.695,-0.711],[0.445,-1.331],[-1.39,0.229],[-0.238,1.831]],"v":[[-3.024,2.938],[2.279,1.275],[3.024,-2.938],[-1.054,-2.003]],"c":true},"ix":2},"nm":"Path 1","mn":"ADBE Vector Shape - Group","hd":false},{"ty":"fl","c":{"a":0,"k":[0.250999989229,0.161000001197,0.263000009574,1],"ix":4},"o":{"a":0,"k":100,"ix":5},"r":1,"bm":0,"nm":"Fill 1","mn":"ADBE Vector Graphic - Fill","hd":false},{"ty":"tr","p":{"a":0,"k":[25.84,3.653],"ix":2},"a":{"a":0,"k":[0,0],"ix":1},"s":{"a":0,"k":[100,100],"ix":3},"r":{"a":0,"k":0,"ix":6},"o":{"a":0,"k":100,"ix":7},"sk":{"a":0,"k":0,"ix":4},"sa":{"a":0,"k":0,"ix":5},"nm":"Transform"}],"nm":"Group 40","np":2,"cix":2,"bm":0,"ix":40,"mn":"ADBE Vector Group","hd":false},{"ty":"gr","it":[{"ind":0,"ty":"sh","ix":1,"ks":{"a":0,"k":{"i":[[-1.468,0.099],[-0.003,1.387],[1.317,-0.218],[0.445,-1.331]],"o":[[0.289,-1.302],[-1.364,0.062],[-0.046,1.467],[1.404,-0.302]],"v":[[1.928,1.717],[2.383,-2.318],[-1.639,-1.894],[-2.383,2.318]],"c":true},"ix":2},"nm":"Path 1","mn":"ADBE Vector Shape - Group","hd":false},{"ty":"fl","c":{"a":0,"k":[0.250999989229,0.161000001197,0.263000009574,1],"ix":4},"o":{"a":0,"k":100,"ix":5},"r":1,"bm":0,"nm":"Fill 1","mn":"ADBE Vector Graphic - Fill","hd":false},{"ty":"tr","p":{"a":0,"k":[30.503,2.609],"ix":2},"a":{"a":0,"k":[0,0],"ix":1},"s":{"a":0,"k":[100,100],"ix":3},"r":{"a":0,"k":0,"ix":6},"o":{"a":0,"k":100,"ix":7},"sk":{"a":0,"k":0,"ix":4},"sa":{"a":0,"k":0,"ix":5},"nm":"Transform"}],"nm":"Group 41","np":2,"cix":2,"bm":0,"ix":41,"mn":"ADBE Vector Group","hd":false},{"ty":"gr","it":[{"ind":0,"ty":"sh","ix":1,"ks":{"a":0,"k":{"i":[[-0.945,1.103],[1.268,0.637],[0.698,-1.157],[-1.324,-0.376]],"o":[[-1.443,-0.25],[-0.826,1.063],[1.188,0.643],[0.78,-1.231]],"v":[[3.188,-1.079],[-0.893,-2.425],[-3.188,0.903],[0.596,2.425]],"c":true},"ix":2},"nm":"Path 1","mn":"ADBE Vector Shape - Group","hd":false},{"ty":"fl","c":{"a":0,"k":[0.250999989229,0.161000001197,0.263000009574,1],"ix":4},"o":{"a":0,"k":100,"ix":5},"r":1,"bm":0,"nm":"Fill 1","mn":"ADBE Vector Graphic - Fill","hd":false},{"ty":"tr","p":{"a":0,"k":[8.34,15.914],"ix":2},"a":{"a":0,"k":[0,0],"ix":1},"s":{"a":0,"k":[100,100],"ix":3},"r":{"a":0,"k":0,"ix":6},"o":{"a":0,"k":100,"ix":7},"sk":{"a":0,"k":0,"ix":4},"sa":{"a":0,"k":0,"ix":5},"nm":"Transform"}],"nm":"Group 42","np":2,"cix":2,"bm":0,"ix":42,"mn":"ADBE Vector Group","hd":false},{"ty":"gr","it":[{"ind":0,"ty":"sh","ix":1,"ks":{"a":0,"k":{"i":[[-0.238,1.831],[3.999,-4.022],[-1.363,0],[-0.474,0.063],[-2.648,1.111]],"o":[[-5.586,1.646],[1.202,0.462],[0.49,0],[2.202,-1.78],[1.036,-1.426]],"v":[[7.29,-4.71],[-7.29,3.984],[-3.427,4.71],[-1.984,4.603],[5.32,0.232]],"c":true},"ix":2},"nm":"Path 1","mn":"ADBE Vector Shape - Group","hd":false},{"ty":"fl","c":{"a":0,"k":[0.250999989229,0.161000001197,0.263000009574,1],"ix":4},"o":{"a":0,"k":100,"ix":5},"r":1,"bm":0,"nm":"Fill 1","mn":"ADBE Vector Graphic - Fill","hd":false},{"ty":"tr","p":{"a":0,"k":[17.496,6.359],"ix":2},"a":{"a":0,"k":[0,0],"ix":1},"s":{"a":0,"k":[100,100],"ix":3},"r":{"a":0,"k":0,"ix":6},"o":{"a":0,"k":100,"ix":7},"sk":{"a":0,"k":0,"ix":4},"sa":{"a":0,"k":0,"ix":5},"nm":"Transform"}],"nm":"Group 43","np":2,"cix":2,"bm":0,"ix":43,"mn":"ADBE Vector Group","hd":false},{"ty":"gr","it":[{"ind":0,"ty":"sh","ix":1,"ks":{"a":0,"k":{"i":[[-0.389,-0.708],[0.137,0.566],[-0.02,0.214],[0.274,-0.104]],"o":[[-0.121,-0.584],[-0.054,-0.221],[-0.268,0.116],[0.439,0.669]],"v":[[0.621,1.191],[0.237,-0.536],[0.198,-1.191],[-0.621,-0.873]],"c":true},"ix":2},"nm":"Path 1","mn":"ADBE Vector Shape - Group","hd":false},{"ty":"fl","c":{"a":0,"k":[0.250999989229,0.161000001197,0.263000009574,1],"ix":4},"o":{"a":0,"k":100,"ix":5},"r":1,"bm":0,"nm":"Fill 1","mn":"ADBE Vector Graphic - Fill","hd":false},{"ty":"tr","p":{"a":0,"k":[87.571,18.702],"ix":2},"a":{"a":0,"k":[0,0],"ix":1},"s":{"a":0,"k":[100,100],"ix":3},"r":{"a":0,"k":0,"ix":6},"o":{"a":0,"k":100,"ix":7},"sk":{"a":0,"k":0,"ix":4},"sa":{"a":0,"k":0,"ix":5},"nm":"Transform"}],"nm":"Group 44","np":2,"cix":2,"bm":0,"ix":44,"mn":"ADBE Vector Group","hd":false},{"ty":"gr","it":[{"ind":0,"ty":"sh","ix":1,"ks":{"a":0,"k":{"i":[[-0.687,0],[0,0],[-0.058,0],[0,1.376],[0,0],[0.525,-0.025],[0.289,-1.302]],"o":[[0,0],[0.058,0],[-0.282,-1.292],[0,0],[-0.532,0],[-0.003,1.386],[0.676,-0.046]],"v":[[-12.699,1.961],[14.568,1.961],[14.741,1.967],[14.302,-2.039],[-12.699,-2.039],[-14.285,-1.997],[-14.741,2.039]],"c":true},"ix":2},"nm":"Path 1","mn":"ADBE Vector Shape - Group","hd":false},{"ty":"fl","c":{"a":0,"k":[0.250999989229,0.161000001197,0.263000009574,1],"ix":4},"o":{"a":0,"k":100,"ix":5},"r":1,"bm":0,"nm":"Fill 1","mn":"ADBE Vector Graphic - Fill","hd":false},{"ty":"tr","p":{"a":0,"k":[47.171,2.288],"ix":2},"a":{"a":0,"k":[0,0],"ix":1},"s":{"a":0,"k":[100,100],"ix":3},"r":{"a":0,"k":0,"ix":6},"o":{"a":0,"k":100,"ix":7},"sk":{"a":0,"k":0,"ix":4},"sa":{"a":0,"k":0,"ix":5},"nm":"Transform"}],"nm":"Group 45","np":2,"cix":2,"bm":0,"ix":45,"mn":"ADBE Vector Group","hd":false},{"ty":"gr","it":[{"ind":0,"ty":"sh","ix":1,"ks":{"a":0,"k":{"i":[[-0.457,0.427],[-0.756,-0.802],[-0.629,-0.528],[0,6.423],[0,0],[-2.963,4.672],[1.188,0.642],[0,-6.46],[0,0],[-3.399,-5.315]],"o":[[0.804,-0.752],[0.018,0.019],[-3.723,-5.126],[0,0],[0,-5.929],[-1.324,-0.376],[-3.111,5.155],[0,0],[0,6.778],[-0.039,-0.579]],"v":[[1.106,22.535],[3.928,22.626],[4.892,23.497],[-0.892,5.728],[-0.892,-6.477],[3.794,-22.61],[0.011,-24.132],[-4.892,-6.477],[-4.892,5.728],[0.485,24.132]],"c":true},"ix":2},"nm":"Path 1","mn":"ADBE Vector Shape - Group","hd":false},{"ty":"fl","c":{"a":0,"k":[0.250999989229,0.161000001197,0.263000009574,1],"ix":4},"o":{"a":0,"k":100,"ix":5},"r":1,"bm":0,"nm":"Fill 1","mn":"ADBE Vector Graphic - Fill","hd":false},{"ty":"tr","p":{"a":0,"k":[5.142,40.949],"ix":2},"a":{"a":0,"k":[0,0],"ix":1},"s":{"a":0,"k":[100,100],"ix":3},"r":{"a":0,"k":0,"ix":6},"o":{"a":0,"k":100,"ix":7},"sk":{"a":0,"k":0,"ix":4},"sa":{"a":0,"k":0,"ix":5},"nm":"Transform"}],"nm":"Group 46","np":2,"cix":2,"bm":0,"ix":46,"mn":"ADBE Vector Group","hd":false}],"ip":0,"op":120.0000048877,"st":0,"bm":0},{"ddd":0,"ind":7,"ty":3,"nm":"B | BODY | MAIN","sr":1,"ks":{"o":{"a":0,"k":100,"ix":11},"r":{"a":0,"k":0,"ix":10},"p":{"a":1,"k":[{"i":{"x":0.667,"y":1},"o":{"x":0.333,"y":0},"t":0,"s":[278,248.5,0],"to":[0,-1.5,0],"ti":[0,0,0]},{"i":{"x":0.667,"y":1},"o":{"x":0.333,"y":0},"t":10,"s":[278,239.5,0],"to":[0,0,0],"ti":[0,0,0]},{"i":{"x":0.667,"y":1},"o":{"x":0.333,"y":0},"t":20,"s":[278,248.5,0],"to":[0,0,0],"ti":[0,0,0]},{"i":{"x":0.667,"y":1},"o":{"x":0.333,"y":0},"t":30,"s":[278,239.5,0],"to":[0,0,0],"ti":[0,-1.5,0]},{"t":40.0000016292334,"s":[278,248.5,0]}],"ix":2,"l":2,"x":"var $bm_rt;\n$bm_rt = loopOut('cycle', 0);"},"a":{"a":0,"k":[0,0,0],"ix":1,"l":2},"s":{"a":1,"k":[{"i":{"x":[0.667,0.667,0.667],"y":[1,1,1]},"o":{"x":[0.333,0.333,0.333],"y":[0,0,0]},"t":0,"s":[100,103,100]},{"i":{"x":[0.667,0.667,0.667],"y":[1,1,1]},"o":{"x":[0.333,0.333,0.333],"y":[0,0,0]},"t":10,"s":[100,100,100]},{"i":{"x":[0.667,0.667,0.667],"y":[1,1,1]},"o":{"x":[0.333,0.333,0.333],"y":[0,0,0]},"t":20,"s":[100,103,100]},{"i":{"x":[0.667,0.667,0.667],"y":[1,1,1]},"o":{"x":[0.333,0.333,0.333],"y":[0,0,0]},"t":30,"s":[100,100,100]},{"t":40.0000016292334,"s":[100,103,100]}],"ix":6,"l":2,"x":"var $bm_rt;\n$bm_rt = loopOut('cycle', 0);"}},"ao":0,"ef":[{"ty":5,"nm":"Bone","np":4,"mn":"Pseudo/DUIK bone","ix":1,"en":1,"ef":[{"ty":2,"nm":"Color","mn":"Pseudo/DUIK bone-0001","ix":1,"v":{"a":0,"k":[0.92549020052,0.0941176489,0.0941176489,1],"ix":1}},{"ty":0,"nm":"Size","mn":"Pseudo/DUIK bone-0002","ix":2,"v":{"a":0,"k":34,"ix":2}}]}],"ip":0,"op":120.0000048877,"st":0,"bm":0},{"ddd":0,"ind":9,"ty":4,"nm":"BODY","sr":1,"ks":{"o":{"a":0,"k":100,"ix":11},"r":{"a":0,"k":0,"ix":10},"p":{"a":0,"k":[251.078,263.409,0],"ix":2,"l":2},"a":{"a":0,"k":[172.525,135.938,0],"ix":1,"l":2},"s":{"a":0,"k":[100,100,100],"ix":6,"l":2}},"ao":0,"ef":[{"ty":34,"nm":"Puppet","np":6,"mn":"ADBE FreePin3","ix":1,"en":1,"ef":[{"ty":7,"nm":"Puppet Engine","mn":"ADBE FreePin3 Puppet Engine","ix":1,"v":{"a":0,"k":2,"ix":1}},{"ty":0,"nm":"Mesh Rotation Refinement","mn":"ADBE FreePin3 Auto Rotate Pins","ix":2,"v":{"a":0,"k":20,"ix":2}},{"ty":7,"nm":"On Transparent","mn":"ADBE FreePin3 On Transparent","ix":3,"v":{"a":0,"k":0,"ix":3}},{"ty":29.9700012207031,"nm":"arap","np":3,"mn":"ADBE FreePin3 ARAP Group","ix":4,"en":1,"ef":[{"ty":6,"nm":"Auto-traced Shapes","mn":"ADBE FreePin3 Outlines","ix":1,"v":0},{"ty":1,"nm":"Mesh","np":2,"mn":"ADBE FreePin3 Mesh Group","ix":2,"en":1,"ef":[{"nm":"Mesh 1","np":8,"mn":"ADBE FreePin3 Mesh Atom","ix":1,"en":1,"ef":[{"ty":6,"nm":"Mesh","mn":"ADBE FreePin3 Mesh","ix":1,"v":0},{"ty":0,"nm":"Triangles","mn":"ADBE FreePin3 Mesh Tri Count","ix":2,"v":{"a":0,"k":50,"ix":2}},{"ty":0,"nm":"Density","mn":"ADBE FreePin3 Mesh Tri Density","ix":3,"v":{"a":0,"k":12,"ix":3}},{"ty":0,"nm":"Expansion","mn":"ADBE FreePin3 Mesh Expansion","ix":4,"v":{"a":0,"k":30,"ix":4}},{"nm":"Deform","np":11,"mn":"ADBE FreePin3 PosPins","ix":5,"en":1,"ef":[{"nm":"L LEG A4","np":7,"mn":"ADBE FreePin3 PosPin Atom","ix":1,"en":1,"ef":[{"ty":3,"nm":"Vertex Offset","mn":"ADBE FreePin3 PosPin Vtx Offset","ix":1,"v":{"a":0,"k":[0,0],"ix":1}},{"ty":0,"nm":"Vertex Index","mn":"ADBE FreePin3 PosPin Vtx Index","ix":2,"v":{"a":0,"k":25,"ix":2}},{"ty":7,"nm":"Pin Type","mn":"ADBE FreePin3 PosPin Type","ix":3,"v":{"a":0,"k":1,"ix":3}},{"ty":3,"nm":"Position","mn":"ADBE FreePin3 PosPin Position","ix":4,"v":{"a":0,"k":[223.5,373],"ix":4,"x":"var $bm_rt;\nvar l = null;\ntry {\n    l = effect('B | L LEG A4 - 4')(1);\n} catch (e) {\n}\n;\nvar result = value;\nif (l != null) {\n    result = l.toWorld(l.anchorPoint);\n}\n$bm_rt = result;"}},{"ty":0,"nm":"Scale","mn":"ADBE FreePin3 PosPin Scale","ix":5,"v":{"a":0,"k":100,"ix":5}},{"ty":0,"nm":"Rotation","mn":"ADBE FreePin3 PosPin Rotation","ix":6,"v":{"a":0,"k":0,"ix":6}}]},{"nm":"L LEG A3","np":7,"mn":"ADBE FreePin3 PosPin Atom","ix":2,"en":1,"ef":[{"ty":3,"nm":"Vertex Offset","mn":"ADBE FreePin3 PosPin Vtx Offset","ix":1,"v":{"a":0,"k":[0,0],"ix":1}},{"ty":0,"nm":"Vertex Index","mn":"ADBE FreePin3 PosPin Vtx Index","ix":2,"v":{"a":0,"k":26,"ix":2}},{"ty":7,"nm":"Pin Type","mn":"ADBE FreePin3 PosPin Type","ix":3,"v":{"a":0,"k":1,"ix":3}},{"ty":3,"nm":"Position","mn":"ADBE FreePin3 PosPin Position","ix":4,"v":{"a":0,"k":[225.5,322],"ix":4,"x":"var $bm_rt;\nvar l = null;\ntry {\n    l = effect('B | L LEG A3 - 4')(1);\n} catch (e) {\n}\n;\nvar result = value;\nif (l != null) {\n    result = l.toWorld(l.anchorPoint);\n}\n$bm_rt = result;"}},{"ty":0,"nm":"Scale","mn":"ADBE FreePin3 PosPin Scale","ix":5,"v":{"a":0,"k":100,"ix":5}},{"ty":0,"nm":"Rotation","mn":"ADBE FreePin3 PosPin Rotation","ix":6,"v":{"a":0,"k":0,"ix":6}}]},{"nm":"L LEG A2","np":7,"mn":"ADBE FreePin3 PosPin Atom","ix":3,"en":1,"ef":[{"ty":3,"nm":"Vertex Offset","mn":"ADBE FreePin3 PosPin Vtx Offset","ix":1,"v":{"a":0,"k":[0,0],"ix":1}},{"ty":0,"nm":"Vertex Index","mn":"ADBE FreePin3 PosPin Vtx Index","ix":2,"v":{"a":0,"k":27,"ix":2}},{"ty":7,"nm":"Pin Type","mn":"ADBE FreePin3 PosPin Type","ix":3,"v":{"a":0,"k":1,"ix":3}},{"ty":3,"nm":"Position","mn":"ADBE FreePin3 PosPin Position","ix":4,"v":{"a":0,"k":[225.5,274],"ix":4,"x":"var $bm_rt;\nvar l = null;\ntry {\n    l = effect('B | L LEG A2 - 4')(1);\n} catch (e) {\n}\n;\nvar result = value;\nif (l != null) {\n    result = l.toWorld(l.anchorPoint);\n}\n$bm_rt = result;"}},{"ty":0,"nm":"Scale","mn":"ADBE FreePin3 PosPin Scale","ix":5,"v":{"a":0,"k":100,"ix":5}},{"ty":0,"nm":"Rotation","mn":"ADBE FreePin3 PosPin Rotation","ix":6,"v":{"a":0,"k":0,"ix":6}}]},{"nm":"L LEG A1","np":7,"mn":"ADBE FreePin3 PosPin Atom","ix":4,"en":1,"ef":[{"ty":3,"nm":"Vertex Offset","mn":"ADBE FreePin3 PosPin Vtx Offset","ix":1,"v":{"a":0,"k":[0,0],"ix":1}},{"ty":0,"nm":"Vertex Index","mn":"ADBE FreePin3 PosPin Vtx Index","ix":2,"v":{"a":0,"k":28,"ix":2}},{"ty":7,"nm":"Pin Type","mn":"ADBE FreePin3 PosPin Type","ix":3,"v":{"a":0,"k":1,"ix":3}},{"ty":3,"nm":"Position","mn":"ADBE FreePin3 PosPin Position","ix":4,"v":{"a":0,"k":[226,215],"ix":4,"x":"var $bm_rt;\nvar l = null;\ntry {\n    l = effect('B | L LEG A1 - 4')(1);\n} catch (e) {\n}\n;\nvar result = value;\nif (l != null) {\n    result = l.toWorld(l.anchorPoint);\n}\n$bm_rt = result;"}},{"ty":0,"nm":"Scale","mn":"ADBE FreePin3 PosPin Scale","ix":5,"v":{"a":0,"k":100,"ix":5}},{"ty":0,"nm":"Rotation","mn":"ADBE FreePin3 PosPin Rotation","ix":6,"v":{"a":0,"k":0,"ix":6}}]},{"nm":"L LEG B4","np":7,"mn":"ADBE FreePin3 PosPin Atom","ix":5,"en":1,"ef":[{"ty":3,"nm":"Vertex Offset","mn":"ADBE FreePin3 PosPin Vtx Offset","ix":1,"v":{"a":0,"k":[0,0],"ix":1}},{"ty":0,"nm":"Vertex Index","mn":"ADBE FreePin3 PosPin Vtx Index","ix":2,"v":{"a":0,"k":29,"ix":2}},{"ty":7,"nm":"Pin Type","mn":"ADBE FreePin3 PosPin Type","ix":3,"v":{"a":0,"k":1,"ix":3}},{"ty":3,"nm":"Position","mn":"ADBE FreePin3 PosPin Position","ix":4,"v":{"a":0,"k":[364,371.5],"ix":4,"x":"var $bm_rt;\nvar l = null;\ntry {\n    l = effect('B | L LEG B4 - 4')(1);\n} catch (e) {\n}\n;\nvar result = value;\nif (l != null) {\n    result = l.toWorld(l.anchorPoint);\n}\n$bm_rt = result;"}},{"ty":0,"nm":"Scale","mn":"ADBE FreePin3 PosPin Scale","ix":5,"v":{"a":0,"k":100,"ix":5}},{"ty":0,"nm":"Rotation","mn":"ADBE FreePin3 PosPin Rotation","ix":6,"v":{"a":0,"k":0,"ix":6}}]},{"nm":"L LEG B3","np":7,"mn":"ADBE FreePin3 PosPin Atom","ix":6,"en":1,"ef":[{"ty":3,"nm":"Vertex Offset","mn":"ADBE FreePin3 PosPin Vtx Offset","ix":1,"v":{"a":0,"k":[0,0],"ix":1}},{"ty":0,"nm":"Vertex Index","mn":"ADBE FreePin3 PosPin Vtx Index","ix":2,"v":{"a":0,"k":30,"ix":2}},{"ty":7,"nm":"Pin Type","mn":"ADBE FreePin3 PosPin Type","ix":3,"v":{"a":0,"k":1,"ix":3}},{"ty":3,"nm":"Position","mn":"ADBE FreePin3 PosPin Position","ix":4,"v":{"a":0,"k":[363.5,322],"ix":4,"x":"var $bm_rt;\nvar l = null;\ntry {\n    l = effect('B | L LEG B3 - 4')(1);\n} catch (e) {\n}\n;\nvar result = value;\nif (l != null) {\n    result = l.toWorld(l.anchorPoint);\n}\n$bm_rt = result;"}},{"ty":0,"nm":"Scale","mn":"ADBE FreePin3 PosPin Scale","ix":5,"v":{"a":0,"k":100,"ix":5}},{"ty":0,"nm":"Rotation","mn":"ADBE FreePin3 PosPin Rotation","ix":6,"v":{"a":0,"k":0,"ix":6}}]},{"nm":"L LEG B2","np":7,"mn":"ADBE FreePin3 PosPin Atom","ix":7,"en":1,"ef":[{"ty":3,"nm":"Vertex Offset","mn":"ADBE FreePin3 PosPin Vtx Offset","ix":1,"v":{"a":0,"k":[0,0],"ix":1}},{"ty":0,"nm":"Vertex Index","mn":"ADBE FreePin3 PosPin Vtx Index","ix":2,"v":{"a":0,"k":31,"ix":2}},{"ty":7,"nm":"Pin Type","mn":"ADBE FreePin3 PosPin Type","ix":3,"v":{"a":0,"k":1,"ix":3}},{"ty":3,"nm":"Position","mn":"ADBE FreePin3 PosPin Position","ix":4,"v":{"a":0,"k":[358,273.5],"ix":4,"x":"var $bm_rt;\nvar l = null;\ntry {\n    l = effect('B | L LEG B2 - 4')(1);\n} catch (e) {\n}\n;\nvar result = value;\nif (l != null) {\n    result = l.toWorld(l.anchorPoint);\n}\n$bm_rt = result;"}},{"ty":0,"nm":"Scale","mn":"ADBE FreePin3 PosPin Scale","ix":5,"v":{"a":0,"k":100,"ix":5}},{"ty":0,"nm":"Rotation","mn":"ADBE FreePin3 PosPin Rotation","ix":6,"v":{"a":0,"k":0,"ix":6}}]},{"nm":"L LEG B1","np":7,"mn":"ADBE FreePin3 PosPin Atom","ix":8,"en":1,"ef":[{"ty":3,"nm":"Vertex Offset","mn":"ADBE FreePin3 PosPin Vtx Offset","ix":1,"v":{"a":0,"k":[0,0],"ix":1}},{"ty":0,"nm":"Vertex Index","mn":"ADBE FreePin3 PosPin Vtx Index","ix":2,"v":{"a":0,"k":32,"ix":2}},{"ty":7,"nm":"Pin Type","mn":"ADBE FreePin3 PosPin Type","ix":3,"v":{"a":0,"k":1,"ix":3}},{"ty":3,"nm":"Position","mn":"ADBE FreePin3 PosPin Position","ix":4,"v":{"a":0,"k":[350.5,216.5],"ix":4,"x":"var $bm_rt;\nvar l = null;\ntry {\n    l = effect('B | L LEG B1 - 4')(1);\n} catch (e) {\n}\n;\nvar result = value;\nif (l != null) {\n    result = l.toWorld(l.anchorPoint);\n}\n$bm_rt = result;"}},{"ty":0,"nm":"Scale","mn":"ADBE FreePin3 PosPin Scale","ix":5,"v":{"a":0,"k":100,"ix":5}},{"ty":0,"nm":"Rotation","mn":"ADBE FreePin3 PosPin Rotation","ix":6,"v":{"a":0,"k":0,"ix":6}}]},{"nm":"MAIN","np":7,"mn":"ADBE FreePin3 PosPin Atom","ix":9,"en":1,"ef":[{"ty":3,"nm":"Vertex Offset","mn":"ADBE FreePin3 PosPin Vtx Offset","ix":1,"v":{"a":0,"k":[0,0],"ix":1}},{"ty":0,"nm":"Vertex Index","mn":"ADBE FreePin3 PosPin Vtx Index","ix":2,"v":{"a":0,"k":33,"ix":2}},{"ty":7,"nm":"Pin Type","mn":"ADBE FreePin3 PosPin Type","ix":3,"v":{"a":0,"k":1,"ix":3}},{"ty":3,"nm":"Position","mn":"ADBE FreePin3 PosPin Position","ix":4,"v":{"a":0,"k":[278,239.5],"ix":4,"x":"var $bm_rt;\nvar l = null;\ntry {\n    l = effect('B | MAIN - 4')(1);\n} catch (e) {\n}\n;\nvar result = value;\nif (l != null) {\n    result = l.toWorld(l.anchorPoint);\n}\n$bm_rt = result;"}},{"ty":0,"nm":"Scale","mn":"ADBE FreePin3 PosPin Scale","ix":5,"v":{"a":0,"k":100,"ix":5}},{"ty":0,"nm":"Rotation","mn":"ADBE FreePin3 PosPin Rotation","ix":6,"v":{"a":0,"k":0,"ix":6}}]},{"nm":"HEAD","np":7,"mn":"ADBE FreePin3 PosPin Atom","ix":10,"en":1,"ef":[{"ty":3,"nm":"Vertex Offset","mn":"ADBE FreePin3 PosPin Vtx Offset","ix":1,"v":{"a":0,"k":[0,0],"ix":1}},{"ty":0,"nm":"Vertex Index","mn":"ADBE FreePin3 PosPin Vtx Index","ix":2,"v":{"a":0,"k":34,"ix":2}},{"ty":7,"nm":"Pin Type","mn":"ADBE FreePin3 PosPin Type","ix":3,"v":{"a":0,"k":1,"ix":3}},{"ty":3,"nm":"Position","mn":"ADBE FreePin3 PosPin Position","ix":4,"v":{"a":0,"k":[146,184],"ix":4,"x":"var $bm_rt;\nvar l = null;\ntry {\n    l = effect('B | HEAD - 4')(1);\n} catch (e) {\n}\n;\nvar result = value;\nif (l != null) {\n    result = l.toWorld(l.anchorPoint);\n}\n$bm_rt = result;"}},{"ty":0,"nm":"Scale","mn":"ADBE FreePin3 PosPin Scale","ix":5,"v":{"a":0,"k":100,"ix":5}},{"ty":0,"nm":"Rotation","mn":"ADBE FreePin3 PosPin Rotation","ix":6,"v":{"a":0,"k":0,"ix":6}}]}]},{"nm":"Overlap","np":1,"mn":"ADBE FreePin3 HghtPins","ix":6,"en":1,"ef":[]},{"nm":"Stiffness","np":1,"mn":"ADBE FreePin3 StarchPins","ix":7,"en":1,"ef":[]}]}]}]}]},{"ty":5,"nm":"B | L LEG A4 - 4","np":4,"mn":"Pseudo/DUIK bone linker","ix":2,"en":1,"ef":[{"ty":10,"nm":"Layer","mn":"Pseudo/DUIK bone linker-0001","ix":1,"v":{"a":0,"k":16,"ix":1}},{"ty":2,"nm":"Bone color","mn":"Pseudo/DUIK bone linker-0002","ix":2,"v":{"a":0,"k":[0.925490196078,0.094117647059,0.094117647059,1],"ix":2}}]},{"ty":5,"nm":"B | L LEG A3 - 4","np":4,"mn":"Pseudo/DUIK bone linker","ix":3,"en":1,"ef":[{"ty":10,"nm":"Layer","mn":"Pseudo/DUIK bone linker-0001","ix":1,"v":{"a":0,"k":17,"ix":1}},{"ty":2,"nm":"Bone color","mn":"Pseudo/DUIK bone linker-0002","ix":2,"v":{"a":0,"k":[0.925490196078,0.094117647059,0.094117647059,1],"ix":2}}]},{"ty":5,"nm":"B | L LEG A2 - 4","np":4,"mn":"Pseudo/DUIK bone linker","ix":4,"en":1,"ef":[{"ty":10,"nm":"Layer","mn":"Pseudo/DUIK bone linker-0001","ix":1,"v":{"a":0,"k":18,"ix":1}},{"ty":2,"nm":"Bone color","mn":"Pseudo/DUIK bone linker-0002","ix":2,"v":{"a":0,"k":[0.925490196078,0.094117647059,0.094117647059,1],"ix":2}}]},{"ty":5,"nm":"B | L LEG A1 - 4","np":4,"mn":"Pseudo/DUIK bone linker","ix":5,"en":1,"ef":[{"ty":10,"nm":"Layer","mn":"Pseudo/DUIK bone linker-0001","ix":1,"v":{"a":0,"k":19,"ix":1}},{"ty":2,"nm":"Bone color","mn":"Pseudo/DUIK bone linker-0002","ix":2,"v":{"a":0,"k":[0.925490196078,0.094117647059,0.094117647059,1],"ix":2}}]},{"ty":5,"nm":"B | L LEG B4 - 4","np":4,"mn":"Pseudo/DUIK bone linker","ix":6,"en":1,"ef":[{"ty":10,"nm":"Layer","mn":"Pseudo/DUIK bone linker-0001","ix":1,"v":{"a":0,"k":20,"ix":1}},{"ty":2,"nm":"Bone color","mn":"Pseudo/DUIK bone linker-0002","ix":2,"v":{"a":0,"k":[0.925490196078,0.094117647059,0.094117647059,1],"ix":2}}]},{"ty":5,"nm":"B | L LEG B3 - 4","np":4,"mn":"Pseudo/DUIK bone linker","ix":7,"en":1,"ef":[{"ty":10,"nm":"Layer","mn":"Pseudo/DUIK bone linker-0001","ix":1,"v":{"a":0,"k":21,"ix":1}},{"ty":2,"nm":"Bone color","mn":"Pseudo/DUIK bone linker-0002","ix":2,"v":{"a":0,"k":[0.925490196078,0.094117647059,0.094117647059,1],"ix":2}}]},{"ty":5,"nm":"B | L LEG B2 - 4","np":4,"mn":"Pseudo/DUIK bone linker","ix":8,"en":1,"ef":[{"ty":10,"nm":"Layer","mn":"Pseudo/DUIK bone linker-0001","ix":1,"v":{"a":0,"k":22,"ix":1}},{"ty":2,"nm":"Bone color","mn":"Pseudo/DUIK bone linker-0002","ix":2,"v":{"a":0,"k":[0.925490196078,0.094117647059,0.094117647059,1],"ix":2}}]},{"ty":5,"nm":"B | L LEG B1 - 4","np":4,"mn":"Pseudo/DUIK bone linker","ix":9,"en":1,"ef":[{"ty":10,"nm":"Layer","mn":"Pseudo/DUIK bone linker-0001","ix":1,"v":{"a":0,"k":23,"ix":1}},{"ty":2,"nm":"Bone color","mn":"Pseudo/DUIK bone linker-0002","ix":2,"v":{"a":0,"k":[0.925490196078,0.094117647059,0.094117647059,1],"ix":2}}]},{"ty":5,"nm":"B | MAIN - 4","np":4,"mn":"Pseudo/DUIK bone linker","ix":10,"en":1,"ef":[{"ty":10,"nm":"Layer","mn":"Pseudo/DUIK bone linker-0001","ix":1,"v":{"a":0,"k":7,"ix":1}},{"ty":2,"nm":"Bone color","mn":"Pseudo/DUIK bone linker-0002","ix":2,"v":{"a":0,"k":[0.925490196078,0.094117647059,0.094117647059,1],"ix":2}}]},{"ty":5,"nm":"B | HEAD - 4","np":4,"mn":"Pseudo/DUIK bone linker","ix":11,"en":1,"ef":[{"ty":10,"nm":"Layer","mn":"Pseudo/DUIK bone linker-0001","ix":1,"v":{"a":0,"k":8,"ix":1}},{"ty":2,"nm":"Bone color","mn":"Pseudo/DUIK bone linker-0002","ix":2,"v":{"a":0,"k":[0.925490196078,0.094117647059,0.094117647059,1],"ix":2}}]}],"shapes":[{"ty":"gr","it":[{"ind":0,"ty":"sh","ix":1,"ks":{"a":0,"k":{"i":[[0.013,0.953],[0.015,0.859],[0.623,5.346],[0.122,0.831],[0.31,1.432],[0.507,0.789],[-0.047,0.031],[0.097,0.033],[0.773,0.942],[0.958,0.919],[5.928,1.38],[1.334,0.146],[1.236,0],[0,0],[0,0],[0.512,-0.024],[1.285,-0.212],[1.294,-0.381],[3.899,-3.92],[0.836,-1.075],[0.681,-1.128],[0,-6.298],[0,0],[-3.313,-5.181],[-0.319,-0.341],[-0.557,-0.492],[-2.546,-1.514],[-2.382,-1.009],[-9.142,-0.789],[-2.905,0],[-6.965,1.244],[0.315,15.072]],"o":[[-0.011,-0.777],[-0.076,-4.438],[-0.098,-0.84],[-0.22,-1.496],[-0.44,-0.833],[0.047,-0.031],[-0.09,-0.048],[-0.668,-1.024],[-0.843,-1.026],[-4.247,-4.074],[-1.282,-0.297],[-1.202,-0.131],[0,0],[0,0],[-0.518,0],[-1.329,0.06],[-1.354,0.223],[-5.447,1.605],[-0.958,0.964],[-0.805,1.036],[-3.033,5.026],[0,0],[0,6.606],[0.029,0.433],[0.071,0.076],[0.961,0.85],[1.653,0.983],[5.244,2.222],[2.57,0.222],[5.549,0],[14.814,-2.642],[-0.017,-0.789]],"v":[[48.547,4.158],[46.008,-12.431],[44.643,-14.011],[44.312,-16.519],[43.523,-20.921],[42.102,-23.353],[42.245,-23.44],[41.967,-23.563],[39.814,-26.519],[37.105,-29.434],[21.62,-37.858],[17.688,-38.504],[14.038,-38.725],[13.777,-38.725],[-12.543,-38.725],[-14.089,-38.686],[-18.009,-38.272],[-21.984,-37.362],[-36.198,-28.886],[-38.887,-25.82],[-41.124,-22.576],[-45.904,-5.364],[-45.904,6.533],[-40.661,24.473],[-40.15,25.672],[-39.208,26.566],[-33.99,30.291],[-29.448,34.327],[-11.623,40.751],[0.831,43.225],[23.816,44.851],[48.839,7.279]],"c":true},"ix":2},"nm":"Path 1","mn":"ADBE Vector Shape - Group","hd":false},{"ty":"fl","c":{"a":0,"k":[0.380000005984,0.352999997606,0.419999994016,1],"ix":4},"o":{"a":0,"k":100,"ix":5},"r":1,"bm":0,"nm":"Fill 1","mn":"ADBE Vector Graphic - Fill","hd":false},{"ty":"tr","p":{"a":0,"k":[67.531,59.254],"ix":2},"a":{"a":0,"k":[0,0],"ix":1},"s":{"a":0,"k":[100,100],"ix":3},"r":{"a":0,"k":0,"ix":6},"o":{"a":0,"k":100,"ix":7},"sk":{"a":0,"k":0,"ix":4},"sa":{"a":0,"k":0,"ix":5},"nm":"Transform"}],"nm":"Group 1","np":2,"cix":2,"bm":0,"ix":1,"mn":"ADBE Vector Group","hd":false},{"ty":"gr","it":[{"ind":0,"ty":"sh","ix":1,"ks":{"a":0,"k":{"i":[[0,0],[7.223,-35.597]],"o":[[9.391,50.473],[0,0]],"v":[[-4.129,-68.683],[-5.261,68.683]],"c":false},"ix":2},"nm":"Path 1","mn":"ADBE Vector Shape - Group","hd":false},{"ty":"st","c":{"a":0,"k":[0.250999989229,0.161000001197,0.263000009574,1],"ix":3},"o":{"a":0,"k":100,"ix":4},"w":{"a":0,"k":4,"ix":5},"lc":2,"lj":2,"bm":0,"nm":"Stroke 1","mn":"ADBE Vector Graphic - Stroke","hd":false},{"ty":"tr","p":{"a":0,"k":[180.684,110.06],"ix":2},"a":{"a":0,"k":[0,0],"ix":1},"s":{"a":0,"k":[100,100],"ix":3},"r":{"a":0,"k":0,"ix":6},"o":{"a":0,"k":100,"ix":7},"sk":{"a":0,"k":0,"ix":4},"sa":{"a":0,"k":0,"ix":5},"nm":"Transform"}],"nm":"Group 2","np":2,"cix":2,"bm":0,"ix":2,"mn":"ADBE Vector Group","hd":false},{"ty":"gr","it":[{"ind":0,"ty":"sh","ix":1,"ks":{"a":0,"k":{"i":[[0,0],[-16.478,32.162],[-8.811,-35.245]],"o":[[-17.623,-17.183],[23.087,-41.413],[0,0]],"v":[[-29.582,64.102],[-36.013,-22.689],[52.491,-12.303]],"c":false},"ix":2},"nm":"Path 1","mn":"ADBE Vector Shape - Group","hd":false},{"ty":"st","c":{"a":0,"k":[0.250999989229,0.161000001197,0.263000009574,1],"ix":3},"o":{"a":0,"k":100,"ix":4},"w":{"a":0,"k":4,"ix":5},"lc":2,"lj":2,"bm":0,"nm":"Stroke 1","mn":"ADBE Vector Graphic - Stroke","hd":false},{"ty":"tr","p":{"a":0,"k":[269.958,129.098],"ix":2},"a":{"a":0,"k":[0,0],"ix":1},"s":{"a":0,"k":[100,100],"ix":3},"r":{"a":0,"k":0,"ix":6},"o":{"a":0,"k":100,"ix":7},"sk":{"a":0,"k":0,"ix":4},"sa":{"a":0,"k":0,"ix":5},"nm":"Transform"}],"nm":"Group 3","np":2,"cix":2,"bm":0,"ix":3,"mn":"ADBE Vector Group","hd":false},{"ty":"gr","it":[{"ind":0,"ty":"sh","ix":1,"ks":{"a":0,"k":{"i":[[0,0],[-29.558,0],[-6.05,1.08],[0.301,14.363],[2.36,9.75]],"o":[[0,0],[6.302,0],[14.143,-2.522],[-0.136,-6.513],[0,0]],"v":[[-42.396,17.247],[-0.921,30.003],[18.075,28.112],[42.095,-1.24],[39.742,-30.003]],"c":false},"ix":2},"nm":"Path 1","mn":"ADBE Vector Shape - Group","hd":false},{"ty":"st","c":{"a":0,"k":[0.250999989229,0.161000001197,0.263000009574,1],"ix":3},"o":{"a":0,"k":100,"ix":4},"w":{"a":0,"k":4,"ix":5},"lc":2,"lj":2,"bm":0,"nm":"Stroke 1","mn":"ADBE Vector Graphic - Stroke","hd":false},{"ty":"tr","p":{"a":0,"k":[69.759,67.448],"ix":2},"a":{"a":0,"k":[0,0],"ix":1},"s":{"a":0,"k":[100,100],"ix":3},"r":{"a":0,"k":0,"ix":6},"o":{"a":0,"k":100,"ix":7},"sk":{"a":0,"k":0,"ix":4},"sa":{"a":0,"k":0,"ix":5},"nm":"Transform"}],"nm":"Group 4","np":2,"cix":2,"bm":0,"ix":4,"mn":"ADBE Vector Group","hd":false},{"ty":"gr","it":[{"ind":0,"ty":"sh","ix":1,"ks":{"a":0,"k":{"i":[[-18.9,0],[0,0],[-5.081,-12.533],[0,0],[0,-31.143],[0,0],[1.13,-9.339],[0,0],[0,0],[0,0],[-10.202,0.485],[0.417,7.307],[4.437,3.184],[0,0],[0,0],[0,0],[0,0],[-10.202,0.485],[0.43,18.564],[4.751,6.071],[10.228,11.733],[0,0],[0,10.085],[0,0]],"o":[[0,0],[14.356,0],[0,0],[31.144,0],[0,0],[0,9.406],[0,0],[0,0],[0,0],[0,-7.773],[0,-6.335],[-0.311,-5.451],[0,0],[0,0],[0,0],[0,0],[0,-7.773],[0,-6.86],[-0.183,-7.886],[-14.616,-4.899],[0,0],[-6.94,-6.263],[0,0],[0,-18.9]],"v":[[-118.302,-115.938],[-91.036,-115.938],[-59.316,-94.561],[96.135,-94.561],[152.524,-38.171],[152.524,-4.714],[150.829,23.429],[145.238,69.652],[135.52,115.938],[71.39,115.938],[89.365,97.963],[88.437,82.187],[80.934,68.534],[61.577,54.641],[4.31,44.365],[-4.064,115.938],[-68.195,115.938],[-50.219,97.963],[-51.249,53.521],[-58.934,32.059],[-96.917,6.726],[-141.22,-44.099],[-152.524,-69.511],[-152.524,-81.716]],"c":true},"ix":2},"nm":"Path 1","mn":"ADBE Vector Shape - Group","hd":false},{"ty":"st","c":{"a":0,"k":[0.250999989229,0.161000001197,0.263000009574,1],"ix":3},"o":{"a":0,"k":100,"ix":4},"w":{"a":0,"k":8,"ix":5},"lc":2,"lj":2,"bm":0,"nm":"Stroke 1","mn":"ADBE Vector Graphic - Stroke","hd":false},{"ty":"tr","p":{"a":0,"k":[172.524,135.938],"ix":2},"a":{"a":0,"k":[0,0],"ix":1},"s":{"a":0,"k":[100,100],"ix":3},"r":{"a":0,"k":0,"ix":6},"o":{"a":0,"k":100,"ix":7},"sk":{"a":0,"k":0,"ix":4},"sa":{"a":0,"k":0,"ix":5},"nm":"Transform"}],"nm":"Group 5","np":2,"cix":2,"bm":0,"ix":5,"mn":"ADBE Vector Group","hd":false},{"ty":"gr","it":[{"ind":0,"ty":"sh","ix":1,"ks":{"a":0,"k":{"i":[[-9.212,1.543],[0.283,-0.705],[-2.805,0],[0,0],[0,0],[0,0]],"o":[[-0.379,0.689],[-1.043,2.604],[0,0],[0,0],[0,0],[0,-7.263]],"v":[[-16.665,-8.88],[-17.66,-6.783],[-13.919,-1.352],[32.664,-1.352],[31.467,8.88],[-32.664,8.88]],"c":true},"ix":2},"nm":"Path 1","mn":"ADBE Vector Shape - Group","hd":false},{"ty":"fl","c":{"a":0,"k":[0.313999998803,0.289999988032,0.349000010771,1],"ix":4},"o":{"a":0,"k":100,"ix":5},"r":1,"bm":0,"nm":"Fill 1","mn":"ADBE Vector Graphic - Fill","hd":false},{"ty":"tr","p":{"a":0,"k":[136.993,242.997],"ix":2},"a":{"a":0,"k":[0,0],"ix":1},"s":{"a":0,"k":[100,100],"ix":3},"r":{"a":0,"k":0,"ix":6},"o":{"a":0,"k":100,"ix":7},"sk":{"a":0,"k":0,"ix":4},"sa":{"a":0,"k":0,"ix":5},"nm":"Transform"}],"nm":"Group 6","np":2,"cix":2,"bm":0,"ix":6,"mn":"ADBE Vector Group","hd":false},{"ty":"gr","it":[{"ind":0,"ty":"sh","ix":1,"ks":{"a":0,"k":{"i":[[-19.625,-2.831],[0,0],[-14.616,-4.899],[-0.183,-7.886],[-0.057,-10.05],[1.93,-0.358],[2.595,-3.265],[0.383,16.512],[4.751,6.071],[10.228,11.733],[0,0],[0,0]],"o":[[0,0],[10.228,11.735],[4.75,6.072],[0.375,16.176],[0.011,1.962],[-4.278,0.791],[-0.11,-8.355],[-0.183,-7.887],[-14.615,-4.899],[0,0],[0,0],[0,0]],"v":[[-25.092,-65.122],[6.186,-29.24],[44.169,-3.906],[51.854,17.556],[52.533,66.24],[49.193,70.201],[38.647,76.207],[37.977,27.788],[30.291,6.325],[-7.691,-19.008],[-50.239,-67.818],[-52.544,-76.207]],"c":true},"ix":2},"nm":"Path 1","mn":"ADBE Vector Shape - Group","hd":false},{"ty":"fl","c":{"a":0,"k":[0.313999998803,0.289999988032,0.349000010771,1],"ix":4},"o":{"a":0,"k":100,"ix":5},"r":1,"bm":0,"nm":"Fill 1","mn":"ADBE Vector Graphic - Fill","hd":false},{"ty":"tr","p":{"a":0,"k":[83.298,161.672],"ix":2},"a":{"a":0,"k":[0,0],"ix":1},"s":{"a":0,"k":[100,100],"ix":3},"r":{"a":0,"k":0,"ix":6},"o":{"a":0,"k":100,"ix":7},"sk":{"a":0,"k":0,"ix":4},"sa":{"a":0,"k":0,"ix":5},"nm":"Transform"}],"nm":"Group 7","np":2,"cix":2,"bm":0,"ix":7,"mn":"ADBE Vector Group","hd":false},{"ty":"gr","it":[{"ind":0,"ty":"sh","ix":1,"ks":{"a":0,"k":{"i":[[0,0],[1.166,6.712],[-22.185,0.62],[0,0],[-0.809,-6.514]],"o":[[-0.317,-5.33],[0,0],[0,0],[1.213,6.523],[0,0]],"v":[[-32.897,9.786],[-35.037,-8.283],[13.497,-9.786],[32.017,-9.786],[35.037,9.786]],"c":true},"ix":2},"nm":"Path 1","mn":"ADBE Vector Shape - Group","hd":false},{"ty":"fl","c":{"a":0,"k":[0.481999984442,0.451000019148,0.528999956916,1],"ix":4},"o":{"a":0,"k":100,"ix":5},"r":1,"bm":0,"nm":"Fill 1","mn":"ADBE Vector Graphic - Fill","hd":false},{"ty":"tr","p":{"a":0,"k":[144.537,51.164],"ix":2},"a":{"a":0,"k":[0,0],"ix":1},"s":{"a":0,"k":[100,100],"ix":3},"r":{"a":0,"k":0,"ix":6},"o":{"a":0,"k":100,"ix":7},"sk":{"a":0,"k":0,"ix":4},"sa":{"a":0,"k":0,"ix":5},"nm":"Transform"}],"nm":"Group 8","np":2,"cix":2,"bm":0,"ix":8,"mn":"ADBE Vector Group","hd":false},{"ty":"gr","it":[{"ind":0,"ty":"sh","ix":1,"ks":{"a":0,"k":{"i":[[-27.491,-0.79],[-6.049,1.08],[0.3,14.363],[1.566,9.022],[-22.184,0.62],[0,0],[7.224,-35.596],[-0.68,-12.883],[0,0],[0,0],[-10.203,0.485],[0.43,18.564],[4.751,6.072],[10.229,11.734],[0,0],[0,0]],"o":[[6.3,0.181],[14.144,-2.522],[-0.137,-6.512],[0,0],[0,0],[9.391,50.473],[-1.678,8.272],[0,0],[0,0],[0,-7.773],[0,-6.861],[-0.183,-7.886],[-14.615,-4.898],[0,0],[0,0],[0,0]],"v":[[-39.512,-49.176],[-20.517,-51.067],[3.505,-80.418],[1.151,-103.746],[49.684,-105.249],[68.204,-105.249],[67.072,32.116],[64.608,66.812],[60.109,105.249],[-4.021,105.249],[13.955,87.275],[12.924,42.833],[5.24,21.37],[-32.743,-3.963],[-75.29,-52.772],[-77.596,-61.162]],"c":true},"ix":2},"nm":"Path 1","mn":"ADBE Vector Shape - Group","hd":false},{"ty":"fl","c":{"a":0,"k":[0.380000005984,0.352999997606,0.419999994016,1],"ix":4},"o":{"a":0,"k":100,"ix":5},"r":1,"bm":0,"nm":"Fill 1","mn":"ADBE Vector Graphic - Fill","hd":false},{"ty":"tr","p":{"a":0,"k":[108.35,146.627],"ix":2},"a":{"a":0,"k":[0,0],"ix":1},"s":{"a":0,"k":[100,100],"ix":3},"r":{"a":0,"k":0,"ix":6},"o":{"a":0,"k":100,"ix":7},"sk":{"a":0,"k":0,"ix":4},"sa":{"a":0,"k":0,"ix":5},"nm":"Transform"}],"nm":"Group 9","np":2,"cix":2,"bm":0,"ix":9,"mn":"ADBE Vector Group","hd":false},{"ty":"gr","it":[{"ind":0,"ty":"sh","ix":1,"ks":{"a":0,"k":{"i":[[-1.557,21.273],[-9.124,-8.895],[0,0],[-0.312,-5.451],[0,-6.335],[0.242,-0.023],[0.066,1.162],[4.436,3.184],[0,0],[0,0.607]],"o":[[1.202,16.213],[1.329,1.254],[4.436,3.183],[0.417,7.308],[-0.246,0.011],[-0.069,-0.939],[-0.312,-5.451],[0,0],[0.022,-0.63],[-11.454,-11.167]],"v":[[-18.044,-40.109],[-2.571,-0.001],[11.17,10.605],[18.672,24.257],[19.601,40.033],[18.876,40.109],[18.672,36.988],[11.17,23.333],[-1.947,13.919],[-1.913,12.062]],"c":true},"ix":2},"nm":"Path 1","mn":"ADBE Vector Shape - Group","hd":false},{"ty":"fl","c":{"a":0,"k":[0.313999998803,0.289999988032,0.349000010771,1],"ix":4},"o":{"a":0,"k":100,"ix":5},"r":1,"bm":0,"nm":"Fill 1","mn":"ADBE Vector Graphic - Fill","hd":false},{"ty":"tr","p":{"a":0,"k":[242.289,181.138],"ix":2},"a":{"a":0,"k":[0,0],"ix":1},"s":{"a":0,"k":[100,100],"ix":3},"r":{"a":0,"k":0,"ix":6},"o":{"a":0,"k":100,"ix":7},"sk":{"a":0,"k":0,"ix":4},"sa":{"a":0,"k":0,"ix":5},"nm":"Transform"}],"nm":"Group 10","np":2,"cix":2,"bm":0,"ix":10,"mn":"ADBE Vector Group","hd":false},{"ty":"gr","it":[{"ind":0,"ty":"sh","ix":1,"ks":{"a":0,"k":{"i":[[-3.818,3.592],[0,0],[0,0],[0,0],[-0.043,9.036],[0,0],[0,0],[1.13,-9.339],[0,0],[0,0],[0,0]],"o":[[0,0],[0,0],[0,0],[1.086,-8.97],[0,0],[0,0],[0,9.407],[0,0],[0,0],[0,0],[0,-4.278]],"v":[[-34.385,53.407],[23.563,53.407],[33.28,7.12],[38.871,-39.104],[40.551,-66.136],[40.568,-66.118],[40.568,-54.517],[38.871,-26.373],[33.28,19.85],[23.563,66.136],[-40.568,66.136]],"c":true},"ix":2},"nm":"Path 1","mn":"ADBE Vector Shape - Group","hd":false},{"ty":"fl","c":{"a":0,"k":[0.313999998803,0.289999988032,0.349000010771,1],"ix":4},"o":{"a":0,"k":100,"ix":5},"r":1,"bm":0,"nm":"Fill 1","mn":"ADBE Vector Graphic - Fill","hd":false},{"ty":"tr","p":{"a":0,"k":[284.482,185.74],"ix":2},"a":{"a":0,"k":[0,0],"ix":1},"s":{"a":0,"k":[100,100],"ix":3},"r":{"a":0,"k":0,"ix":6},"o":{"a":0,"k":100,"ix":7},"sk":{"a":0,"k":0,"ix":4},"sa":{"a":0,"k":0,"ix":5},"nm":"Transform"}],"nm":"Group 11","np":2,"cix":2,"bm":0,"ix":11,"mn":"ADBE Vector Group","hd":false},{"ty":"gr","it":[{"ind":0,"ty":"sh","ix":1,"ks":{"a":0,"k":{"i":[[-8.812,-35.245],[0,0],[0,0],[1.129,-9.338],[0,0],[0,0],[0,0],[-10.203,0.485],[0.417,7.307],[4.437,3.184],[0,0],[0,0.608],[-16.478,32.163]],"o":[[0,0],[0,0],[0,9.407],[0,0],[0,0],[0,0],[0,-7.773],[0,-6.336],[-0.312,-5.451],[0,0],[0.022,-0.63],[-17.623,-17.182],[23.087,-41.413]],"v":[[49.742,-43.216],[53.791,-38.815],[53.791,-27.213],[52.095,0.93],[46.504,47.154],[36.787,93.44],[-27.344,93.44],[-9.368,75.465],[-10.297,59.689],[-17.799,46.036],[-30.916,36.622],[-30.882,34.764],[-37.313,-52.027]],"c":true},"ix":2},"nm":"Path 1","mn":"ADBE Vector Shape - Group","hd":false},{"ty":"fl","c":{"a":0,"k":[0.380000005984,0.352999997606,0.419999994016,1],"ix":4},"o":{"a":0,"k":100,"ix":5},"r":1,"bm":0,"nm":"Fill 1","mn":"ADBE Vector Graphic - Fill","hd":false},{"ty":"tr","p":{"a":0,"k":[271.258,158.436],"ix":2},"a":{"a":0,"k":[0,0],"ix":1},"s":{"a":0,"k":[100,100],"ix":3},"r":{"a":0,"k":0,"ix":6},"o":{"a":0,"k":100,"ix":7},"sk":{"a":0,"k":0,"ix":4},"sa":{"a":0,"k":0,"ix":5},"nm":"Transform"}],"nm":"Group 12","np":2,"cix":2,"bm":0,"ix":12,"mn":"ADBE Vector Group","hd":false},{"ty":"gr","it":[{"ind":0,"ty":"sh","ix":1,"ks":{"a":0,"k":{"i":[[-1.281,0.795],[0,0],[0,0],[0,0],[0,0],[0,0],[0,0],[0,0]],"o":[[0,0],[0,0],[0,0],[0,0],[0,0],[0,0],[0,0],[0,0]],"v":[[23.476,-8.711],[37.945,17.605],[35.309,19.277],[23.632,10.896],[-33.635,0.62],[-34.1,4.589],[-37.945,3.031],[-35.407,-19.277]],"c":true},"ix":2},"nm":"Path 1","mn":"ADBE Vector Shape - Group","hd":false},{"ty":"fl","c":{"a":0,"k":[0.847000002394,0.830999995213,0.773000021542,1],"ix":4},"o":{"a":0,"k":100,"ix":5},"r":1,"bm":0,"nm":"Fill 1","mn":"ADBE Vector Graphic - Fill","hd":false},{"ty":"tr","p":{"a":0,"k":[210.47,179.683],"ix":2},"a":{"a":0,"k":[0,0],"ix":1},"s":{"a":0,"k":[100,100],"ix":3},"r":{"a":0,"k":0,"ix":6},"o":{"a":0,"k":100,"ix":7},"sk":{"a":0,"k":0,"ix":4},"sa":{"a":0,"k":0,"ix":5},"nm":"Transform"}],"nm":"Group 13","np":2,"cix":2,"bm":0,"ix":13,"mn":"ADBE Vector Group","hd":false},{"ty":"gr","it":[{"ind":0,"ty":"sh","ix":1,"ks":{"a":0,"k":{"i":[[0,0],[0,0],[-10.34,-11.98],[0,0]],"o":[[0,0],[17.067,0],[0,0],[0,0]],"v":[[-68.742,-9.787],[26.05,-9.787],[68.742,9.787],[-68.742,9.787]],"c":true},"ix":2},"nm":"Path 1","mn":"ADBE Vector Shape - Group","hd":false},{"ty":"fl","c":{"a":0,"k":[1,1,1,1],"ix":4},"o":{"a":0,"k":100,"ix":5},"r":1,"bm":0,"nm":"Fill 1","mn":"ADBE Vector Graphic - Fill","hd":false},{"ty":"tr","p":{"a":0,"k":[242.61,51.163],"ix":2},"a":{"a":0,"k":[0,0],"ix":1},"s":{"a":0,"k":[100,100],"ix":3},"r":{"a":0,"k":0,"ix":6},"o":{"a":0,"k":100,"ix":7},"sk":{"a":0,"k":0,"ix":4},"sa":{"a":0,"k":0,"ix":5},"nm":"Transform"}],"nm":"Group 14","np":2,"cix":2,"bm":0,"ix":14,"mn":"ADBE Vector Group","hd":false},{"ty":"gr","it":[{"ind":0,"ty":"sh","ix":1,"ks":{"a":0,"k":{"i":[[-18.9,0],[0,0],[-5.081,-12.533],[0,0],[0,-31.143],[0,0],[1.13,-9.339],[0,0],[0,0],[0,0],[-10.202,0.485],[0.417,7.307],[4.437,3.184],[0,0],[0,0],[0,0],[0,0],[-10.202,0.485],[0.43,18.564],[4.751,6.071],[10.228,11.733],[0,0],[0,10.085],[0,0]],"o":[[0,0],[14.356,0],[0,0],[31.144,0],[0,0],[0,9.406],[0,0],[0,0],[0,0],[0,-7.773],[0,-6.335],[-0.311,-5.451],[0,0],[0,0],[0,0],[0,0],[0,-7.773],[0,-6.86],[-0.183,-7.886],[-14.616,-4.899],[0,0],[-6.94,-6.263],[0,0],[0,-18.9]],"v":[[-118.302,-115.938],[-91.036,-115.938],[-59.316,-94.561],[96.135,-94.561],[152.524,-38.171],[152.524,-4.714],[150.829,23.429],[145.238,69.652],[135.52,115.938],[71.39,115.938],[89.365,97.963],[88.437,82.187],[80.934,68.534],[61.577,54.641],[4.31,44.365],[-4.064,115.938],[-68.195,115.938],[-50.219,97.963],[-51.249,53.521],[-58.934,32.059],[-96.917,6.726],[-141.22,-44.099],[-152.524,-69.511],[-152.524,-81.716]],"c":true},"ix":2},"nm":"Path 1","mn":"ADBE Vector Shape - Group","hd":false},{"ty":"fl","c":{"a":0,"k":[0.976000019148,0.969000004787,0.929000016755,1],"ix":4},"o":{"a":0,"k":100,"ix":5},"r":1,"bm":0,"nm":"Fill 1","mn":"ADBE Vector Graphic - Fill","hd":false},{"ty":"tr","p":{"a":0,"k":[172.524,135.938],"ix":2},"a":{"a":0,"k":[0,0],"ix":1},"s":{"a":0,"k":[100,100],"ix":3},"r":{"a":0,"k":0,"ix":6},"o":{"a":0,"k":100,"ix":7},"sk":{"a":0,"k":0,"ix":4},"sa":{"a":0,"k":0,"ix":5},"nm":"Transform"}],"nm":"Group 15","np":2,"cix":2,"bm":0,"ix":15,"mn":"ADBE Vector Group","hd":false}],"ip":0,"op":120.0000048877,"st":0,"bm":0},{"ddd":0,"ind":10,"ty":4,"nm":"TAIL ","parent":7,"sr":1,"ks":{"o":{"a":0,"k":100,"ix":11},"r":{"a":0,"k":0,"ix":10},"p":{"a":0,"k":[117.444,-48.243,0],"ix":2,"l":2},"a":{"a":0,"k":[39.002,39.002,0],"ix":1,"l":2},"s":{"a":1,"k":[{"i":{"x":[0.667,0.667,0.667],"y":[1,1,1]},"o":{"x":[0.333,0.333,0.333],"y":[0,0,0]},"t":0,"s":[100,100,100]},{"i":{"x":[0.667,0.667,0.667],"y":[1,1,1]},"o":{"x":[0.333,0.333,0.333],"y":[0,0,0]},"t":10,"s":[116,100,100]},{"i":{"x":[0.667,0.667,0.667],"y":[1,1,1]},"o":{"x":[0.333,0.333,0.333],"y":[0,0,0]},"t":20,"s":[100,100,100]},{"i":{"x":[0.667,0.667,0.667],"y":[1,1,1]},"o":{"x":[0.333,0.333,0.333],"y":[0,0,0]},"t":30,"s":[116,100,100]},{"t":40.0000016292334,"s":[100,100,100]}],"ix":6,"l":2,"x":"var $bm_rt;\n$bm_rt = loopOut('cycle', 0);"}},"ao":0,"shapes":[{"ty":"gr","it":[{"ind":0,"ty":"sh","ix":1,"ks":{"a":0,"k":{"i":[[0,-10.495],[-10.494,0],[0,10.495],[10.495,0]],"o":[[0,10.495],[10.495,0],[0,-10.495],[-10.494,0]],"v":[[-19.002,0],[0,19.002],[19.002,0],[0,-19.002]],"c":true},"ix":2},"nm":"Path 1","mn":"ADBE Vector Shape - Group","hd":false},{"ty":"st","c":{"a":0,"k":[0.250999989229,0.161000001197,0.263000009574,1],"ix":3},"o":{"a":0,"k":100,"ix":4},"w":{"a":0,"k":8,"ix":5},"lc":2,"lj":2,"bm":0,"nm":"Stroke 1","mn":"ADBE Vector Graphic - Stroke","hd":false},{"ty":"fl","c":{"a":0,"k":[0.380000005984,0.352999997606,0.419999994016,1],"ix":4},"o":{"a":0,"k":100,"ix":5},"r":1,"bm":0,"nm":"Fill 1","mn":"ADBE Vector Graphic - Fill","hd":false},{"ty":"tr","p":{"a":0,"k":[39.002,39.002],"ix":2},"a":{"a":0,"k":[0,0],"ix":1},"s":{"a":0,"k":[100,100],"ix":3},"r":{"a":0,"k":0,"ix":6},"o":{"a":0,"k":100,"ix":7},"sk":{"a":0,"k":0,"ix":4},"sa":{"a":0,"k":0,"ix":5},"nm":"Transform"}],"nm":"Group 1","np":3,"cix":2,"bm":0,"ix":1,"mn":"ADBE Vector Group","hd":false}],"ip":0,"op":120.0000048877,"st":0,"bm":0},{"ddd":0,"ind":11,"ty":4,"nm":"EAR 2","parent":6,"sr":1,"ks":{"o":{"a":0,"k":100,"ix":11},"r":{"a":0,"k":0,"ix":10},"p":{"a":1,"k":[{"i":{"x":0.667,"y":1},"o":{"x":0.333,"y":0},"t":0,"s":[80.29,0.25,0],"to":[0,1.5,0],"ti":[0,0,0]},{"i":{"x":0.667,"y":1},"o":{"x":0.333,"y":0},"t":10,"s":[80.29,9.25,0],"to":[0,0,0],"ti":[0,-1.5,0]},{"i":{"x":0.667,"y":1},"o":{"x":0.333,"y":0},"t":20,"s":[80.29,0.25,0],"to":[0,1.5,0],"ti":[0,0,0]},{"i":{"x":0.667,"y":1},"o":{"x":0.333,"y":0},"t":30,"s":[80.29,9.25,0],"to":[0,0,0],"ti":[0,-1.5,0]},{"t":40.0000016292334,"s":[80.29,0.25,0]}],"ix":2,"l":2,"x":"var $bm_rt;\n$bm_rt = loopOut('cycle', 0);"},"a":{"a":0,"k":[34.819,34.819,0],"ix":1,"l":2},"s":{"a":1,"k":[{"i":{"x":[0.667,0.667,0.667],"y":[1,1,1]},"o":{"x":[0.333,0.333,0.333],"y":[0,0,0]},"t":0,"s":[100,100,100]},{"i":{"x":[0.667,0.667,0.667],"y":[1,1,1]},"o":{"x":[0.333,0.333,0.333],"y":[0,0,0]},"t":10,"s":[116,100,100]},{"i":{"x":[0.667,0.667,0.667],"y":[1,1,1]},"o":{"x":[0.333,0.333,0.333],"y":[0,0,0]},"t":20,"s":[100,100,100]},{"i":{"x":[0.667,0.667,0.667],"y":[1,1,1]},"o":{"x":[0.333,0.333,0.333],"y":[0,0,0]},"t":30,"s":[116,100,100]},{"t":40.0000016292334,"s":[100,100,100]}],"ix":6,"l":2}},"ao":0,"shapes":[{"ty":"gr","it":[{"ind":0,"ty":"sh","ix":1,"ks":{"a":0,"k":{"i":[[-8.172,0],[0,8.171],[8.171,0],[0,-8.172]],"o":[[8.171,0],[0,-8.172],[-8.172,0],[0,8.171]],"v":[[0.001,14.819],[14.818,0.001],[0.001,-14.819],[-14.818,0.001]],"c":true},"ix":2},"nm":"Path 1","mn":"ADBE Vector Shape - Group","hd":false},{"ty":"st","c":{"a":0,"k":[0.250999989229,0.161000001197,0.263000009574,1],"ix":3},"o":{"a":0,"k":100,"ix":4},"w":{"a":0,"k":8,"ix":5},"lc":2,"lj":2,"bm":0,"nm":"Stroke 1","mn":"ADBE Vector Graphic - Stroke","hd":false},{"ty":"fl","c":{"a":0,"k":[0.380000005984,0.352999997606,0.419999994016,1],"ix":4},"o":{"a":0,"k":100,"ix":5},"r":1,"bm":0,"nm":"Fill 1","mn":"ADBE Vector Graphic - Fill","hd":false},{"ty":"tr","p":{"a":0,"k":[34.818,34.819],"ix":2},"a":{"a":0,"k":[0,0],"ix":1},"s":{"a":0,"k":[100,100],"ix":3},"r":{"a":0,"k":0,"ix":6},"o":{"a":0,"k":100,"ix":7},"sk":{"a":0,"k":0,"ix":4},"sa":{"a":0,"k":0,"ix":5},"nm":"Transform"}],"nm":"Group 1","np":3,"cix":2,"bm":0,"ix":1,"mn":"ADBE Vector Group","hd":false}],"ip":0,"op":120.0000048877,"st":0,"bm":0},{"ddd":0,"ind":12,"ty":4,"nm":"EAR","parent":6,"sr":1,"ks":{"o":{"a":0,"k":100,"ix":11},"r":{"a":0,"k":0,"ix":10},"p":{"a":1,"k":[{"i":{"x":0.667,"y":1},"o":{"x":0.333,"y":0},"t":0,"s":[14.069,0.25,0],"to":[0,1.5,0],"ti":[0,0,0]},{"i":{"x":0.667,"y":1},"o":{"x":0.333,"y":0},"t":10,"s":[14.069,9.25,0],"to":[0,0,0],"ti":[0,-1.5,0]},{"i":{"x":0.667,"y":1},"o":{"x":0.333,"y":0},"t":20,"s":[14.069,0.25,0],"to":[0,1.5,0],"ti":[0,0,0]},{"i":{"x":0.667,"y":1},"o":{"x":0.333,"y":0},"t":30,"s":[14.069,9.25,0],"to":[0,0,0],"ti":[0,-1.5,0]},{"t":40.0000016292334,"s":[14.069,0.25,0]}],"ix":2,"l":2,"x":"var $bm_rt;\n$bm_rt = loopOut('cycle', 0);"},"a":{"a":0,"k":[34.818,34.819,0],"ix":1,"l":2},"s":{"a":1,"k":[{"i":{"x":[0.667,0.667,0.667],"y":[1,1,1]},"o":{"x":[0.333,0.333,0.333],"y":[0,0,0]},"t":0,"s":[100,100,100]},{"i":{"x":[0.667,0.667,0.667],"y":[1,1,1]},"o":{"x":[0.333,0.333,0.333],"y":[0,0,0]},"t":10,"s":[116,100,100]},{"i":{"x":[0.667,0.667,0.667],"y":[1,1,1]},"o":{"x":[0.333,0.333,0.333],"y":[0,0,0]},"t":20,"s":[100,100,100]},{"i":{"x":[0.667,0.667,0.667],"y":[1,1,1]},"o":{"x":[0.333,0.333,0.333],"y":[0,0,0]},"t":30,"s":[116,100,100]},{"t":40.0000016292334,"s":[100,100,100]}],"ix":6,"l":2}},"ao":0,"shapes":[{"ty":"gr","it":[{"ind":0,"ty":"sh","ix":1,"ks":{"a":0,"k":{"i":[[-8.172,0],[0,8.171],[8.171,0],[0,-8.172]],"o":[[8.171,0],[0,-8.172],[-8.172,0],[0,8.171]],"v":[[0.001,14.819],[14.818,0.001],[0.001,-14.819],[-14.818,0.001]],"c":true},"ix":2},"nm":"Path 1","mn":"ADBE Vector Shape - Group","hd":false},{"ty":"st","c":{"a":0,"k":[0.250999989229,0.161000001197,0.263000009574,1],"ix":3},"o":{"a":0,"k":100,"ix":4},"w":{"a":0,"k":8,"ix":5},"lc":2,"lj":2,"bm":0,"nm":"Stroke 1","mn":"ADBE Vector Graphic - Stroke","hd":false},{"ty":"fl","c":{"a":0,"k":[0.380000005984,0.352999997606,0.419999994016,1],"ix":4},"o":{"a":0,"k":100,"ix":5},"r":1,"bm":0,"nm":"Fill 1","mn":"ADBE Vector Graphic - Fill","hd":false},{"ty":"tr","p":{"a":0,"k":[34.818,34.819],"ix":2},"a":{"a":0,"k":[0,0],"ix":1},"s":{"a":0,"k":[100,100],"ix":3},"r":{"a":0,"k":0,"ix":6},"o":{"a":0,"k":100,"ix":7},"sk":{"a":0,"k":0,"ix":4},"sa":{"a":0,"k":0,"ix":5},"nm":"Transform"}],"nm":"Group 1","np":3,"cix":2,"bm":0,"ix":1,"mn":"ADBE Vector Group","hd":false}],"ip":0,"op":120.0000048877,"st":0,"bm":0},{"ddd":0,"ind":13,"ty":4,"nm":"R HAND A","sr":1,"ks":{"o":{"a":0,"k":100,"ix":11},"r":{"a":0,"k":0,"ix":10},"p":{"a":0,"k":[186,309.674,0],"ix":2,"l":2},"a":{"a":0,"k":[64,89.674,0],"ix":1,"l":2},"s":{"a":0,"k":[100,100,100],"ix":6,"l":2}},"ao":0,"ef":[{"ty":34,"nm":"Puppet","np":6,"mn":"ADBE FreePin3","ix":1,"en":1,"ef":[{"ty":7,"nm":"Puppet Engine","mn":"ADBE FreePin3 Puppet Engine","ix":1,"v":{"a":0,"k":2,"ix":1}},{"ty":0,"nm":"Mesh Rotation Refinement","mn":"ADBE FreePin3 Auto Rotate Pins","ix":2,"v":{"a":0,"k":20,"ix":2}},{"ty":7,"nm":"On Transparent","mn":"ADBE FreePin3 On Transparent","ix":3,"v":{"a":0,"k":0,"ix":3}},{"ty":29.9700012207031,"nm":"arap","np":3,"mn":"ADBE FreePin3 ARAP Group","ix":4,"en":1,"ef":[{"ty":6,"nm":"Auto-traced Shapes","mn":"ADBE FreePin3 Outlines","ix":1,"v":0},{"ty":1,"nm":"Mesh","np":2,"mn":"ADBE FreePin3 Mesh Group","ix":2,"en":1,"ef":[{"nm":"Mesh 1","np":8,"mn":"ADBE FreePin3 Mesh Atom","ix":1,"en":1,"ef":[{"ty":6,"nm":"Mesh","mn":"ADBE FreePin3 Mesh","ix":1,"v":0},{"ty":0,"nm":"Triangles","mn":"ADBE FreePin3 Mesh Tri Count","ix":2,"v":{"a":0,"k":50,"ix":2}},{"ty":0,"nm":"Density","mn":"ADBE FreePin3 Mesh Tri Density","ix":3,"v":{"a":0,"k":12,"ix":3}},{"ty":0,"nm":"Expansion","mn":"ADBE FreePin3 Mesh Expansion","ix":4,"v":{"a":0,"k":30,"ix":4}},{"nm":"Deform","np":5,"mn":"ADBE FreePin3 PosPins","ix":5,"en":1,"ef":[{"nm":"4","np":7,"mn":"ADBE FreePin3 PosPin Atom","ix":1,"en":1,"ef":[{"ty":3,"nm":"Vertex Offset","mn":"ADBE FreePin3 PosPin Vtx Offset","ix":1,"v":{"a":0,"k":[0,0],"ix":1}},{"ty":0,"nm":"Vertex Index","mn":"ADBE FreePin3 PosPin Vtx Index","ix":2,"v":{"a":0,"k":9,"ix":2}},{"ty":7,"nm":"Pin Type","mn":"ADBE FreePin3 PosPin Type","ix":3,"v":{"a":0,"k":1,"ix":3}},{"ty":3,"nm":"Position","mn":"ADBE FreePin3 PosPin Position","ix":4,"v":{"a":0,"k":[198,372.5],"ix":4,"x":"var $bm_rt;\nvar l = null;\ntry {\n    l = effect('B | 4 - 4')(1);\n} catch (e) {\n}\n;\nvar result = value;\nif (l != null) {\n    result = l.toWorld(l.anchorPoint);\n}\n$bm_rt = result;"}},{"ty":0,"nm":"Scale","mn":"ADBE FreePin3 PosPin Scale","ix":5,"v":{"a":0,"k":100,"ix":5}},{"ty":0,"nm":"Rotation","mn":"ADBE FreePin3 PosPin Rotation","ix":6,"v":{"a":0,"k":0,"ix":6}}]},{"nm":"3","np":7,"mn":"ADBE FreePin3 PosPin Atom","ix":2,"en":1,"ef":[{"ty":3,"nm":"Vertex Offset","mn":"ADBE FreePin3 PosPin Vtx Offset","ix":1,"v":{"a":0,"k":[0,0],"ix":1}},{"ty":0,"nm":"Vertex Index","mn":"ADBE FreePin3 PosPin Vtx Index","ix":2,"v":{"a":0,"k":10,"ix":2}},{"ty":7,"nm":"Pin Type","mn":"ADBE FreePin3 PosPin Type","ix":3,"v":{"a":0,"k":1,"ix":3}},{"ty":3,"nm":"Position","mn":"ADBE FreePin3 PosPin Position","ix":4,"v":{"a":0,"k":[199.5,321.5],"ix":4,"x":"var $bm_rt;\nvar l = null;\ntry {\n    l = effect('B | 3 - 4')(1);\n} catch (e) {\n}\n;\nvar result = value;\nif (l != null) {\n    result = l.toWorld(l.anchorPoint);\n}\n$bm_rt = result;"}},{"ty":0,"nm":"Scale","mn":"ADBE FreePin3 PosPin Scale","ix":5,"v":{"a":0,"k":100,"ix":5}},{"ty":0,"nm":"Rotation","mn":"ADBE FreePin3 PosPin Rotation","ix":6,"v":{"a":0,"k":0,"ix":6}}]},{"nm":"2","np":7,"mn":"ADBE FreePin3 PosPin Atom","ix":3,"en":1,"ef":[{"ty":3,"nm":"Vertex Offset","mn":"ADBE FreePin3 PosPin Vtx Offset","ix":1,"v":{"a":0,"k":[0,0],"ix":1}},{"ty":0,"nm":"Vertex Index","mn":"ADBE FreePin3 PosPin Vtx Index","ix":2,"v":{"a":0,"k":11,"ix":2}},{"ty":7,"nm":"Pin Type","mn":"ADBE FreePin3 PosPin Type","ix":3,"v":{"a":0,"k":1,"ix":3}},{"ty":3,"nm":"Position","mn":"ADBE FreePin3 PosPin Position","ix":4,"v":{"a":0,"k":[197,273.5],"ix":4,"x":"var $bm_rt;\nvar l = null;\ntry {\n    l = effect('B | 2 - 4')(1);\n} catch (e) {\n}\n;\nvar result = value;\nif (l != null) {\n    result = l.toWorld(l.anchorPoint);\n}\n$bm_rt = result;"}},{"ty":0,"nm":"Scale","mn":"ADBE FreePin3 PosPin Scale","ix":5,"v":{"a":0,"k":100,"ix":5}},{"ty":0,"nm":"Rotation","mn":"ADBE FreePin3 PosPin Rotation","ix":6,"v":{"a":0,"k":0,"ix":6}}]},{"nm":"1","np":7,"mn":"ADBE FreePin3 PosPin Atom","ix":4,"en":1,"ef":[{"ty":3,"nm":"Vertex Offset","mn":"ADBE FreePin3 PosPin Vtx Offset","ix":1,"v":{"a":0,"k":[0,0],"ix":1}},{"ty":0,"nm":"Vertex Index","mn":"ADBE FreePin3 PosPin Vtx Index","ix":2,"v":{"a":0,"k":12,"ix":2}},{"ty":7,"nm":"Pin Type","mn":"ADBE FreePin3 PosPin Type","ix":3,"v":{"a":0,"k":1,"ix":3}},{"ty":3,"nm":"Position","mn":"ADBE FreePin3 PosPin Position","ix":4,"v":{"a":0,"k":[194.5,244],"ix":4,"x":"var $bm_rt;\nvar l = null;\ntry {\n    l = effect('B | 1 - 4')(1);\n} catch (e) {\n}\n;\nvar result = value;\nif (l != null) {\n    result = l.toWorld(l.anchorPoint);\n}\n$bm_rt = result;"}},{"ty":0,"nm":"Scale","mn":"ADBE FreePin3 PosPin Scale","ix":5,"v":{"a":0,"k":100,"ix":5}},{"ty":0,"nm":"Rotation","mn":"ADBE FreePin3 PosPin Rotation","ix":6,"v":{"a":0,"k":0,"ix":6}}]}]},{"nm":"Overlap","np":1,"mn":"ADBE FreePin3 HghtPins","ix":6,"en":1,"ef":[]},{"nm":"Stiffness","np":1,"mn":"ADBE FreePin3 StarchPins","ix":7,"en":1,"ef":[]}]}]}]}]},{"ty":5,"nm":"B | 4 - 4","np":4,"mn":"Pseudo/DUIK bone linker","ix":2,"en":1,"ef":[{"ty":10,"nm":"Layer","mn":"Pseudo/DUIK bone linker-0001","ix":1,"v":{"a":0,"k":24,"ix":1}},{"ty":2,"nm":"Bone color","mn":"Pseudo/DUIK bone linker-0002","ix":2,"v":{"a":0,"k":[0.925490196078,0.094117647059,0.094117647059,1],"ix":2}}]},{"ty":5,"nm":"B | 3 - 4","np":4,"mn":"Pseudo/DUIK bone linker","ix":3,"en":1,"ef":[{"ty":10,"nm":"Layer","mn":"Pseudo/DUIK bone linker-0001","ix":1,"v":{"a":0,"k":25,"ix":1}},{"ty":2,"nm":"Bone color","mn":"Pseudo/DUIK bone linker-0002","ix":2,"v":{"a":0,"k":[0.925490196078,0.094117647059,0.094117647059,1],"ix":2}}]},{"ty":5,"nm":"B | 2 - 4","np":4,"mn":"Pseudo/DUIK bone linker","ix":4,"en":1,"ef":[{"ty":10,"nm":"Layer","mn":"Pseudo/DUIK bone linker-0001","ix":1,"v":{"a":0,"k":26,"ix":1}},{"ty":2,"nm":"Bone color","mn":"Pseudo/DUIK bone linker-0002","ix":2,"v":{"a":0,"k":[0.925490196078,0.094117647059,0.094117647059,1],"ix":2}}]},{"ty":5,"nm":"B | 1 - 4","np":4,"mn":"Pseudo/DUIK bone linker","ix":5,"en":1,"ef":[{"ty":10,"nm":"Layer","mn":"Pseudo/DUIK bone linker-0001","ix":1,"v":{"a":0,"k":27,"ix":1}},{"ty":2,"nm":"Bone color","mn":"Pseudo/DUIK bone linker-0002","ix":2,"v":{"a":0,"k":[0.925490196078,0.094117647059,0.094117647059,1],"ix":2}}]}],"shapes":[{"ty":"gr","it":[{"ind":0,"ty":"sh","ix":1,"ks":{"a":0,"k":{"i":[[0,0],[0,0],[0,0],[-10.203,0.485],[0.429,18.544],[5.882,10.742],[0,0],[0,0]],"o":[[0,0],[0,0],[0,-7.774],[0,-6.787],[-0.283,-12.244],[0,0],[0,0],[0,0]],"v":[[43.975,-14.678],[34.258,69.674],[-29.872,69.674],[-11.896,51.698],[-12.913,7.857],[-22.295,-27.122],[-44,-69.674],[44,-69.674]],"c":true},"ix":2},"nm":"Path 1","mn":"ADBE Vector Shape - Group","hd":false},{"ty":"st","c":{"a":0,"k":[0.250999989229,0.161000001197,0.263000009574,1],"ix":3},"o":{"a":0,"k":100,"ix":4},"w":{"a":0,"k":8,"ix":5},"lc":2,"lj":2,"bm":0,"nm":"Stroke 1","mn":"ADBE Vector Graphic - Stroke","hd":false},{"ty":"fl","c":{"a":0,"k":[0.258999992819,0.231000010173,0.298000021542,1],"ix":4},"o":{"a":0,"k":100,"ix":5},"r":1,"bm":0,"nm":"Fill 1","mn":"ADBE Vector Graphic - Fill","hd":false},{"ty":"tr","p":{"a":0,"k":[64,89.674],"ix":2},"a":{"a":0,"k":[0,0],"ix":1},"s":{"a":0,"k":[100,100],"ix":3},"r":{"a":0,"k":0,"ix":6},"o":{"a":0,"k":100,"ix":7},"sk":{"a":0,"k":0,"ix":4},"sa":{"a":0,"k":0,"ix":5},"nm":"Transform"}],"nm":"Group 1","np":3,"cix":2,"bm":0,"ix":1,"mn":"ADBE Vector Group","hd":false}],"ip":0,"op":120.0000048877,"st":0,"bm":0},{"ddd":0,"ind":14,"ty":4,"nm":"R HAND B","sr":1,"ks":{"o":{"a":0,"k":100,"ix":11},"r":{"a":0,"k":0,"ix":10},"p":{"a":0,"k":[317,322.174,0],"ix":2,"l":2},"a":{"a":0,"k":[69,77.174,0],"ix":1,"l":2},"s":{"a":0,"k":[100,100,100],"ix":6,"l":2}},"ao":0,"ef":[{"ty":34,"nm":"Puppet","np":6,"mn":"ADBE FreePin3","ix":1,"en":1,"ef":[{"ty":7,"nm":"Puppet Engine","mn":"ADBE FreePin3 Puppet Engine","ix":1,"v":{"a":0,"k":2,"ix":1}},{"ty":0,"nm":"Mesh Rotation Refinement","mn":"ADBE FreePin3 Auto Rotate Pins","ix":2,"v":{"a":0,"k":20,"ix":2}},{"ty":7,"nm":"On Transparent","mn":"ADBE FreePin3 On Transparent","ix":3,"v":{"a":0,"k":0,"ix":3}},{"ty":29.9700012207031,"nm":"arap","np":3,"mn":"ADBE FreePin3 ARAP Group","ix":4,"en":1,"ef":[{"ty":6,"nm":"Auto-traced Shapes","mn":"ADBE FreePin3 Outlines","ix":1,"v":0},{"ty":1,"nm":"Mesh","np":2,"mn":"ADBE FreePin3 Mesh Group","ix":2,"en":1,"ef":[{"nm":"Mesh 1","np":8,"mn":"ADBE FreePin3 Mesh Atom","ix":1,"en":1,"ef":[{"ty":6,"nm":"Mesh","mn":"ADBE FreePin3 Mesh","ix":1,"v":0},{"ty":0,"nm":"Triangles","mn":"ADBE FreePin3 Mesh Tri Count","ix":2,"v":{"a":0,"k":50,"ix":2}},{"ty":0,"nm":"Density","mn":"ADBE FreePin3 Mesh Tri Density","ix":3,"v":{"a":0,"k":12,"ix":3}},{"ty":0,"nm":"Expansion","mn":"ADBE FreePin3 Mesh Expansion","ix":4,"v":{"a":0,"k":30,"ix":4}},{"nm":"Deform","np":5,"mn":"ADBE FreePin3 PosPins","ix":5,"en":1,"ef":[{"nm":"4","np":7,"mn":"ADBE FreePin3 PosPin Atom","ix":1,"en":1,"ef":[{"ty":3,"nm":"Vertex Offset","mn":"ADBE FreePin3 PosPin Vtx Offset","ix":1,"v":{"a":0,"k":[0,0],"ix":1}},{"ty":0,"nm":"Vertex Index","mn":"ADBE FreePin3 PosPin Vtx Index","ix":2,"v":{"a":0,"k":8,"ix":2}},{"ty":7,"nm":"Pin Type","mn":"ADBE FreePin3 PosPin Type","ix":3,"v":{"a":0,"k":1,"ix":3}},{"ty":3,"nm":"Position","mn":"ADBE FreePin3 PosPin Position","ix":4,"v":{"a":0,"k":[336.5,372.5],"ix":4,"x":"var $bm_rt;\nvar l = null;\ntry {\n    l = effect('B | 4 - 4')(1);\n} catch (e) {\n}\n;\nvar result = value;\nif (l != null) {\n    result = l.toWorld(l.anchorPoint);\n}\n$bm_rt = result;"}},{"ty":0,"nm":"Scale","mn":"ADBE FreePin3 PosPin Scale","ix":5,"v":{"a":0,"k":100,"ix":5}},{"ty":0,"nm":"Rotation","mn":"ADBE FreePin3 PosPin Rotation","ix":6,"v":{"a":0,"k":0,"ix":6}}]},{"nm":"3","np":7,"mn":"ADBE FreePin3 PosPin Atom","ix":2,"en":1,"ef":[{"ty":3,"nm":"Vertex Offset","mn":"ADBE FreePin3 PosPin Vtx Offset","ix":1,"v":{"a":0,"k":[0,0],"ix":1}},{"ty":0,"nm":"Vertex Index","mn":"ADBE FreePin3 PosPin Vtx Index","ix":2,"v":{"a":0,"k":9,"ix":2}},{"ty":7,"nm":"Pin Type","mn":"ADBE FreePin3 PosPin Type","ix":3,"v":{"a":0,"k":1,"ix":3}},{"ty":3,"nm":"Position","mn":"ADBE FreePin3 PosPin Position","ix":4,"v":{"a":0,"k":[333,340.5],"ix":4,"x":"var $bm_rt;\nvar l = null;\ntry {\n    l = effect('B | 3 - 4')(1);\n} catch (e) {\n}\n;\nvar result = value;\nif (l != null) {\n    result = l.toWorld(l.anchorPoint);\n}\n$bm_rt = result;"}},{"ty":0,"nm":"Scale","mn":"ADBE FreePin3 PosPin Scale","ix":5,"v":{"a":0,"k":100,"ix":5}},{"ty":0,"nm":"Rotation","mn":"ADBE FreePin3 PosPin Rotation","ix":6,"v":{"a":0,"k":0,"ix":6}}]},{"nm":"2","np":7,"mn":"ADBE FreePin3 PosPin Atom","ix":3,"en":1,"ef":[{"ty":3,"nm":"Vertex Offset","mn":"ADBE FreePin3 PosPin Vtx Offset","ix":1,"v":{"a":0,"k":[0,0],"ix":1}},{"ty":0,"nm":"Vertex Index","mn":"ADBE FreePin3 PosPin Vtx Index","ix":2,"v":{"a":0,"k":10,"ix":2}},{"ty":7,"nm":"Pin Type","mn":"ADBE FreePin3 PosPin Type","ix":3,"v":{"a":0,"k":1,"ix":3}},{"ty":3,"nm":"Position","mn":"ADBE FreePin3 PosPin Position","ix":4,"v":{"a":0,"k":[327.5,306.5],"ix":4,"x":"var $bm_rt;\nvar l = null;\ntry {\n    l = effect('B | 2 - 4')(1);\n} catch (e) {\n}\n;\nvar result = value;\nif (l != null) {\n    result = l.toWorld(l.anchorPoint);\n}\n$bm_rt = result;"}},{"ty":0,"nm":"Scale","mn":"ADBE FreePin3 PosPin Scale","ix":5,"v":{"a":0,"k":100,"ix":5}},{"ty":0,"nm":"Rotation","mn":"ADBE FreePin3 PosPin Rotation","ix":6,"v":{"a":0,"k":0,"ix":6}}]},{"nm":"1","np":7,"mn":"ADBE FreePin3 PosPin Atom","ix":4,"en":1,"ef":[{"ty":3,"nm":"Vertex Offset","mn":"ADBE FreePin3 PosPin Vtx Offset","ix":1,"v":{"a":0,"k":[0,0],"ix":1}},{"ty":0,"nm":"Vertex Index","mn":"ADBE FreePin3 PosPin Vtx Index","ix":2,"v":{"a":0,"k":11,"ix":2}},{"ty":7,"nm":"Pin Type","mn":"ADBE FreePin3 PosPin Type","ix":3,"v":{"a":0,"k":1,"ix":3}},{"ty":3,"nm":"Position","mn":"ADBE FreePin3 PosPin Position","ix":4,"v":{"a":0,"k":[322.5,266],"ix":4,"x":"var $bm_rt;\nvar l = null;\ntry {\n    l = effect('B | 1 - 4')(1);\n} catch (e) {\n}\n;\nvar result = value;\nif (l != null) {\n    result = l.toWorld(l.anchorPoint);\n}\n$bm_rt = result;"}},{"ty":0,"nm":"Scale","mn":"ADBE FreePin3 PosPin Scale","ix":5,"v":{"a":0,"k":100,"ix":5}},{"ty":0,"nm":"Rotation","mn":"ADBE FreePin3 PosPin Rotation","ix":6,"v":{"a":0,"k":0,"ix":6}}]}]},{"nm":"Overlap","np":1,"mn":"ADBE FreePin3 HghtPins","ix":6,"en":1,"ef":[]},{"nm":"Stiffness","np":1,"mn":"ADBE FreePin3 StarchPins","ix":7,"en":1,"ef":[]}]}]}]}]},{"ty":5,"nm":"B | 4 - 4","np":4,"mn":"Pseudo/DUIK bone linker","ix":2,"en":1,"ef":[{"ty":10,"nm":"Layer","mn":"Pseudo/DUIK bone linker-0001","ix":1,"v":{"a":0,"k":28,"ix":1}},{"ty":2,"nm":"Bone color","mn":"Pseudo/DUIK bone linker-0002","ix":2,"v":{"a":0,"k":[0.925490196078,0.094117647059,0.094117647059,1],"ix":2}}]},{"ty":5,"nm":"B | 3 - 4","np":4,"mn":"Pseudo/DUIK bone linker","ix":3,"en":1,"ef":[{"ty":10,"nm":"Layer","mn":"Pseudo/DUIK bone linker-0001","ix":1,"v":{"a":0,"k":29,"ix":1}},{"ty":2,"nm":"Bone color","mn":"Pseudo/DUIK bone linker-0002","ix":2,"v":{"a":0,"k":[0.925490196078,0.094117647059,0.094117647059,1],"ix":2}}]},{"ty":5,"nm":"B | 2 - 4","np":4,"mn":"Pseudo/DUIK bone linker","ix":4,"en":1,"ef":[{"ty":10,"nm":"Layer","mn":"Pseudo/DUIK bone linker-0001","ix":1,"v":{"a":0,"k":30,"ix":1}},{"ty":2,"nm":"Bone color","mn":"Pseudo/DUIK bone linker-0002","ix":2,"v":{"a":0,"k":[0.925490196078,0.094117647059,0.094117647059,1],"ix":2}}]},{"ty":5,"nm":"B | 1 - 4","np":4,"mn":"Pseudo/DUIK bone linker","ix":5,"en":1,"ef":[{"ty":10,"nm":"Layer","mn":"Pseudo/DUIK bone linker-0001","ix":1,"v":{"a":0,"k":31,"ix":1}},{"ty":2,"nm":"Bone color","mn":"Pseudo/DUIK bone linker-0002","ix":2,"v":{"a":0,"k":[0.925490196078,0.094117647059,0.094117647059,1],"ix":2}}]}],"shapes":[{"ty":"gr","it":[{"ind":0,"ty":"sh","ix":1,"ks":{"a":0,"k":{"i":[[0,0],[0,0],[0,0],[-10.202,0.485],[0.387,7.041],[5.616,4.031],[0,0],[0,0],[0,0]],"o":[[0,0],[0,0],[0,-7.773],[0,-5.694],[-0.379,-6.903],[0,0],[0,0],[0,0],[0,0]],"v":[[48.742,10.888],[39.025,57.174],[-25.106,57.174],[-7.13,39.199],[-7.93,25.728],[-17.417,8.437],[-88.41,-55.165],[-49,-57.174],[49,-54.174]],"c":true},"ix":2},"nm":"Path 1","mn":"ADBE Vector Shape - Group","hd":false},{"ty":"st","c":{"a":0,"k":[0.250999989229,0.161000001197,0.263000009574,1],"ix":3},"o":{"a":0,"k":100,"ix":4},"w":{"a":0,"k":8,"ix":5},"lc":2,"lj":2,"bm":0,"nm":"Stroke 1","mn":"ADBE Vector Graphic - Stroke","hd":false},{"ty":"fl","c":{"a":0,"k":[0.258999992819,0.231000010173,0.298000021542,1],"ix":4},"o":{"a":0,"k":100,"ix":5},"r":1,"bm":0,"nm":"Fill 1","mn":"ADBE Vector Graphic - Fill","hd":false},{"ty":"tr","p":{"a":0,"k":[69,77.174],"ix":2},"a":{"a":0,"k":[0,0],"ix":1},"s":{"a":0,"k":[100,100],"ix":3},"r":{"a":0,"k":0,"ix":6},"o":{"a":0,"k":100,"ix":7},"sk":{"a":0,"k":0,"ix":4},"sa":{"a":0,"k":0,"ix":5},"nm":"Transform"}],"nm":"Group 1","np":3,"cix":2,"bm":0,"ix":1,"mn":"ADBE Vector Group","hd":false}],"ip":0,"op":120.0000048877,"st":0,"bm":0}],"markers":[]}